Workbook
Name NativeTimeline_F._FIN: #N/A
Name SegmentaciónDeDatos_AÑO: #N/A
Name SegmentaciónDeDatos_MES: #N/A

Sheet Dashboard

Sheet TD 2024
AN1: Top 5
B2: Mes. | C2: Total | E2: Mes | F2: Total | H2: Genero. | I2: Total | K2: Genero | L2: Total | N2: N. Dias Incap. | O2: Ttal. | Q2: N. Dias Inc. | S2: Clase de Inc. | T2: Cuenta de CLASE DE INCAPACIDAD | V2: Clase Inc. | W2: Total | Y2: Tipo de Inc. | Z2: Total | AB2: Tipo de Inc. | AC2: Total | AE2: Entidad | AF2: Ttal. | AH2: Entidad | AI2: Total | AK2: Descrip. | AL2: Total | AN2: Descrip. | AO2: Total | AQ2: Total | AR2: Etiquetas de columna | BB2: Cargos | BC2: Total | BE2: =BB2 -> Cargos | BF2: Total | BH2: Empresa Usuaria. | BI2: Total | BK2: =BH2 -> Empresa Usuaria. | BL2: Total | BN2: Área o Dpto. | BO2: Total. | BQ2: =BN2 -> Área o Dpto. | BR2: Total | BW2: =BT2 -> 0 | BX2: Total
B3: ENERO | C3: 10 | E3: ENERO | F3: =_xlfn.IFNA(VLOOKUP(E3,$B$3:$C$14,2,FALSE),"0") -> 10 | H3: HOMBRE | I3: 10 | K3: HOMBRE | L3: =_xlfn.IFNA(VLOOKUP(K3,$H$3:$I$14,2,FALSE),"0") -> 10 | N3: 1 | O3: 6 | Q3: =SUM(O3:O33) -> 124 | S3: ARL | T3: 1 | V3: ARL | W3: =_xlfn.IFNA(VLOOKUP(V3,$S$3:$T$14,2,FALSE),"0") -> 1 | Y3: ENFERMENDAD GENERAL | Z3: 18 | AB3: ENFERMENDAD GENERAL | AC3: =_xlfn.IFNA(VLOOKUP(AB3,$Y$3:$Z$14,2,FALSE),"0") -> 18 | AE3: CAJACOPI | AF3: 3 | AH3: CAFESALUD | AI3: =_xlfn.IFNA(VLOOKUP(AH3,$AE$3:$AF$17,2,FALSE),"0") -> 0 | AK3: Amigdalitis aguda, no especificada | AL3: 1 | AN3: Amigdalitis aguda, no especificada | AO3: =_xlfn.IFNA(VLOOKUP(AN3,$AK$3:$AL$7,2,FALSE),"0") -> 1 | AQ3: Descrip. | AR3: HOMBRE | AS3: MUJER | AW3: Entidad | AX3: Hombre | AY3: Mujer | AZ3: Total | BB3: AUXILIAR DE BODEGA | BC3: 2 | BE3: AMA DE LLAVES | BF3: =_xlfn.IFNA(VLOOKUP(BE3,$BB$3:$BC$48,2,FALSE),"0") -> 0 | BH3: COMFAMILIAR ATLANTICO | BI3: 20 | BK3: COMFAMILIAR ATLANTICO | BL3: =_xlfn.IFNA(VLOOKUP(BK3,$BH$3:$BI$10,2,FALSE),"0") -> 20 | BN3: CENTRO DE PROCESAMIENTO | BO3: 1 | BQ3: 40 MIL EMPLEOS | BR3: =_xlfn.IFNA(VLOOKUP(BQ3,$BN$3:$BO$44,2,FALSE),"0") -> 0 | BW3: =BT3 -> 0 | BX3: =BU3 -> 0
B4: MARZO | C4: 5 | E4: MARZO | F4: =_xlfn.IFNA(VLOOKUP(E4,$B$3:$C$14,2,FALSE),"0") -> 5 | H4: MUJER | I4: 10 | K4: MUJER | L4: =_xlfn.IFNA(VLOOKUP(K4,$H$3:$I$14,2,FALSE),"0") -> 10 | N4: 2 | O4: 14 | S4: EPS | T4: 19 | V4: EPS | W4: =_xlfn.IFNA(VLOOKUP(V4,$S$3:$T$14,2,FALSE),"0") -> 19 | Y4: ACCIDENTE DE TRANSITO | Z4: 1 | AB4: LICENCIA DE LUTO | AC4: =_xlfn.IFNA(VLOOKUP(AB4,$Y$3:$Z$14,2,FALSE),"0") -> 0 | AE4: COOSALUD | AF4: 1 | AH4: CAJACOPI | AI4: =_xlfn.IFNA(VLOOKUP(AH4,$AE$3:$AF$17,2,FALSE),"0") -> 3 | AK4: Contusion de la rodilla | AL4: 1 | AN4: Cefalea | AO4: =_xlfn.IFNA(VLOOKUP(AN4,$AK$3:$AL$7,2,FALSE),"0") -> 0 | AQ4: Amigdalitis aguda, no especificada | AR4: 1 | AW4: Amigdalitis aguda, no especificada | AX4: =_xlfn.IFNA(VLOOKUP(AW4,$AQ$4:$AS$328,2,FALSE),"0") -> 1 | AY4: =_xlfn.IFNA(VLOOKUP(AW4,$AQ$4:$AS$328,3,FALSE),"0") -> 0 | AZ4: =SUM(AX4:AY4) -> 1 | BB4: AUXILIAR DE COCINA | BC4: 1 | BE4: ASESOR COMERCIAL | BF4: =_xlfn.IFNA(VLOOKUP(BE4,$BB$3:$BC$48,2,FALSE),"0") -> 0 | BK4: EDIFICIO TESTA ROSA | BL4: =_xlfn.IFNA(VLOOKUP(BK4,$BH$3:$BI$10,2,FALSE),"0") -> 0 | BN4: CENTRO RECREACIONAL CLL 48 | BO4: 4 | BQ4: ASEO | BR4: =_xlfn.IFNA(VLOOKUP(BQ4,$BN$3:$BO$44,2,FALSE),"0") -> 0 | BW4: =BT4 -> 0 | BX4: =BU4 -> 0
B5: FEBRERO | C5: 5 | E5: ABRIL | F5: =_xlfn.IFNA(VLOOKUP(E5,$B$3:$C$14,2,FALSE),"0") -> 0 | K5: HOMBRE | L5: =L3/F15 -> 0.66666667 | M5: =1-L5 -> 0.33333333 | N5: 4 | O5: 4 | V5: =S5 -> 0 | W5: =_xlfn.IFNA(VLOOKUP(V5,$S$3:$T$14,2,FALSE),"0") -> 0 | Y5: ACCIDENTE LABORAL | Z5: 1 | AB5: LICENCIA DE MATERNIDAD | AC5: =_xlfn.IFNA(VLOOKUP(AB5,$Y$3:$Z$14,2,FALSE),"0") -> 0 | AE5: E.P.S SANITAS | AF5: 1 | AH5: COOMEVA | AI5: =_xlfn.IFNA(VLOOKUP(AH5,$AE$3:$AF$17,2,FALSE),"0") -> 0 | AK5: Otros dolores abdominales y los no especificados | AL5: 1 | AN5: Colico renal, no especificado | AO5: =_xlfn.IFNA(VLOOKUP(AN5,$AK$3:$AL$7,2,FALSE),"0") -> 0 | AQ5: Contusion de la rodilla | AS5: 1 | AW5: Cefalea | AX5: =_xlfn.IFNA(VLOOKUP(AW5,$AQ$4:$AS$328,2,FALSE),"0") -> 0 | AY5: =_xlfn.IFNA(VLOOKUP(AW5,$AQ$4:$AS$328,3,FALSE),"0") -> 0 | AZ5: =SUM(AX5:AY5) -> 0 | BB5: AYUDANTE COCINA | BC5: 6 | BE5: AUX GESTION DOCUMENTAL | BF5: =_xlfn.IFNA(VLOOKUP(BE5,$BB$3:$BC$48,2,FALSE),"0") -> 0 | BK5: MARTA LUCIA YEPES R. | BL5: =_xlfn.IFNA(VLOOKUP(BK5,$BH$3:$BI$10,2,FALSE),"0") -> 0 | BN5: CENTRO RECREACIONAL TURIPANA | BO5: 7 | BQ5: C. ATENCION C.48 | BR5: =_xlfn.IFNA(VLOOKUP(BQ5,$BN$3:$BO$44,2,FALSE),"0") -> 0 | BW5: =BT5 -> 0 | BX5: =BU5 -> 0
E6: MAYO | F6: =_xlfn.IFNA(VLOOKUP(E6,$B$3:$C$14,2,FALSE),"0") -> 0 | K6: MUJER | L6: =L4/F15 -> 0.66666667 | M6: =1-L6 -> 0.33333333 | N6: 7 | O6: 14 | AB6: LICENCIA DE PATERNIDAD | AC6: =_xlfn.IFNA(VLOOKUP(AB6,$Y$3:$Z$14,2,FALSE),"0") -> 0 | AE6: EPS/SURA | AF6: 2 | AH6: COOSALUD | AI6: =_xlfn.IFNA(VLOOKUP(AH6,$AE$3:$AF$17,2,FALSE),"0") -> 1 | AK6: Otras colitis y gastroenteritis no infecciosas especificadas | AL6: 2 | AN6: Contusion de la rodilla | AO6: =_xlfn.IFNA(VLOOKUP(AN6,$AK$3:$AL$7,2,FALSE),"0") -> 1 | AQ6: Otros dolores abdominales y los no especificados | AS6: 1 | AW6: Colico renal, no especificado | AX6: =_xlfn.IFNA(VLOOKUP(AW6,$AQ$4:$AS$328,2,FALSE),"0") -> 0 | AY6: =_xlfn.IFNA(VLOOKUP(AW6,$AQ$4:$AS$328,3,FALSE),"0") -> 0 | AZ6: =SUM(AX6:AY6) -> 0 | BB6: CHEF | BC6: 1 | BE6: AUX.INTERMEDIACION LABORAL | BF6: =_xlfn.IFNA(VLOOKUP(BE6,$BB$3:$BC$48,2,FALSE),"0") -> 0 | BK6: No Existe | BL6: =_xlfn.IFNA(VLOOKUP(BK6,$BH$3:$BI$10,2,FALSE),"0") -> 0 | BN6: SEDE CARIBE | BO6: 1 | BQ6: C. ATENCION VIA 40 | BR6: =_xlfn.IFNA(VLOOKUP(BQ6,$BN$3:$BO$44,2,FALSE),"0") -> 0 | BW6: =BT6 -> 0 | BX6: =BU6 -> 0
E7: JUNIO | F7: =_xlfn.IFNA(VLOOKUP(E7,$B$3:$C$14,2,FALSE),"0") -> 0 | N7: 15 | O7: 15 | AB7: ACCIDENTE DE TRANSITO | AC7: =_xlfn.IFNA(VLOOKUP(AB7,$Y$3:$Z$14,2,FALSE),"0") -> 1 | AE7: FAMISANAR | AF7: 3 | AH7: E.P.S SANITAS | AI7: =_xlfn.IFNA(VLOOKUP(AH7,$AE$3:$AF$17,2,FALSE),"0") -> 1 | AK7: Migrana con aura [migrana clasica] | AL7: 2 | AN7: Dengue sin signos de alarma | AO7: =_xlfn.IFNA(VLOOKUP(AN7,$AK$3:$AL$7,2,FALSE),"0") -> 0 | AQ7: Otras colitis y gastroenteritis no infecciosas especificadas | AS7: 2 | AW7: Contusion de la rodilla | AX7: =_xlfn.IFNA(VLOOKUP(AW7,$AQ$4:$AS$328,2,FALSE),"0") -> 0 | AY7: =_xlfn.IFNA(VLOOKUP(AW7,$AQ$4:$AS$328,3,FALSE),"0") -> 1 | AZ7: =SUM(AX7:AY7) -> 1 | BB7: COCINERO 1 | BC7: 3 | BE7: AUXILIAR | BF7: =_xlfn.IFNA(VLOOKUP(BE7,$BB$3:$BC$48,2,FALSE),"0") -> 0 | BK7: PLASDIBAR LTDA | BL7: =_xlfn.IFNA(VLOOKUP(BK7,$BH$3:$BI$10,2,FALSE),"0") -> 0 | BN7: SEDE CARIBE MERCADEO | BO7: 4 | BQ7: C.A. VIVA QUILLA | BR7: =_xlfn.IFNA(VLOOKUP(BQ7,$BN$3:$BO$44,2,FALSE),"0") -> 0 | BW7: =BT7 -> 0 | BX7: =BU7 -> 0
E8: JULIO | F8: =_xlfn.IFNA(VLOOKUP(E8,$B$3:$C$14,2,FALSE),"0") -> 0 | N8: 16 | O8: 16 | AB8: ACCIDENTE LABORAL | AC8: =_xlfn.IFNA(VLOOKUP(AB8,$Y$3:$Z$14,2,FALSE),"0") -> 1 | AE8: MUTUALSER | AF8: 1 | AH8: EPS/SURA | AI8: =_xlfn.IFNA(VLOOKUP(AH8,$AE$3:$AF$17,2,FALSE),"0") -> 2 | AK8: Dolor en el pecho, no especificado | AL8: 1 | AN8: Dientes incluidos | AO8: =_xlfn.IFNA(VLOOKUP(AN8,$AK$3:$AL$7,2,FALSE),"0") -> 0 | AQ8: Migrana con aura [migrana clasica] | AS8: 2 | AW8: Dengue sin signos de alarma | AX8: =_xlfn.IFNA(VLOOKUP(AW8,$AQ$4:$AS$328,2,FALSE),"0") -> 0 | AY8: =_xlfn.IFNA(VLOOKUP(AW8,$AQ$4:$AS$328,3,FALSE),"0") -> 0 | AZ8: =SUM(AX8:AY8) -> 0 | BB8: STEWARD | BC8: 1 | BE8: AUXILIAR CAPACITACION | BF8: =_xlfn.IFNA(VLOOKUP(BE8,$BB$3:$BC$48,2,FALSE),"0") -> 0 | BK8: TEMPOACTIVA EST S.A.S. | BL8: =_xlfn.IFNA(VLOOKUP(BK8,$BH$3:$BI$10,2,FALSE),"0") -> 0 | BN8: SEDE NORTE MERCADEO | BO8: 2 | BQ8: C.ATENCION C.82 | BR8: =_xlfn.IFNA(VLOOKUP(BQ8,$BN$3:$BO$44,2,FALSE),"0") -> 0 | BW8: =BT8 -> 0 | BX8: =BU8 -> 0
E9: AGOSTO | F9: =_xlfn.IFNA(VLOOKUP(E9,$B$3:$C$14,2,FALSE),"0") -> 0 | N9: 24 | O9: 24 | AB9: =Y9 -> 0 | AC9: =_xlfn.IFNA(VLOOKUP(AB9,$Y$3:$Z$14,2,FALSE),"0") -> 0 | AE9: NUEVA E.P.S. | AF9: 6 | AH9: FAMISANAR | AI9: =_xlfn.IFNA(VLOOKUP(AH9,$AE$3:$AF$17,2,FALSE),"0") -> 3 | AK9: Otros sindromes de cefalea especificados | AL9: 1 | AN9: Dolor abdominal localizado en parte superior | AO9: =_xlfn.IFNA(VLOOKUP(AN9,$AK$3:$AL$7,2,FALSE),"0") -> 0 | AQ9: Dolor en el pecho, no especificado | AR9: 1 | AW9: Dientes incluidos | AX9: =_xlfn.IFNA(VLOOKUP(AW9,$AQ$4:$AS$328,2,FALSE),"0") -> 0 | AY9: =_xlfn.IFNA(VLOOKUP(AW9,$AQ$4:$AS$328,3,FALSE),"0") -> 0 | AZ9: =SUM(AX9:AY9) -> 0 | BB9: SUPERNUMERARIO(A) | BC9: 6 | BE9: AUXILIAR DE ARCHIVO | BF9: =_xlfn.IFNA(VLOOKUP(BE9,$BB$3:$BC$48,2,FALSE),"0") -> 0 | BN9: TURIPANA MERCADEO | BO9: 1 | BQ9: C.ATENCION. C.76 | BR9: =_xlfn.IFNA(VLOOKUP(BQ9,$BN$3:$BO$44,2,FALSE),"0") -> 0 | BW9: =BT9 -> 0 | BX9: =BU9 -> 0
E10: SEPTIEMBRE | F10: =_xlfn.IFNA(VLOOKUP(E10,$B$3:$C$14,2,FALSE),"0") -> 0 | N10: 31 | O10: 31 | AE10: SALUD TOTAL | AF10: 3 | AH10: MEDIMAS | AI10: =_xlfn.IFNA(VLOOKUP(AH10,$AE$3:$AF$17,2,FALSE),"0") -> 0 | AK10: Dorsalgia, no especificada | AL10: 1 | AN10: Esguinces y torceduras del tobillo | AO10: =_xlfn.IFNA(VLOOKUP(AN10,$AK$3:$AL$7,2,FALSE),"0") -> 0 | AQ10: Otros sindromes de cefalea especificados | AR10: 1 | AW10: Dolor abdominal localizado en parte superior | AX10: =_xlfn.IFNA(VLOOKUP(AW10,$AQ$4:$AS$328,2,FALSE),"0") -> 0 | AY10: =_xlfn.IFNA(VLOOKUP(AW10,$AQ$4:$AS$328,3,FALSE),"0") -> 0 | AZ10: =SUM(AX10:AY10) -> 0 | BE10: AUXILIAR DE BAR | BF10: =_xlfn.IFNA(VLOOKUP(BE10,$BB$3:$BC$48,2,FALSE),"0") -> 0 | BQ10: C.R.U | BR10: =_xlfn.IFNA(VLOOKUP(BQ10,$BN$3:$BO$44,2,FALSE),"0") -> 0 | BW10: =BT10 -> 0 | BX10: =BU10 -> 0
E11: FEBRERO | F11: =_xlfn.IFNA(VLOOKUP(E11,$B$3:$C$14,2,FALSE),"0") -> 0 | AH11: MUTUALSER | AI11: =_xlfn.IFNA(VLOOKUP(AH11,$AE$3:$AF$17,2,FALSE),"0") -> 1 | AK11: Otros estados postquirurgicos especificados | AL11: 1 | AN11: Esguinces y torceduras que comprometen el ligamento cruzado (anterior) (posterior) de la rodilla | AO11: =_xlfn.IFNA(VLOOKUP(AN11,$AK$3:$AL$7,2,FALSE),"0") -> 0 | AQ11: Dorsalgia, no especificada | AR11: 1 | AW11: Esguinces y torceduras del tobillo | AX11: =_xlfn.IFNA(VLOOKUP(AW11,$AQ$4:$AS$328,2,FALSE),"0") -> 0 | AY11: =_xlfn.IFNA(VLOOKUP(AW11,$AQ$4:$AS$328,3,FALSE),"0") -> 0 | AZ11: =SUM(AX11:AY11) -> 0 | BE11: AUXILIAR DE BODEGA | BF11: =_xlfn.IFNA(VLOOKUP(BE11,$BB$3:$BC$48,2,FALSE),"0") -> 2 | BQ11: CENTRO DE ATENCION PIMSAS | BR11: =_xlfn.IFNA(VLOOKUP(BQ11,$BN$3:$BO$44,2,FALSE),"0") -> 0 | BW11: =BT11 -> 0 | BX11: =BU11 -> 0
E12: OCTUBRE | F12: =_xlfn.IFNA(VLOOKUP(E12,$B$3:$C$14,2,FALSE),"0") -> 0 | AH12: CONSORCIO SAYP | AI12: =_xlfn.IFNA(VLOOKUP(AH12,$AE$3:$AF$17,2,FALSE),"0") -> 0 | AK12: Fractura de otros huesos metacarpianos | AL12: 1 | AN12: Fiebre, no especificada | AO12: =_xlfn.IFNA(VLOOKUP(AN12,$AK$3:$AL$7,2,FALSE),"0") -> 0 | AQ12: Otros estados postquirurgicos especificados | AR12: 1 | AW12: Esguinces y torceduras que comprometen el ligamento cruzado (anterior) (posterior) de la rodilla | AX12: =_xlfn.IFNA(VLOOKUP(AW12,$AQ$4:$AS$328,2,FALSE),"0") -> 0 | AY12: =_xlfn.IFNA(VLOOKUP(AW12,$AQ$4:$AS$328,3,FALSE),"0") -> 0 | AZ12: =SUM(AX12:AY12) -> 0 | BE12: AUXILIAR DE COBRANZAS | BF12: =_xlfn.IFNA(VLOOKUP(BE12,$BB$3:$BC$48,2,FALSE),"0") -> 0 | BQ12: CENTRO DE PROCESAMIENTO | BR12: =_xlfn.IFNA(VLOOKUP(BQ12,$BN$3:$BO$44,2,FALSE),"0") -> 1 | BW12: =BT12 -> 0 | BX12: =BU12 -> 0
E13: NOVIEMBRE | F13: =_xlfn.IFNA(VLOOKUP(E13,$B$3:$C$14,2,FALSE),"0") -> 0 | AH13: NUEVA E.P.S. | AI13: =_xlfn.IFNA(VLOOKUP(AH13,$AE$3:$AF$17,2,FALSE),"0") -> 6 | AK13: Hernia inguinal unilateral o no especificada, sin obstruccion ni gangrena | AL13: 1 | AN13: Herida de dedo(s) de la mano, con dano de la(s) una(s) | AO13: =_xlfn.IFNA(VLOOKUP(AN13,$AK$3:$AL$7,2,FALSE),"0") -> 0 | AQ13: Fractura de otros huesos metacarpianos | AR13: 1 | AW13: Fiebre, no especificada | AX13: =_xlfn.IFNA(VLOOKUP(AW13,$AQ$4:$AS$328,2,FALSE),"0") -> 0 | AY13: =_xlfn.IFNA(VLOOKUP(AW13,$AQ$4:$AS$328,3,FALSE),"0") -> 0 | AZ13: =SUM(AX13:AY13) -> 0 | BE13: AUXILIAR DE COCINA | BF13: =_xlfn.IFNA(VLOOKUP(BE13,$BB$3:$BC$48,2,FALSE),"0") -> 1 | BQ13: CENTRO NIÑEZ | BR13: =_xlfn.IFNA(VLOOKUP(BQ13,$BN$3:$BO$44,2,FALSE),"0") -> 0 | BW13: =BT13 -> 0 | BX13: =BU13 -> 0
E14: DICIEMBRE | F14: =_xlfn.IFNA(VLOOKUP(E14,$B$3:$C$14,2,FALSE),"0") -> 0 | AH14: SALUD TOTAL | AI14: =_xlfn.IFNA(VLOOKUP(AH14,$AE$3:$AF$17,2,FALSE),"0") -> 3 | AK14: Fractura de hueso del metatarso | AL14: 1 | AN14: Herida de la muneca y de la mano, parte no especificada | AO14: =_xlfn.IFNA(VLOOKUP(AN14,$AK$3:$AL$7,2,FALSE),"0") -> 0 | AQ14: Hernia inguinal unilateral o no especificada, sin obstruccion ni gangrena | AS14: 1 | AW14: Herida de dedo(s) de la mano, con dano de la(s) una(s) | AX14: =_xlfn.IFNA(VLOOKUP(AW14,$AQ$4:$AS$328,2,FALSE),"0") -> 0 | AY14: =_xlfn.IFNA(VLOOKUP(AW14,$AQ$4:$AS$328,3,FALSE),"0") -> 0 | AZ14: =SUM(AX14:AY14) -> 0 | BE14: AUXILIAR DE PANADERIA | BF14: =_xlfn.IFNA(VLOOKUP(BE14,$BB$3:$BC$48,2,FALSE),"0") -> 0 | BQ14: CENTRO RECREACIONAL CLL 48 | BR14: =_xlfn.IFNA(VLOOKUP(BQ14,$BN$3:$BO$44,2,FALSE),"0") -> 4 | BW14: =BT14 -> 0 | BX14: =BU14 -> 0
E15: Total | F15: =SUM(F3:F14) -> 15 | AH15: SALUDVIDA E.P.S. | AI15: =_xlfn.IFNA(VLOOKUP(AH15,$AE$3:$AF$17,2,FALSE),"0") -> 0 | AK15: Contusion del hombro y del brazo | AL15: 1 | AN15: Herida de otras partes de la cabeza | AO15: =_xlfn.IFNA(VLOOKUP(AN15,$AK$3:$AL$7,2,FALSE),"0") -> 0 | AQ15: Fractura de hueso del metatarso | AR15: 1 | AW15: Herida de la muneca y de la mano, parte no especificada | AX15: =_xlfn.IFNA(VLOOKUP(AW15,$AQ$4:$AS$328,2,FALSE),"0") -> 0 | AY15: =_xlfn.IFNA(VLOOKUP(AW15,$AQ$4:$AS$328,3,FALSE),"0") -> 0 | AZ15: =SUM(AX15:AY15) -> 0 | BE15: AUXILIAR DE PRIMEROS AUXILIOS | BF15: =_xlfn.IFNA(VLOOKUP(BE15,$BB$3:$BC$48,2,FALSE),"0") -> 0 | BQ15: CENTRO RECREACIONAL TURIPANA | BR15: =_xlfn.IFNA(VLOOKUP(BQ15,$BN$3:$BO$44,2,FALSE),"0") -> 7 | BW15: =BT15 -> 0 | BX15: =BU15 -> 0
AH16: COLMENA | AI16: =_xlfn.IFNA(VLOOKUP(AH16,$AE$3:$AF$17,2,FALSE),"0") -> 0 | AK16: No especificado | AL16: 1 | AN16: Herida de otras partes de la muneca y de la mano | AO16: =_xlfn.IFNA(VLOOKUP(AN16,$AK$3:$AL$7,2,FALSE),"0") -> 0 | AQ16: Contusion del hombro y del brazo | AR16: 1 | AW16: Herida de otras partes de la cabeza | AX16: =_xlfn.IFNA(VLOOKUP(AW16,$AQ$4:$AS$328,2,FALSE),"0") -> 0 | AY16: =_xlfn.IFNA(VLOOKUP(AW16,$AQ$4:$AS$328,3,FALSE),"0") -> 0 | AZ16: =SUM(AX16:AY16) -> 0 | BE16: AUXILIAR DE SERVICIOS | BF16: =_xlfn.IFNA(VLOOKUP(BE16,$BB$3:$BC$48,2,FALSE),"0") -> 0 | BQ16: CLUB SOCIAL | BR16: =_xlfn.IFNA(VLOOKUP(BQ16,$BN$3:$BO$44,2,FALSE),"0") -> 0 | BW16: =BT16 -> 0 | BX16: =BU16 -> 0
AH17: EMPRESA | AI17: =_xlfn.IFNA(VLOOKUP(AH17,$AE$3:$AF$17,2,FALSE),"0") -> 0 | AK17: Fractura de la clavicula | AL17: 1 | AN17: Infarto agudo del miocardio, sin otra especificacion | AO17: =_xlfn.IFNA(VLOOKUP(AN17,$AK$3:$AL$7,2,FALSE),"0") -> 0 | AQ17: No especificado | AS17: 1 | AW17: Herida de otras partes de la muneca y de la mano | AX17: =_xlfn.IFNA(VLOOKUP(AW17,$AQ$4:$AS$328,2,FALSE),"0") -> 0 | AY17: =_xlfn.IFNA(VLOOKUP(AW17,$AQ$4:$AS$328,3,FALSE),"0") -> 0 | AZ17: =SUM(AX17:AY17) -> 0 | BE17: AUXILIAR DE SISTEMAS | BF17: =_xlfn.IFNA(VLOOKUP(BE17,$BB$3:$BC$48,2,FALSE),"0") -> 0 | BK17: Total | BL17: =SUM(BL3:BL16) -> 20 | BQ17: CONTRATO I.C.B.F | BR17: =_xlfn.IFNA(VLOOKUP(BQ17,$BN$3:$BO$44,2,FALSE),"0") -> 0 | BW17: =BT17 -> 0 | BX17: =BU17 -> 0
AI18: =_xlfn.IFNA(VLOOKUP(AH18,$AE$3:$AF$17,2,FALSE),"0") -> 0 | AK18: Urticaria alergica | AL18: 2 | AN18: Infeccion aguda de las vias respiratorias superiores, no especificada | AO18: =_xlfn.IFNA(VLOOKUP(AN18,$AK$3:$AL$7,2,FALSE),"0") -> 0 | AQ18: Fractura de la clavicula | AR18: 1 | AW18: Infarto agudo del miocardio, sin otra especificacion | AX18: =_xlfn.IFNA(VLOOKUP(AW18,$AQ$4:$AS$328,2,FALSE),"0") -> 0 | AY18: =_xlfn.IFNA(VLOOKUP(AW18,$AQ$4:$AS$328,3,FALSE),"0") -> 0 | AZ18: =SUM(AX18:AY18) -> 0 | BE18: AUXILIAR NOMINA | BF18: =_xlfn.IFNA(VLOOKUP(BE18,$BB$3:$BC$48,2,FALSE),"0") -> 0 | BQ18: CRU MERCADEO | BR18: =_xlfn.IFNA(VLOOKUP(BQ18,$BN$3:$BO$44,2,FALSE),"0") -> 0 | BW18: =BT18 -> 0 | BX18: =BU18 -> 0
AK19: Fractura de la diafisis de la tibia | AL19: 1 | AN19: Infeccion aguda no especificada de las vias respiratorias inferiores | AO19: =_xlfn.IFNA(VLOOKUP(AN19,$AK$3:$AL$7,2,FALSE),"0") -> 0 | AQ19: Urticaria alergica | AS19: 2 | AW19: Infeccion aguda de las vias respiratorias superiores, no especificada | AX19: =_xlfn.IFNA(VLOOKUP(AW19,$AQ$4:$AS$328,2,FALSE),"0") -> 0 | AY19: =_xlfn.IFNA(VLOOKUP(AW19,$AQ$4:$AS$328,3,FALSE),"0") -> 0 | AZ19: =SUM(AX19:AY19) -> 0 | BE19: AYUDANTE | BF19: =_xlfn.IFNA(VLOOKUP(BE19,$BB$3:$BC$48,2,FALSE),"0") -> 0 | BQ19: DIRECCION RECREACION | BR19: =_xlfn.IFNA(VLOOKUP(BQ19,$BN$3:$BO$44,2,FALSE),"0") -> 0 | BW19: =BT19 -> 0 | BX19: =BU19 -> 0
AN20: Infeccion de vias urinarias, sitio no especificado | AO20: =_xlfn.IFNA(VLOOKUP(AN20,$AK$3:$AL$7,2,FALSE),"0") -> 0 | AQ20: Fractura de la diafisis de la tibia | AR20: 1 | AW20: Infeccion aguda no especificada de las vias respiratorias inferiores | AX20: =_xlfn.IFNA(VLOOKUP(AW20,$AQ$4:$AS$328,2,FALSE),"0") -> 0 | AY20: =_xlfn.IFNA(VLOOKUP(AW20,$AQ$4:$AS$328,3,FALSE),"0") -> 0 | AZ20: =SUM(AX20:AY20) -> 0 | BE20: AYUDANTE COCINA | BF20: =_xlfn.IFNA(VLOOKUP(BE20,$BB$3:$BC$48,2,FALSE),"0") -> 6 | BQ20: DPTO DE CONSTRUCCION | BR20: =_xlfn.IFNA(VLOOKUP(BQ20,$BN$3:$BO$44,2,FALSE),"0") -> 0 | BW20: =BT20 -> 0 | BX20: =BU20 -> 0
AN21: Infeccion intestinal viral, sin otra especificacion | AO21: =_xlfn.IFNA(VLOOKUP(AN21,$AK$3:$AL$7,2,FALSE),"0") -> 0 | AW21: Infeccion de vias urinarias, sitio no especificado | AX21: =_xlfn.IFNA(VLOOKUP(AW21,$AQ$4:$AS$328,2,FALSE),"0") -> 0 | AY21: =_xlfn.IFNA(VLOOKUP(AW21,$AQ$4:$AS$328,3,FALSE),"0") -> 0 | AZ21: =SUM(AX21:AY21) -> 0 | BE21: AYUDANTE MANTENIMIENTO | BF21: =_xlfn.IFNA(VLOOKUP(BE21,$BB$3:$BC$48,2,FALSE),"0") -> 0 | BQ21: EDIFICIO TESTA ROSA | BR21: =_xlfn.IFNA(VLOOKUP(BQ21,$BN$3:$BO$44,2,FALSE),"0") -> 0 | BW21: =BT21 -> 0 | BX21: =BU21 -> 0
AN22: Infeccion viral, no especificada | AO22: =_xlfn.IFNA(VLOOKUP(AN22,$AK$3:$AL$7,2,FALSE),"0") -> 0 | AW22: Infeccion intestinal viral, sin otra especificacion | AX22: =_xlfn.IFNA(VLOOKUP(AW22,$AQ$4:$AS$328,2,FALSE),"0") -> 0 | AY22: =_xlfn.IFNA(VLOOKUP(AW22,$AQ$4:$AS$328,3,FALSE),"0") -> 0 | AZ22: =SUM(AX22:AY22) -> 0 | BE22: BARMAN | BF22: =_xlfn.IFNA(VLOOKUP(BE22,$BB$3:$BC$48,2,FALSE),"0") -> 0 | BQ22: MANTENIMIENTO TECNICO | BR22: =_xlfn.IFNA(VLOOKUP(BQ22,$BN$3:$BO$44,2,FALSE),"0") -> 0 | BW22: =BT22 -> 0 | BX22: =BU22 -> 0
AN23: Iridociclitis aguda y subaguda | AO23: =_xlfn.IFNA(VLOOKUP(AN23,$AK$3:$AL$7,2,FALSE),"0") -> 0 | AW23: Infeccion viral, no especificada | AX23: =_xlfn.IFNA(VLOOKUP(AW23,$AQ$4:$AS$328,2,FALSE),"0") -> 0 | AY23: =_xlfn.IFNA(VLOOKUP(AW23,$AQ$4:$AS$328,3,FALSE),"0") -> 0 | AZ23: =SUM(AX23:AY23) -> 0 | BE23: CAJERO(A) | BF23: =_xlfn.IFNA(VLOOKUP(BE23,$BB$3:$BC$48,2,FALSE),"0") -> 0 | BQ23: MARTHA L. YEPES | BR23: =_xlfn.IFNA(VLOOKUP(BQ23,$BN$3:$BO$44,2,FALSE),"0") -> 0 | BW23: =BT23 -> 0 | BX23: =BU23 -> 0
AN24: Laringofaringitis aguda | AO24: =_xlfn.IFNA(VLOOKUP(AN24,$AK$3:$AL$7,2,FALSE),"0") -> 0 | AW24: Iridociclitis aguda y subaguda | AX24: =_xlfn.IFNA(VLOOKUP(AW24,$AQ$4:$AS$328,2,FALSE),"0") -> 0 | AY24: =_xlfn.IFNA(VLOOKUP(AW24,$AQ$4:$AS$328,3,FALSE),"0") -> 0 | AZ24: =SUM(AX24:AY24) -> 0 | BE24: CHEF | BF24: =_xlfn.IFNA(VLOOKUP(BE24,$BB$3:$BC$48,2,FALSE),"0") -> 1 | BQ24: No Existe | BR24: =_xlfn.IFNA(VLOOKUP(BQ24,$BN$3:$BO$44,2,FALSE),"0") -> 0 | BW24: =BT24 -> 0 | BX24: =BU24 -> 0
AN25: Mareo y desvanecimiento | AO25: =_xlfn.IFNA(VLOOKUP(AN25,$AK$3:$AL$7,2,FALSE),"0") -> 0 | AW25: Laringofaringitis aguda | AX25: =_xlfn.IFNA(VLOOKUP(AW25,$AQ$4:$AS$328,2,FALSE),"0") -> 0 | AY25: =_xlfn.IFNA(VLOOKUP(AW25,$AQ$4:$AS$328,3,FALSE),"0") -> 0 | AZ25: =SUM(AX25:AY25) -> 0 | BE25: COCINERO 1 | BF25: =_xlfn.IFNA(VLOOKUP(BE25,$BB$3:$BC$48,2,FALSE),"0") -> 3 | BQ25: PLANEACION | BR25: =_xlfn.IFNA(VLOOKUP(BQ25,$BN$3:$BO$44,2,FALSE),"0") -> 0 | BW25: =BT25 -> 0 | BX25: =BU25 -> 0
AN26: Otras enteritis virales | AO26: =_xlfn.IFNA(VLOOKUP(AN26,$AK$3:$AL$7,2,FALSE),"0") -> 0 | AW26: Mareo y desvanecimiento | AX26: =_xlfn.IFNA(VLOOKUP(AW26,$AQ$4:$AS$328,2,FALSE),"0") -> 0 | AY26: =_xlfn.IFNA(VLOOKUP(AW26,$AQ$4:$AS$328,3,FALSE),"0") -> 0 | AZ26: =SUM(AX26:AY26) -> 0 | BE26: COLABORADOR | BF26: =_xlfn.IFNA(VLOOKUP(BE26,$BB$3:$BC$48,2,FALSE),"0") -> 0 | BQ26: PLASDIBAR LTDA | BR26: =_xlfn.IFNA(VLOOKUP(BQ26,$BN$3:$BO$44,2,FALSE),"0") -> 0 | BW26: =BT26 -> 0 | BX26: =BU26 -> 0
AN27: Otras infecciones agudas de sitios multiples de las vias respiratorias superiores | AO27: =_xlfn.IFNA(VLOOKUP(AN27,$AK$3:$AL$7,2,FALSE),"0") -> 0 | AW27: Otras enteritis virales | AX27: =_xlfn.IFNA(VLOOKUP(AW27,$AQ$4:$AS$328,2,FALSE),"0") -> 0 | AY27: =_xlfn.IFNA(VLOOKUP(AW27,$AQ$4:$AS$328,3,FALSE),"0") -> 0 | AZ27: =SUM(AX27:AY27) -> 0 | BE27: COORDINADOR | BF27: =_xlfn.IFNA(VLOOKUP(BE27,$BB$3:$BC$48,2,FALSE),"0") -> 0 | BQ27: PROGRAMAS RECREATIVOS | BR27: =_xlfn.IFNA(VLOOKUP(BQ27,$BN$3:$BO$44,2,FALSE),"0") -> 0 | BW27: =BT27 -> 0 | BX27: =BU27 -> 0
AN28: Otros tipos de neumotorax espontaneo | AO28: =_xlfn.IFNA(VLOOKUP(AN28,$AK$3:$AL$7,2,FALSE),"0") -> 0 | AW28: Otras infecciones agudas de sitios multiples de las vias respiratorias superiores | AX28: =_xlfn.IFNA(VLOOKUP(AW28,$AQ$4:$AS$328,2,FALSE),"0") -> 0 | AY28: =_xlfn.IFNA(VLOOKUP(AW28,$AQ$4:$AS$328,3,FALSE),"0") -> 0 | AZ28: =SUM(AX28:AY28) -> 0 | BE28: EMPACADOR | BF28: =_xlfn.IFNA(VLOOKUP(BE28,$BB$3:$BC$48,2,FALSE),"0") -> 0 | BQ28: PROMOCION Y COMUNICACIONES | BR28: =_xlfn.IFNA(VLOOKUP(BQ28,$BN$3:$BO$44,2,FALSE),"0") -> 0 | BW28: =BT28 -> 0 | BX28: =BU28 -> 0
AN29: Parto por cesarea de emergencia | AO29: =_xlfn.IFNA(VLOOKUP(AN29,$AK$3:$AL$7,2,FALSE),"0") -> 0 | AW29: Otros tipos de neumotorax espontaneo | AX29: =_xlfn.IFNA(VLOOKUP(AW29,$AQ$4:$AS$328,2,FALSE),"0") -> 0 | AY29: =_xlfn.IFNA(VLOOKUP(AW29,$AQ$4:$AS$328,3,FALSE),"0") -> 0 | AZ29: =SUM(AX29:AY29) -> 0 | BE29: INSTRUCTOR | BF29: =_xlfn.IFNA(VLOOKUP(BE29,$BB$3:$BC$48,2,FALSE),"0") -> 0 | BQ29: RECREACION Y TURISMO | BR29: =_xlfn.IFNA(VLOOKUP(BQ29,$BN$3:$BO$44,2,FALSE),"0") -> 0 | BW29: =BT29 -> 0 | BX29: =BU29 -> 0
AN30: Parto por cesarea, sin otra especificacion | AO30: =_xlfn.IFNA(VLOOKUP(AN30,$AK$3:$AL$7,2,FALSE),"0") -> 0 | AW30: Parto por cesarea de emergencia | AX30: =_xlfn.IFNA(VLOOKUP(AW30,$AQ$4:$AS$328,2,FALSE),"0") -> 0 | AY30: =_xlfn.IFNA(VLOOKUP(AW30,$AQ$4:$AS$328,3,FALSE),"0") -> 0 | AZ30: =SUM(AX30:AY30) -> 0 | BE30: MAITRE | BF30: =_xlfn.IFNA(VLOOKUP(BE30,$BB$3:$BC$48,2,FALSE),"0") -> 0 | BQ30: SALGARITO | BR30: =_xlfn.IFNA(VLOOKUP(BQ30,$BN$3:$BO$44,2,FALSE),"0") -> 0 | BW30: =BT30 -> 0 | BX30: =BU30 -> 0
AN31: Periodontitis cronica | AO31: =_xlfn.IFNA(VLOOKUP(AN31,$AK$3:$AL$7,2,FALSE),"0") -> 0 | AW31: Parto por cesarea, sin otra especificacion | AX31: =_xlfn.IFNA(VLOOKUP(AW31,$AQ$4:$AS$328,2,FALSE),"0") -> 0 | AY31: =_xlfn.IFNA(VLOOKUP(AW31,$AQ$4:$AS$328,3,FALSE),"0") -> 0 | AZ31: =SUM(AX31:AY31) -> 0 | BE31: MANIPULADOR DE ALIMENTOS | BF31: =_xlfn.IFNA(VLOOKUP(BE31,$BB$3:$BC$48,2,FALSE),"0") -> 0 | BQ31: SALGARITO MERCADEO | BR31: =_xlfn.IFNA(VLOOKUP(BQ31,$BN$3:$BO$44,2,FALSE),"0") -> 0 | BW31: =BT31 -> 0 | BX31: =BU31 -> 0
AN32: Pulpitis | AO32: =_xlfn.IFNA(VLOOKUP(AN32,$AK$3:$AL$7,2,FALSE),"0") -> 0 | AW32: Periodontitis cronica | AX32: =_xlfn.IFNA(VLOOKUP(AW32,$AQ$4:$AS$328,2,FALSE),"0") -> 0 | AY32: =_xlfn.IFNA(VLOOKUP(AW32,$AQ$4:$AS$328,3,FALSE),"0") -> 0 | AZ32: =SUM(AX32:AY32) -> 0 | BE32: MESERO | BF32: =_xlfn.IFNA(VLOOKUP(BE32,$BB$3:$BC$48,2,FALSE),"0") -> 0 | BQ32: SEDE CARIBE | BR32: =_xlfn.IFNA(VLOOKUP(BQ32,$BN$3:$BO$44,2,FALSE),"0") -> 1 | BW32: =BT32 -> 0 | BX32: =BU32 -> 0
... AN42: Lumbago no especificado | AO42: =_xlfn.IFNA(VLOOKUP(AN42,$AK$3:$AL$7,2,FALSE),"0") -> 0 | AW42: Diarrea y gastroenteritis de presunto origen infeccioso | AX42: =_xlfn.IFNA(VLOOKUP(AW42,$AQ$4:$AS$328,2,FALSE),"0") -> 0 | AY42: =_xlfn.IFNA(VLOOKUP(AW42,$AQ$4:$AS$328,3,FALSE),"0") -> 0 | AZ42: =SUM(AX42:AY42) -> 0 | BE42: SUPERNUMERARIO(A) | BF42: =_xlfn.IFNA(VLOOKUP(BE42,$BB$3:$BC$48,2,FALSE),"0") -> 6 | BQ42: TURIPANA | BR42: =_xlfn.IFNA(VLOOKUP(BQ42,$BN$3:$BO$44,2,FALSE),"0") -> 0 | BW42: =BT42 -> 0 | BX42: =BU42 -> 0
AN43: Nacido vivo, unico | AO43: =_xlfn.IFNA(VLOOKUP(AN43,$AK$3:$AL$7,2,FALSE),"0") -> 0 | AW43: Varices en otros sitios especificados | AX43: =_xlfn.IFNA(VLOOKUP(AW43,$AQ$4:$AS$328,2,FALSE),"0") -> 0 | AY43: =_xlfn.IFNA(VLOOKUP(AW43,$AQ$4:$AS$328,3,FALSE),"0") -> 0 | AZ43: =SUM(AX43:AY43) -> 0 | BQ43: TURIPANA MERCADEO | BR43: =_xlfn.IFNA(VLOOKUP(BQ43,$BN$3:$BO$44,2,FALSE),"0") -> 1 | BW43: =BT43 -> 0 | BX43: =BU43 -> 0
AN44: No especificado | AO44: =_xlfn.IFNA(VLOOKUP(AN44,$AK$3:$AL$7,2,FALSE),"0") -> 0 | AW44: Varicela sin complicaciones | AX44: =_xlfn.IFNA(VLOOKUP(AW44,$AQ$4:$AS$328,2,FALSE),"0") -> 0 | AY44: =_xlfn.IFNA(VLOOKUP(AW44,$AQ$4:$AS$328,3,FALSE),"0") -> 0 | AZ44: =SUM(AX44:AY44) -> 0 | BW44: =BT44 -> 0 | BX44: =BU44 -> 0
AN45: Bronquitis aguda debida a otros microorganismos especificados | AO45: =_xlfn.IFNA(VLOOKUP(AN45,$AK$3:$AL$7,2,FALSE),"0") -> 0 | AW45: Otros traumatismos especificados de la muneca y de la mano | AX45: =_xlfn.IFNA(VLOOKUP(AW45,$AQ$4:$AS$328,2,FALSE),"0") -> 0 | AY45: =_xlfn.IFNA(VLOOKUP(AW45,$AQ$4:$AS$328,3,FALSE),"0") -> 0 | AZ45: =SUM(AX45:AY45) -> 0 | BW45: =BT45 -> 0 | BX45: =BU45 -> 0
AN46: Anomalias de la posicion del diente | AO46: =_xlfn.IFNA(VLOOKUP(AN46,$AK$3:$AL$7,2,FALSE),"0") -> 0 | AW46: Cuidado posterior a la ortopedia, no especificado | AX46: =_xlfn.IFNA(VLOOKUP(AW46,$AQ$4:$AS$328,2,FALSE),"0") -> 0 | AY46: =_xlfn.IFNA(VLOOKUP(AW46,$AQ$4:$AS$328,3,FALSE),"0") -> 0 | AZ46: =SUM(AX46:AY46) -> 0 | BW46: =BT46 -> 0 | BX46: =BU46 -> 0
AN47: 0 | AO47: =_xlfn.IFNA(VLOOKUP(AN47,$AK$3:$AL$7,2,FALSE),"0") -> 0 | AW47: Otros dolores abdominales y los no especificados | AX47: =_xlfn.IFNA(VLOOKUP(AW47,$AQ$4:$AS$328,2,FALSE),"0") -> 0 | AY47: =_xlfn.IFNA(VLOOKUP(AW47,$AQ$4:$AS$328,3,FALSE),"0") -> 1 | AZ47: =SUM(AX47:AY47) -> 1 | BW47: =BT47 -> 0 | BX47: =BU47 -> 0
AN48: 0 | AO48: =_xlfn.IFNA(VLOOKUP(AN48,$AK$3:$AL$7,2,FALSE),"0") -> 0 | AW48: Bronconeumonia, no especificada | AX48: =_xlfn.IFNA(VLOOKUP(AW48,$AQ$4:$AS$328,2,FALSE),"0") -> 0 | AY48: =_xlfn.IFNA(VLOOKUP(AW48,$AQ$4:$AS$328,3,FALSE),"0") -> 0 | AZ48: =SUM(AX48:AY48) -> 0 | BW48: =BT48 -> 0 | BX48: =BU48 -> 0
AN49: 0 | AO49: =_xlfn.IFNA(VLOOKUP(AN49,$AK$3:$AL$7,2,FALSE),"0") -> 0 | AW49: Dolor agudo | AX49: =_xlfn.IFNA(VLOOKUP(AW49,$AQ$4:$AS$328,2,FALSE),"0") -> 0 | AY49: =_xlfn.IFNA(VLOOKUP(AW49,$AQ$4:$AS$328,3,FALSE),"0") -> 0 | AZ49: =SUM(AX49:AY49) -> 0 | BW49: =BT49 -> 0 | BX49: =BU49 -> 0
AN50: 0 | AO50: =_xlfn.IFNA(VLOOKUP(AN50,$AK$3:$AL$7,2,FALSE),"0") -> 0 | AW50: Ruptura espontanea de otros tendones | AX50: =_xlfn.IFNA(VLOOKUP(AW50,$AQ$4:$AS$328,2,FALSE),"0") -> 0 | AY50: =_xlfn.IFNA(VLOOKUP(AW50,$AQ$4:$AS$328,3,FALSE),"0") -> 0 | AZ50: =SUM(AX50:AY50) -> 0 | BW50: =BT50 -> 0 | BX50: =BU50 -> 0
AN51: 0 | AO51: =_xlfn.IFNA(VLOOKUP(AN51,$AK$3:$AL$7,2,FALSE),"0") -> 0 | AW51: Hipertension esencial (primaria) | AX51: =_xlfn.IFNA(VLOOKUP(AW51,$AQ$4:$AS$328,2,FALSE),"0") -> 0 | AY51: =_xlfn.IFNA(VLOOKUP(AW51,$AQ$4:$AS$328,3,FALSE),"0") -> 0 | AZ51: =SUM(AX51:AY51) -> 0 | BW51: =BT51 -> 0 | BX51: =BU51 -> 0
AN52: 0 | AO52: =_xlfn.IFNA(VLOOKUP(AN52,$AK$3:$AL$7,2,FALSE),"0") -> 0 | AW52: Cervicalgia | AX52: =_xlfn.IFNA(VLOOKUP(AW52,$AQ$4:$AS$328,2,FALSE),"0") -> 0 | AY52: =_xlfn.IFNA(VLOOKUP(AW52,$AQ$4:$AS$328,3,FALSE),"0") -> 0 | AZ52: =SUM(AX52:AY52) -> 0 | BW52: =BT52 -> 0 | BX52: =BU52 -> 0
AN53: 0 | AO53: =_xlfn.IFNA(VLOOKUP(AN53,$AK$3:$AL$7,2,FALSE),"0") -> 0 | AW53: Faringitis estreptococica | AX53: =_xlfn.IFNA(VLOOKUP(AW53,$AQ$4:$AS$328,2,FALSE),"0") -> 0 | AY53: =_xlfn.IFNA(VLOOKUP(AW53,$AQ$4:$AS$328,3,FALSE),"0") -> 0 | AZ53: =SUM(AX53:AY53) -> 0
AN54: 0 | AO54: =_xlfn.IFNA(VLOOKUP(AN54,$AK$3:$AL$7,2,FALSE),"0") -> 0 | AW54: Sindrome de la articulacion condrocostal [Tietze] | AX54: =_xlfn.IFNA(VLOOKUP(AW54,$AQ$4:$AS$328,2,FALSE),"0") -> 0 | AY54: =_xlfn.IFNA(VLOOKUP(AW54,$AQ$4:$AS$328,3,FALSE),"0") -> 0 | AZ54: =SUM(AX54:AY54) -> 0
AN55: 0 | AO55: =_xlfn.IFNA(VLOOKUP(AN55,$AK$3:$AL$7,2,FALSE),"0") -> 0 | AW55: Dolor, no especificado | AX55: =_xlfn.IFNA(VLOOKUP(AW55,$AQ$4:$AS$328,2,FALSE),"0") -> 0 | AY55: =_xlfn.IFNA(VLOOKUP(AW55,$AQ$4:$AS$328,3,FALSE),"0") -> 0 | AZ55: =SUM(AX55:AY55) -> 0 | BQ55: Total | BR55: =SUM(BR3:BR54) -> 20 | BW55: Total | BX55: =SUM(BX3:BX54) -> 0
AN56: 0 | AO56: =_xlfn.IFNA(VLOOKUP(AN56,$AK$3:$AL$7,2,FALSE),"0") -> 0 | AW56: COVID-19, virus no identificado | AX56: =_xlfn.IFNA(VLOOKUP(AW56,$AQ$4:$AS$328,2,FALSE),"0") -> 0 | AY56: =_xlfn.IFNA(VLOOKUP(AW56,$AQ$4:$AS$328,3,FALSE),"0") -> 0 | AZ56: =SUM(AX56:AY56) -> 0
AN57: 0 | AO57: =_xlfn.IFNA(VLOOKUP(AN57,$AK$3:$AL$7,2,FALSE),"0") -> 0 | AW57: Contusion de la region lumbosacra y de la pelvis | AX57: =_xlfn.IFNA(VLOOKUP(AW57,$AQ$4:$AS$328,2,FALSE),"0") -> 0 | AY57: =_xlfn.IFNA(VLOOKUP(AW57,$AQ$4:$AS$328,3,FALSE),"0") -> 0 | AZ57: =SUM(AX57:AY57) -> 0 | BE57: Total | BF57: =SUM(BF3:BF56) -> 20
AW58: Diarrea funcional | AX58: =_xlfn.IFNA(VLOOKUP(AW58,$AQ$4:$AS$328,2,FALSE),"0") -> 0 | AY58: =_xlfn.IFNA(VLOOKUP(AW58,$AQ$4:$AS$328,3,FALSE),"0") -> 0 | AZ58: =SUM(AX58:AY58) -> 0
AW59: Pterigion | AX59: =_xlfn.IFNA(VLOOKUP(AW59,$AQ$4:$AS$328,2,FALSE),"0") -> 0 | AY59: =_xlfn.IFNA(VLOOKUP(AW59,$AQ$4:$AS$328,3,FALSE),"0") -> 0 | AZ59: =SUM(AX59:AY59) -> 0
AW60: Celulitis de otras partes de los miembros | AX60: =_xlfn.IFNA(VLOOKUP(AW60,$AQ$4:$AS$328,2,FALSE),"0") -> 0 | AY60: =_xlfn.IFNA(VLOOKUP(AW60,$AQ$4:$AS$328,3,FALSE),"0") -> 0 | AZ60: =SUM(AX60:AY60) -> 0
AW61: Parto unico espontaneo, presentacion cefalica de vertice | AX61: =_xlfn.IFNA(VLOOKUP(AW61,$AQ$4:$AS$328,2,FALSE),"0") -> 0 | AY61: =_xlfn.IFNA(VLOOKUP(AW61,$AQ$4:$AS$328,3,FALSE),"0") -> 0 | AZ61: =SUM(AX61:AY61) -> 0
AW62: Otras convulsiones y las no especificadas | AX62: =_xlfn.IFNA(VLOOKUP(AW62,$AQ$4:$AS$328,2,FALSE),"0") -> 0 | AY62: =_xlfn.IFNA(VLOOKUP(AW62,$AQ$4:$AS$328,3,FALSE),"0") -> 0 | AZ62: =SUM(AX62:AY62) -> 0
AW63: Falso trabajo de parto a las 37 y mas semanas completas de gestacion | AX63: =_xlfn.IFNA(VLOOKUP(AW63,$AQ$4:$AS$328,2,FALSE),"0") -> 0 | AY63: =_xlfn.IFNA(VLOOKUP(AW63,$AQ$4:$AS$328,3,FALSE),"0") -> 0 | AZ63: =SUM(AX63:AY63) -> 0
AW64: Gastroduodenitis, no especificada | AX64: =_xlfn.IFNA(VLOOKUP(AW64,$AQ$4:$AS$328,2,FALSE),"0") -> 0 | AY64: =_xlfn.IFNA(VLOOKUP(AW64,$AQ$4:$AS$328,3,FALSE),"0") -> 0 | AZ64: =SUM(AX64:AY64) -> 0
AW65: Hidronefrosis con obstruccion por calculos del rinon y del ureter | AX65: =_xlfn.IFNA(VLOOKUP(AW65,$AQ$4:$AS$328,2,FALSE),"0") -> 0 | AY65: =_xlfn.IFNA(VLOOKUP(AW65,$AQ$4:$AS$328,3,FALSE),"0") -> 0 | AZ65: =SUM(AX65:AY65) -> 0
AW66: Dermatitis de contacto, forma no especificada, debida a otros agentes | AX66: =_xlfn.IFNA(VLOOKUP(AW66,$AQ$4:$AS$328,2,FALSE),"0") -> 0 | AY66: =_xlfn.IFNA(VLOOKUP(AW66,$AQ$4:$AS$328,3,FALSE),"0") -> 0 | AZ66: =SUM(AX66:AY66) -> 0
AW67: Celulitis de sitio no especificado | AX67: =_xlfn.IFNA(VLOOKUP(AW67,$AQ$4:$AS$328,2,FALSE),"0") -> 0 | AY67: =_xlfn.IFNA(VLOOKUP(AW67,$AQ$4:$AS$328,3,FALSE),"0") -> 0 | AZ67: =SUM(AX67:AY67) -> 0
AW68: Lumbago no especificado | AX68: =_xlfn.IFNA(VLOOKUP(AW68,$AQ$4:$AS$328,2,FALSE),"0") -> 0 | AY68: =_xlfn.IFNA(VLOOKUP(AW68,$AQ$4:$AS$328,3,FALSE),"0") -> 0 | AZ68: =SUM(AX68:AY68) -> 0
AW69: Otros trastornos sinoviales y tendinosos en enfermedades clasificadas en otra parte | AX69: =_xlfn.IFNA(VLOOKUP(AW69,$AQ$4:$AS$328,2,FALSE),"0") -> 0 | AY69: =_xlfn.IFNA(VLOOKUP(AW69,$AQ$4:$AS$328,3,FALSE),"0") -> 0 | AZ69: =SUM(AX69:AY69) -> 0
... AW288: Enfermedades del sistma digestivo | AX288: =_xlfn.IFNA(VLOOKUP(AW288,$AQ$4:$AS$328,2,FALSE),"0") -> 0 | AY288: =_xlfn.IFNA(VLOOKUP(AW288,$AQ$4:$AS$328,3,FALSE),"0") -> 0 | AZ288: =SUM(AX288:AY288) -> 0

Sheet Tempoactiva 2024
E1: PROCESO DE GESTION INTEGRAL | Q1: CODIGO: GI-FO-076
E3: AUSENTISMO POR ARL Y EPS | Q3: REV. 02 ENERO 12 DEL 2023
A7: No | B7: EMPRESA | C7: NOMBRE | D7: CEDULA | E7: Columna1 | F7: CARGO | G7: EMPRESA USUARIA | H7: ÁREA O DPTO | I7: GENERO | J7: MES | K7: N° DIAS DE INCAPACIDAD | L7: CLASE DE INCAPACIDAD | M7: TIPO DE INCAPACIDAD | N7: ENTIDAD | O7: AÑO | P7: F. INICIO | Q7: F. FIN | R7: CODIGO | S7: DESCRIPCION | T7: > 10 Dias | U7: D. T. P. | V7: A. Inc. | W7: M. Inc. | X7: Concepto | Y7: Descripción
A8: 1 | B8: TEMPOACTIVA | C8: =_xlfn.XLOOKUP(D8,[1]!Data[CEDULA],[1]!Data[Nombre Completo],"No Existe",0,1) -> KARINA GREGORIA SALAS BROCHERO | D8: 1007096798 | E8: =IFERROR(_xlfn.NUMBERVALUE(Data[[#This Row],[CEDULA ]],",","."),_xlfn.NUMBERVALUE(Data[[#This Row],[CEDULA ]],".",",")) -> 1007096798 | F8: =_xlfn.XLOOKUP(E8,[1]!Data[CEDULA],[1]!Data[CARGO],"No Existe",0,1) -> SUPERNUMERARIO(A) | G8: =_xlfn.XLOOKUP(E8,[1]!Data[CEDULA],[1]!Data[EMPRESA DONDE PRESTA SERVICIO],"No Existe",0,1) -> COMFAMILIAR ATLANTICO | H8: =_xlfn.XLOOKUP(E8,[1]!Data[CEDULA],[1]!Data[UBICACIÓN],"No Existe",0,1) -> SEDE NORTE | I8: MUJER | J8: =UPPER(TEXT(Data[[#This Row],[F. INICIO]],"mmmm")) -> ABRIL | K8: 1 | L8: EPS | M8: LICENCIA DE MATERNIDAD | N8: =_xlfn.XLOOKUP(D8,[1]!Data[CEDULA],[1]!Data[EPS/SURA],"No Existe",0,1) -> E.P.S SANITAS | O8: =YEAR(Data[[#This Row],[F. INICIO]]) -> 2024 | P8: 45383 | Q8: 45017 | R8: O829 | S8: =IF(Data[[#This Row],[TIPO DE INCAPACIDAD]]="LICENCIA DE PATERNIDAD","Licencia de paternidad",IF(Data[[#This Row],[TIPO DE INCAPACIDAD]]="LICENCIA DE LUTO","Licencia de Luto",_xlfn.IFNA(VLOOKUP(R8,'CIE-10 PARA RIPS'!$A$6:B13176,2,0),"No especificado"))) -> Parto por cesarea, sin otra especificacion | T8: =IF(P8<>"", IF(P8>0, IF(P8<=DATE(YEAR(P8),MONTH(P8),DAY(P8)), IF(P8>=DATE(YEAR(P8),MONTH(P8),1), IF(K8>10, C8, IF(SUMIFS($K:$K, $C:$C, C8, $P:$P, ">="&DATE(YEAR(P8),MONTH(P8),1), $P:$P, "<="&EOMONTH(P8,0))>10, C8, "")), ""))), "") | U8: =IF(AND(P8<>"", P8>=DATE(YEAR(P8),MONTH(P8),1), SUMIFS($K:$K, $C:$C, C8, $P:$P, ">="&DATE(YEAR(P8),MONTH(P8),1), $P:$P, "<="&EOMONTH(P8,0))>10), K8, "") | V8: =IF(AND(P8<>"", P8>=DATE(YEAR(P8),MONTH(P8),1), SUMIFS($K:$K, $C:$C, C8, $P:$P, ">="&DATE(YEAR(P8),MONTH(P8),1), $P:$P, "<="&EOMONTH(P8,0))>10), YEAR(P8), "") | W8: =IF(AND(P8<>"", P8>=DATE(YEAR(P8),MONTH(P8),1), SUMIFS($K:$K, $C:$C, C8, $P:$P, ">="&DATE(YEAR(P8),MONTH(P8),1), $P:$P, "<="&EOMONTH(P8,0))>10), TEXT(P8, "MMMM"), "") | X8: {=IF(AND(P8<>"", P8>=DATE(YEAR(P8),MONTH(P8),1), SUMIFS($K:$K, $C:$C, C8, $P:$P, ">="&DATE(YEAR(P8),MONTH(P8),1), $P:$P, "<="&EOMONTH(P8,0))>10), _xlfn.TEXTJOIN(", ", TRUE, _xlfn._xlws.FILTER($R:$R, ($C:$C=C8) * ($P:$P>=DATE(YEAR(P8),MONTH(P8),1)) * ($P:$P<=EOMONTH(P8,0)))), "")} | Y8: {=IF(AND(P8<>"", P8>=DATE(YEAR(P8),MONTH(P8),1), SUMIFS($K:$K, $C:$C, C8, $P:$P, ">="&DATE(YEAR(P8),MONTH(P8),1), $P:$P, "<="&EOMONTH(P8,0))>10), _xlfn.TEXTJOIN(", ", TRUE, _xlfn._xlws.FILTER($S:$S, ($C:$C=C8) * ($P:$P>=DATE(YEAR(P8),MONTH(P8),1)) * ($P:$P<=EOMONTH(P8,0)))), "")}
A9: 2 | B9: TEMPOACTIVA | C9: =_xlfn.XLOOKUP(D9,[1]!Data[CEDULA],[1]!Data[Nombre Completo],"No Existe",0,1) -> HELIS MARI RAMIREZ PATIÑO | D9: 1140868628 | E9: =IFERROR(_xlfn.NUMBERVALUE(Data[[#This Row],[CEDULA ]],",","."),_xlfn.NUMBERVALUE(Data[[#This Row],[CEDULA ]],".",",")) -> 1140868628 | F9: =_xlfn.XLOOKUP(E9,[1]!Data[CEDULA],[1]!Data[CARGO],"No Existe",0,1) -> SUPERNUMERARIO(A) | G9: =_xlfn.XLOOKUP(E9,[1]!Data[CEDULA],[1]!Data[EMPRESA DONDE PRESTA SERVICIO],"No Existe",0,1) -> COMFAMILIAR ATLANTICO | H9: =_xlfn.XLOOKUP(E9,[1]!Data[CEDULA],[1]!Data[UBICACIÓN],"No Existe",0,1) -> SEDE NORTE | I9: MUJER | J9: =UPPER(TEXT(Data[[#This Row],[F. INICIO]],"mmmm")) -> ABRIL | K9: 3 | L9: EPS | M9: ENFERMENDAD GENERAL | N9: =_xlfn.XLOOKUP(D9,[1]!Data[CEDULA],[1]!Data[EPS/SURA],"No Existe",0,1) -> MUTUALSER | O9: =YEAR(Data[[#This Row],[F. INICIO]]) -> 2024 | P9: 45383 | Q9: 45354 | R9: Z359 | S9: =IF(Data[[#This Row],[TIPO DE INCAPACIDAD]]="LICENCIA DE PATERNIDAD","Licencia de paternidad",IF(Data[[#This Row],[TIPO DE INCAPACIDAD]]="LICENCIA DE LUTO","Licencia de Luto",_xlfn.IFNA(VLOOKUP(R9,'CIE-10 PARA RIPS'!$A$6:B13196,2,0),"No especificado"))) -> Supervision de embarazo de alto riesgo, sin otra especificacion | T9: =IF(P9<>"", IF(P9>0, IF(P9<=DATE(YEAR(P9),MONTH(P9),DAY(P9)), IF(P9>=DATE(YEAR(P9),MONTH(P9),1), IF(K9>10, C9, IF(SUMIFS($K:$K, $C:$C, C9, $P:$P, ">="&DATE(YEAR(P9),MONTH(P9),1), $P:$P, "<="&EOMONTH(P9,0))>10, C9, "")), ""))), "") -> HELIS MARI RAMIREZ PATIÑO | U9: =IF(AND(P9<>"", P9>=DATE(YEAR(P9),MONTH(P9),1), SUMIFS($K:$K, $C:$C, C9, $P:$P, ">="&DATE(YEAR(P9),MONTH(P9),1), $P:$P, "<="&EOMONTH(P9,0))>10), K9, "") -> 3 | V9: =IF(AND(P9<>"", P9>=DATE(YEAR(P9),MONTH(P9),1), SUMIFS($K:$K, $C:$C, C9, $P:$P, ">="&DATE(YEAR(P9),MONTH(P9),1), $P:$P, "<="&EOMONTH(P9,0))>10), YEAR(P9), "") -> 2024 | W9: =IF(AND(P9<>"", P9>=DATE(YEAR(P9),MONTH(P9),1), SUMIFS($K:$K, $C:$C, C9, $P:$P, ">="&DATE(YEAR(P9),MONTH(P9),1), $P:$P, "<="&EOMONTH(P9,0))>10), TEXT(P9, "MMMM"), "") -> abril | X9: {=IF(AND(P9<>"", P9>=DATE(YEAR(P9),MONTH(P9),1), SUMIFS($K:$K, $C:$C, C9, $P:$P, ">="&DATE(YEAR(P9),MONTH(P9),1), $P:$P, "<="&EOMONTH(P9,0))>10), _xlfn.TEXTJOIN(", ", TRUE, _xlfn._xlws.FILTER($R:$R, ($C:$C=C9) * ($P:$P>=DATE(YEAR(P9),MONTH(P9),1)) * ($P:$P<=EOMONTH(P9,0)))), "")} -> Z359, O821 | Y9: {=IF(AND(P9<>"", P9>=DATE(YEAR(P9),MONTH(P9),1), SUMIFS($K:$K, $C:$C, C9, $P:$P, ">="&DATE(YEAR(P9),MONTH(P9),1), $P:$P, "<="&EOMONTH(P9,0))>10), _xlfn.TEXTJOIN(", ", TRUE, _xlfn._xlws.FILTER($S:$S, ($C:$C=C9) * ($P:$P>=DATE(YEAR(P9),MONTH(P9),1)) * ($P:$P<=EOMONTH(P9,0)))), "")} -> Supervision de embarazo de alto riesgo, sin otra especificacion, Parto por cesarea de emergencia
A10: 3 | B10: TEMPOACTIVA | C10: =_xlfn.XLOOKUP(D10,[1]!Data[CEDULA],[1]!Data[Nombre Completo],"No Existe",0,1) -> HELIS MARI RAMIREZ PATIÑO | D10: 1140868628 | E10: =IFERROR(_xlfn.NUMBERVALUE(Data[[#This Row],[CEDULA ]],",","."),_xlfn.NUMBERVALUE(Data[[#This Row],[CEDULA ]],".",",")) -> 1140868628 | F10: =_xlfn.XLOOKUP(E10,[1]!Data[CEDULA],[1]!Data[CARGO],"No Existe",0,1) -> SUPERNUMERARIO(A) | G10: =_xlfn.XLOOKUP(E10,[1]!Data[CEDULA],[1]!Data[EMPRESA DONDE PRESTA SERVICIO],"No Existe",0,1) -> COMFAMILIAR ATLANTICO | H10: =_xlfn.XLOOKUP(E10,[1]!Data[CEDULA],[1]!Data[UBICACIÓN],"No Existe",0,1) -> SEDE NORTE | I10: MUJER | J10: =UPPER(TEXT(Data[[#This Row],[F. INICIO]],"mmmm")) -> ABRIL | K10: 20 | L10: EPS | M10: LICENCIA DE MATERNIDAD | N10: =_xlfn.XLOOKUP(D10,[1]!Data[CEDULA],[1]!Data[EPS/SURA],"No Existe",0,1) -> MUTUALSER | O10: =YEAR(Data[[#This Row],[F. INICIO]]) -> 2024 | P10: 45393 | Q10: 45412 | R10: O821 | S10: =IF(Data[[#This Row],[TIPO DE INCAPACIDAD]]="LICENCIA DE PATERNIDAD","Licencia de paternidad",IF(Data[[#This Row],[TIPO DE INCAPACIDAD]]="LICENCIA DE LUTO","Licencia de Luto",_xlfn.IFNA(VLOOKUP(R10,'CIE-10 PARA RIPS'!$A$6:B13232,2,0),"No especificado"))) -> Parto por cesarea de emergencia | T10: =IF(P10<>"", IF(P10>0, IF(P10<=DATE(YEAR(P10),MONTH(P10),DAY(P10)), IF(P10>=DATE(YEAR(P10),MONTH(P10),1), IF(K10>10, C10, IF(SUMIFS($K:$K, $C:$C, C10, $P:$P, ">="&DATE(YEAR(P10),MONTH(P10),1), $P:$P, "<="&EOMONTH(P10,0))>10, C10, "")), ""))), "") -> HELIS MARI RAMIREZ PATIÑO | U10: =IF(AND(P10<>"", P10>=DATE(YEAR(P10),MONTH(P10),1), SUMIFS($K:$K, $C:$C, C10, $P:$P, ">="&DATE(YEAR(P10),MONTH(P10),1), $P:$P, "<="&EOMONTH(P10,0))>10), K10, "") -> 20 | V10: =IF(AND(P10<>"", P10>=DATE(YEAR(P10),MONTH(P10),1), SUMIFS($K:$K, $C:$C, C10, $P:$P, ">="&DATE(YEAR(P10),MONTH(P10),1), $P:$P, "<="&EOMONTH(P10,0))>10), YEAR(P10), "") -> 2024 | W10: =IF(AND(P10<>"", P10>=DATE(YEAR(P10),MONTH(P10),1), SUMIFS($K:$K, $C:$C, C10, $P:$P, ">="&DATE(YEAR(P10),MONTH(P10),1), $P:$P, "<="&EOMONTH(P10,0))>10), TEXT(P10, "MMMM"), "") -> abril | X10: {=IF(AND(P10<>"", P10>=DATE(YEAR(P10),MONTH(P10),1), SUMIFS($K:$K, $C:$C, C10, $P:$P, ">="&DATE(YEAR(P10),MONTH(P10),1), $P:$P, "<="&EOMONTH(P10,0))>10), _xlfn.TEXTJOIN(", ", TRUE, _xlfn._xlws.FILTER($R:$R, ($C:$C=C10) * ($P:$P>=DATE(YEAR(P10),MONTH(P10),1)) * ($P:$P<=EOMONTH(P10,0)))), "")} -> Z359, O821 | Y10: {=IF(AND(P10<>"", P10>=DATE(YEAR(P10),MONTH(P10),1), SUMIFS($K:$K, $C:$C, C10, $P:$P, ">="&DATE(YEAR(P10),MONTH(P10),1), $P:$P, "<="&EOMONTH(P10,0))>10), _xlfn.TEXTJOIN(", ", TRUE, _xlfn._xlws.FILTER($S:$S, ($C:$C=C10) * ($P:$P>=DATE(YEAR(P10),MONTH(P10),1)) * ($P:$P<=EOMONTH(P10,0)))), "")} -> Supervision de embarazo de alto riesgo, sin otra especificacion, Parto por cesarea de emergencia
A11: 4 | B11: TEMPOACTIVA | C11: =_xlfn.XLOOKUP(D11,[1]!Data[CEDULA],[1]!Data[Nombre Completo],"No Existe",0,1) -> HELIS MARI RAMIREZ PATIÑO | D11: 1140868628 | E11: =IFERROR(_xlfn.NUMBERVALUE(Data[[#This Row],[CEDULA ]],",","."),_xlfn.NUMBERVALUE(Data[[#This Row],[CEDULA ]],".",",")) -> 1140868628 | F11: =_xlfn.XLOOKUP(E11,[1]!Data[CEDULA],[1]!Data[CARGO],"No Existe",0,1) -> SUPERNUMERARIO(A) | G11: =_xlfn.XLOOKUP(E11,[1]!Data[CEDULA],[1]!Data[EMPRESA DONDE PRESTA SERVICIO],"No Existe",0,1) -> COMFAMILIAR ATLANTICO | H11: =_xlfn.XLOOKUP(E11,[1]!Data[CEDULA],[1]!Data[UBICACIÓN],"No Existe",0,1) -> SEDE NORTE | I11: MUJER | J11: =UPPER(TEXT(Data[[#This Row],[F. INICIO]],"mmmm")) -> AGOSTO | K11: 31 | L11: EPS | M11: LICENCIA DE MATERNIDAD | N11: =_xlfn.XLOOKUP(D11,[1]!Data[CEDULA],[1]!Data[EPS/SURA],"No Existe",0,1) -> MUTUALSER | O11: =YEAR(Data[[#This Row],[F. INICIO]]) -> 2024 | P11: 45505 | Q11: 45535 | R11: O821 | S11: =IF(Data[[#This Row],[TIPO DE INCAPACIDAD]]="LICENCIA DE PATERNIDAD","Licencia de paternidad",IF(Data[[#This Row],[TIPO DE INCAPACIDAD]]="LICENCIA DE LUTO","Licencia de Luto",_xlfn.IFNA(VLOOKUP(R11,'CIE-10 PARA RIPS'!$A$6:B13236,2,0),"No especificado"))) -> Parto por cesarea de emergencia | T11: =IF(P11<>"", IF(P11>0, IF(P11<=DATE(YEAR(P11),MONTH(P11),DAY(P11)), IF(P11>=DATE(YEAR(P11),MONTH(P11),1), IF(K11>10, C11, IF(SUMIFS($K:$K, $C:$C, C11, $P:$P, ">="&DATE(YEAR(P11),MONTH(P11),1), $P:$P, "<="&EOMONTH(P11,0))>10, C11, "")), ""))), "") -> HELIS MARI RAMIREZ PATIÑO | U11: =IF(AND(P11<>"", P11>=DATE(YEAR(P11),MONTH(P11),1), SUMIFS($K:$K, $C:$C, C11, $P:$P, ">="&DATE(YEAR(P11),MONTH(P11),1), $P:$P, "<="&EOMONTH(P11,0))>10), K11, "") -> 31 | V11: =IF(AND(P11<>"", P11>=DATE(YEAR(P11),MONTH(P11),1), SUMIFS($K:$K, $C:$C, C11, $P:$P, ">="&DATE(YEAR(P11),MONTH(P11),1), $P:$P, "<="&EOMONTH(P11,0))>10), YEAR(P11), "") -> 2024 | W11: =IF(AND(P11<>"", P11>=DATE(YEAR(P11),MONTH(P11),1), SUMIFS($K:$K, $C:$C, C11, $P:$P, ">="&DATE(YEAR(P11),MONTH(P11),1), $P:$P, "<="&EOMONTH(P11,0))>10), TEXT(P11, "MMMM"), "") -> agosto | X11: {=IF(AND(P11<>"", P11>=DATE(YEAR(P11),MONTH(P11),1), SUMIFS($K:$K, $C:$C, C11, $P:$P, ">="&DATE(YEAR(P11),MONTH(P11),1), $P:$P, "<="&EOMONTH(P11,0))>10), _xlfn.TEXTJOIN(", ", TRUE, _xlfn._xlws.FILTER($R:$R, ($C:$C=C11) * ($P:$P>=DATE(YEAR(P11),MONTH(P11),1)) * ($P:$P<=EOMONTH(P11,0)))), "")} -> O821 | Y11: {=IF(AND(P11<>"", P11>=DATE(YEAR(P11),MONTH(P11),1), SUMIFS($K:$K, $C:$C, C11, $P:$P, ">="&DATE(YEAR(P11),MONTH(P11),1), $P:$P, "<="&EOMONTH(P11,0))>10), _xlfn.TEXTJOIN(", ", TRUE, _xlfn._xlws.FILTER($S:$S, ($C:$C=C11) * ($P:$P>=DATE(YEAR(P11),MONTH(P11),1)) * ($P:$P<=EOMONTH(P11,0)))), "")} -> Parto por cesarea de emergencia
A12: 5 | B12: TEMPOACTIVA | C12: =_xlfn.XLOOKUP(D12,[1]!Data[CEDULA],[1]!Data[Nombre Completo],"No Existe",0,1) -> KARINA GREGORIA SALAS BROCHERO | D12: 1007096798 | E12: =IFERROR(_xlfn.NUMBERVALUE(Data[[#This Row],[CEDULA ]],",","."),_xlfn.NUMBERVALUE(Data[[#This Row],[CEDULA ]],".",",")) -> 1007096798 | F12: =_xlfn.XLOOKUP(E12,[1]!Data[CEDULA],[1]!Data[CARGO],"No Existe",0,1) -> SUPERNUMERARIO(A) | G12: =_xlfn.XLOOKUP(E12,[1]!Data[CEDULA],[1]!Data[EMPRESA DONDE PRESTA SERVICIO],"No Existe",0,1) -> COMFAMILIAR ATLANTICO | H12: =_xlfn.XLOOKUP(E12,[1]!Data[CEDULA],[1]!Data[UBICACIÓN],"No Existe",0,1) -> SEDE NORTE | I12: MUJER | J12: =UPPER(TEXT(Data[[#This Row],[F. INICIO]],"mmmm")) -> ENERO | K12: 31 | L12: EPS | M12: LICENCIA DE MATERNIDAD | N12: =_xlfn.XLOOKUP(D12,[1]!Data[CEDULA],[1]!Data[EPS/SURA],"No Existe",0,1) -> E.P.S SANITAS | O12: =YEAR(Data[[#This Row],[F. INICIO]]) -> 2024 | P12: 45292 | Q12: 45322 | R12: O829 | S12: =IF(Data[[#This Row],[TIPO DE INCAPACIDAD]]="LICENCIA DE PATERNIDAD","Licencia de paternidad",IF(Data[[#This Row],[TIPO DE INCAPACIDAD]]="LICENCIA DE LUTO","Licencia de Luto",_xlfn.IFNA(VLOOKUP(R12,'CIE-10 PARA RIPS'!$A$6:B13173,2,0),"No especificado"))) -> Parto por cesarea, sin otra especificacion | T12: =IF(P12<>"", IF(P12>0, IF(P12<=DATE(YEAR(P12),MONTH(P12),DAY(P12)), IF(P12>=DATE(YEAR(P12),MONTH(P12),1), IF(K12>10, C12, IF(SUMIFS($K:$K, $C:$C, C12, $P:$P, ">="&DATE(YEAR(P12),MONTH(P12),1), $P:$P, "<="&EOMONTH(P12,0))>10, C12, "")), ""))), "") -> KARINA GREGORIA SALAS BROCHERO | U12: =IF(AND(P12<>"", P12>=DATE(YEAR(P12),MONTH(P12),1), SUMIFS($K:$K, $C:$C, C12, $P:$P, ">="&DATE(YEAR(P12),MONTH(P12),1), $P:$P, "<="&EOMONTH(P12,0))>10), K12, "") -> 31 | V12: =IF(AND(P12<>"", P12>=DATE(YEAR(P12),MONTH(P12),1), SUMIFS($K:$K, $C:$C, C12, $P:$P, ">="&DATE(YEAR(P12),MONTH(P12),1), $P:$P, "<="&EOMONTH(P12,0))>10), YEAR(P12), "") -> 2024 | W12: =IF(AND(P12<>"", P12>=DATE(YEAR(P12),MONTH(P12),1), SUMIFS($K:$K, $C:$C, C12, $P:$P, ">="&DATE(YEAR(P12),MONTH(P12),1), $P:$P, "<="&EOMONTH(P12,0))>10), TEXT(P12, "MMMM"), "") -> enero | X12: {=IF(AND(P12<>"", P12>=DATE(YEAR(P12),MONTH(P12),1), SUMIFS($K:$K, $C:$C, C12, $P:$P, ">="&DATE(YEAR(P12),MONTH(P12),1), $P:$P, "<="&EOMONTH(P12,0))>10), _xlfn.TEXTJOIN(", ", TRUE, _xlfn._xlws.FILTER($R:$R, ($C:$C=C12) * ($P:$P>=DATE(YEAR(P12),MONTH(P12),1)) * ($P:$P<=EOMONTH(P12,0)))), "")} -> O829 | Y12: {=IF(AND(P12<>"", P12>=DATE(YEAR(P12),MONTH(P12),1), SUMIFS($K:$K, $C:$C, C12, $P:$P, ">="&DATE(YEAR(P12),MONTH(P12),1), $P:$P, "<="&EOMONTH(P12,0))>10), _xlfn.TEXTJOIN(", ", TRUE, _xlfn._xlws.FILTER($S:$S, ($C:$C=C12) * ($P:$P>=DATE(YEAR(P12),MONTH(P12),1)) * ($P:$P<=EOMONTH(P12,0)))), "")} -> Parto por cesarea, sin otra especificacion
A13: 6 | B13: TEMPOACTIVA | C13: =_xlfn.XLOOKUP(D13,[1]!Data[CEDULA],[1]!Data[Nombre Completo],"No Existe",0,1) -> GENISIS MARIA CANTILLO TORRES | D13: 1002228922 | E13: =IFERROR(_xlfn.NUMBERVALUE(Data[[#This Row],[CEDULA ]],",","."),_xlfn.NUMBERVALUE(Data[[#This Row],[CEDULA ]],".",",")) -> 1002228922 | F13: =_xlfn.XLOOKUP(E13,[1]!Data[CEDULA],[1]!Data[CARGO],"No Existe",0,1) -> MESERO | G13: =_xlfn.XLOOKUP(E13,[1]!Data[CEDULA],[1]!Data[EMPRESA DONDE PRESTA SERVICIO],"No Existe",0,1) -> COMFAMILIAR ATLANTICO | H13: =_xlfn.XLOOKUP(E13,[1]!Data[CEDULA],[1]!Data[UBICACIÓN],"No Existe",0,1) -> SEDE SPORT GYM | I13: MUJER | J13: =UPPER(TEXT(Data[[#This Row],[F. INICIO]],"mmmm")) -> ENERO | K13: 31 | L13: EPS | M13: LICENCIA DE MATERNIDAD | N13: =_xlfn.XLOOKUP(D13,[1]!Data[CEDULA],[1]!Data[EPS/SURA],"No Existe",0,1) -> MUTUALSER | O13: =YEAR(Data[[#This Row],[F. INICIO]]) -> 2024 | P13: 45292 | Q13: 45322 | R13: O829 | S13: =IF(Data[[#This Row],[TIPO DE INCAPACIDAD]]="LICENCIA DE PATERNIDAD","Licencia de paternidad",IF(Data[[#This Row],[TIPO DE INCAPACIDAD]]="LICENCIA DE LUTO","Licencia de Luto",_xlfn.IFNA(VLOOKUP(R13,'CIE-10 PARA RIPS'!$A$6:B13177,2,0),"No especificado"))) -> Parto por cesarea, sin otra especificacion | T13: =IF(P13<>"", IF(P13>0, IF(P13<=DATE(YEAR(P13),MONTH(P13),DAY(P13)), IF(P13>=DATE(YEAR(P13),MONTH(P13),1), IF(K13>10, C13, IF(SUMIFS($K:$K, $C:$C, C13, $P:$P, ">="&DATE(YEAR(P13),MONTH(P13),1), $P:$P, "<="&EOMONTH(P13,0))>10, C13, "")), ""))), "") -> GENISIS MARIA CANTILLO TORRES | U13: =IF(AND(P13<>"", P13>=DATE(YEAR(P13),MONTH(P13),1), SUMIFS($K:$K, $C:$C, C13, $P:$P, ">="&DATE(YEAR(P13),MONTH(P13),1), $P:$P, "<="&EOMONTH(P13,0))>10), K13, "") -> 31 | V13: =IF(AND(P13<>"", P13>=DATE(YEAR(P13),MONTH(P13),1), SUMIFS($K:$K, $C:$C, C13, $P:$P, ">="&DATE(YEAR(P13),MONTH(P13),1), $P:$P, "<="&EOMONTH(P13,0))>10), YEAR(P13), "") -> 2024 | W13: =IF(AND(P13<>"", P13>=DATE(YEAR(P13),MONTH(P13),1), SUMIFS($K:$K, $C:$C, C13, $P:$P, ">="&DATE(YEAR(P13),MONTH(P13),1), $P:$P, "<="&EOMONTH(P13,0))>10), TEXT(P13, "MMMM"), "") -> enero | X13: {=IF(AND(P13<>"", P13>=DATE(YEAR(P13),MONTH(P13),1), SUMIFS($K:$K, $C:$C, C13, $P:$P, ">="&DATE(YEAR(P13),MONTH(P13),1), $P:$P, "<="&EOMONTH(P13,0))>10), _xlfn.TEXTJOIN(", ", TRUE, _xlfn._xlws.FILTER($R:$R, ($C:$C=C13) * ($P:$P>=DATE(YEAR(P13),MONTH(P13),1)) * ($P:$P<=EOMONTH(P13,0)))), "")} -> O829 | Y13: {=IF(AND(P13<>"", P13>=DATE(YEAR(P13),MONTH(P13),1), SUMIFS($K:$K, $C:$C, C13, $P:$P, ">="&DATE(YEAR(P13),MONTH(P13),1), $P:$P, "<="&EOMONTH(P13,0))>10), _xlfn.TEXTJOIN(", ", TRUE, _xlfn._xlws.FILTER($S:$S, ($C:$C=C13) * ($P:$P>=DATE(YEAR(P13),MONTH(P13),1)) * ($P:$P<=EOMONTH(P13,0)))), "")} -> Parto por cesarea, sin otra especificacion
A14: 7 | B14: TEMPOACTIVA | C14: =_xlfn.XLOOKUP(D14,[1]!Data[CEDULA],[1]!Data[Nombre Completo],"No Existe",0,1) -> JUAN CARLOS CORRO MOLINA | D14: 1044392407 | E14: =IFERROR(_xlfn.NUMBERVALUE(Data[[#This Row],[CEDULA ]],",","."),_xlfn.NUMBERVALUE(Data[[#This Row],[CEDULA ]],".",",")) -> 1044392407 | F14: =_xlfn.XLOOKUP(E14,[1]!Data[CEDULA],[1]!Data[CARGO],"No Existe",0,1) -> SUPERNUMERARIO(A) | G14: =_xlfn.XLOOKUP(E14,[1]!Data[CEDULA],[1]!Data[EMPRESA DONDE PRESTA SERVICIO],"No Existe",0,1) -> COMFAMILIAR ATLANTICO | H14: =_xlfn.XLOOKUP(E14,[1]!Data[CEDULA],[1]!Data[UBICACIÓN],"No Existe",0,1) -> CENTRO RECREACIONAL TURIPANA | I14: HOMBRE | J14: =UPPER(TEXT(Data[[#This Row],[F. INICIO]],"mmmm")) -> ENERO | K14: 6 | L14: EPS | M14: ENFERMENDAD GENERAL | N14: =_xlfn.XLOOKUP(D14,[1]!Data[CEDULA],[1]!Data[EPS/SURA],"No Existe",0,1) -> MUTUALSER | O14: =YEAR(Data[[#This Row],[F. INICIO]]) -> 2024 | P14: 45292 | Q14: 45297 | R14: S835 | S14: =IF(Data[[#This Row],[TIPO DE INCAPACIDAD]]="LICENCIA DE PATERNIDAD","Licencia de paternidad",IF(Data[[#This Row],[TIPO DE INCAPACIDAD]]="LICENCIA DE LUTO","Licencia de Luto",_xlfn.IFNA(VLOOKUP(R14,'CIE-10 PARA RIPS'!$A$6:B13180,2,0),"No especificado"))) -> Esguinces y torceduras que comprometen el ligamento cruzado (anterior) (posterior) de la rodilla | T14: =IF(P14<>"", IF(P14>0, IF(P14<=DATE(YEAR(P14),MONTH(P14),DAY(P14)), IF(P14>=DATE(YEAR(P14),MONTH(P14),1), IF(K14>10, C14, IF(SUMIFS($K:$K, $C:$C, C14, $P:$P, ">="&DATE(YEAR(P14),MONTH(P14),1), $P:$P, "<="&EOMONTH(P14,0))>10, C14, "")), ""))), "") | U14: =IF(AND(P14<>"", P14>=DATE(YEAR(P14),MONTH(P14),1), SUMIFS($K:$K, $C:$C, C14, $P:$P, ">="&DATE(YEAR(P14),MONTH(P14),1), $P:$P, "<="&EOMONTH(P14,0))>10), K14, "") | V14: =IF(AND(P14<>"", P14>=DATE(YEAR(P14),MONTH(P14),1), SUMIFS($K:$K, $C:$C, C14, $P:$P, ">="&DATE(YEAR(P14),MONTH(P14),1), $P:$P, "<="&EOMONTH(P14,0))>10), YEAR(P14), "") | W14: =IF(AND(P14<>"", P14>=DATE(YEAR(P14),MONTH(P14),1), SUMIFS($K:$K, $C:$C, C14, $P:$P, ">="&DATE(YEAR(P14),MONTH(P14),1), $P:$P, "<="&EOMONTH(P14,0))>10), TEXT(P14, "MMMM"), "") | X14: {=IF(AND(P14<>"", P14>=DATE(YEAR(P14),MONTH(P14),1), SUMIFS($K:$K, $C:$C, C14, $P:$P, ">="&DATE(YEAR(P14),MONTH(P14),1), $P:$P, "<="&EOMONTH(P14,0))>10), _xlfn.TEXTJOIN(", ", TRUE, _xlfn._xlws.FILTER($R:$R, ($C:$C=C14) * ($P:$P>=DATE(YEAR(P14),MONTH(P14),1)) * ($P:$P<=EOMONTH(P14,0)))), "")} | Y14: {=IF(AND(P14<>"", P14>=DATE(YEAR(P14),MONTH(P14),1), SUMIFS($K:$K, $C:$C, C14, $P:$P, ">="&DATE(YEAR(P14),MONTH(P14),1), $P:$P, "<="&EOMONTH(P14,0))>10), _xlfn.TEXTJOIN(", ", TRUE, _xlfn._xlws.FILTER($S:$S, ($C:$C=C14) * ($P:$P>=DATE(YEAR(P14),MONTH(P14),1)) * ($P:$P<=EOMONTH(P14,0)))), "")}
A15: 8 | B15: TEMPOACTIVA | C15: =_xlfn.XLOOKUP(D15,[1]!Data[CEDULA],[1]!Data[Nombre Completo],"No Existe",0,1) -> MARIA DEL CARMEN FERRER ALVIS | D15: 22506589 | E15: =IFERROR(_xlfn.NUMBERVALUE(Data[[#This Row],[CEDULA ]],",","."),_xlfn.NUMBERVALUE(Data[[#This Row],[CEDULA ]],".",",")) -> 22506589 | F15: =_xlfn.XLOOKUP(E15,[1]!Data[CEDULA],[1]!Data[CARGO],"No Existe",0,1) -> PORCINADOR | G15: =_xlfn.XLOOKUP(E15,[1]!Data[CEDULA],[1]!Data[EMPRESA DONDE PRESTA SERVICIO],"No Existe",0,1) -> COMFAMILIAR ATLANTICO | H15: =_xlfn.XLOOKUP(E15,[1]!Data[CEDULA],[1]!Data[UBICACIÓN],"No Existe",0,1) -> CENTRO DE PROCESAMIENTO | I15: MUJER | J15: =UPPER(TEXT(Data[[#This Row],[F. INICIO]],"mmmm")) -> ENERO | K15: 1 | L15: EPS | M15: ENFERMENDAD GENERAL | N15: =_xlfn.XLOOKUP(D15,[1]!Data[CEDULA],[1]!Data[EPS/SURA],"No Existe",0,1) -> SALUD TOTAL | O15: =YEAR(Data[[#This Row],[F. INICIO]]) -> 2024 | P15: 45300 | Q15: 45300 | R15: R51X | S15: =IF(Data[[#This Row],[TIPO DE INCAPACIDAD]]="LICENCIA DE PATERNIDAD","Licencia de paternidad",IF(Data[[#This Row],[TIPO DE INCAPACIDAD]]="LICENCIA DE LUTO","Licencia de Luto",_xlfn.IFNA(VLOOKUP(R15,'CIE-10 PARA RIPS'!$A$6:B13181,2,0),"No especificado"))) -> Cefalea | T15: =IF(P15<>"", IF(P15>0, IF(P15<=DATE(YEAR(P15),MONTH(P15),DAY(P15)), IF(P15>=DATE(YEAR(P15),MONTH(P15),1), IF(K15>10, C15, IF(SUMIFS($K:$K, $C:$C, C15, $P:$P, ">="&DATE(YEAR(P15),MONTH(P15),1), $P:$P, "<="&EOMONTH(P15,0))>10, C15, "")), ""))), "") | U15: =IF(AND(P15<>"", P15>=DATE(YEAR(P15),MONTH(P15),1), SUMIFS($K:$K, $C:$C, C15, $P:$P, ">="&DATE(YEAR(P15),MONTH(P15),1), $P:$P, "<="&EOMONTH(P15,0))>10), K15, "") | V15: =IF(AND(P15<>"", P15>=DATE(YEAR(P15),MONTH(P15),1), SUMIFS($K:$K, $C:$C, C15, $P:$P, ">="&DATE(YEAR(P15),MONTH(P15),1), $P:$P, "<="&EOMONTH(P15,0))>10), YEAR(P15), "") | W15: =IF(AND(P15<>"", P15>=DATE(YEAR(P15),MONTH(P15),1), SUMIFS($K:$K, $C:$C, C15, $P:$P, ">="&DATE(YEAR(P15),MONTH(P15),1), $P:$P, "<="&EOMONTH(P15,0))>10), TEXT(P15, "MMMM"), "") | X15: {=IF(AND(P15<>"", P15>=DATE(YEAR(P15),MONTH(P15),1), SUMIFS($K:$K, $C:$C, C15, $P:$P, ">="&DATE(YEAR(P15),MONTH(P15),1), $P:$P, "<="&EOMONTH(P15,0))>10), _xlfn.TEXTJOIN(", ", TRUE, _xlfn._xlws.FILTER($R:$R, ($C:$C=C15) * ($P:$P>=DATE(YEAR(P15),MONTH(P15),1)) * ($P:$P<=EOMONTH(P15,0)))), "")} | Y15: {=IF(AND(P15<>"", P15>=DATE(YEAR(P15),MONTH(P15),1), SUMIFS($K:$K, $C:$C, C15, $P:$P, ">="&DATE(YEAR(P15),MONTH(P15),1), $P:$P, "<="&EOMONTH(P15,0))>10), _xlfn.TEXTJOIN(", ", TRUE, _xlfn._xlws.FILTER($S:$S, ($C:$C=C15) * ($P:$P>=DATE(YEAR(P15),MONTH(P15),1)) * ($P:$P<=EOMONTH(P15,0)))), "")}
A16: 9 | B16: TEMPOACTIVA | C16: =_xlfn.XLOOKUP(D16,[1]!Data[CEDULA],[1]!Data[Nombre Completo],"No Existe",0,1) -> JHON JARLIS PABUENA EVERTSZ | D16: 72235252 | E16: =IFERROR(_xlfn.NUMBERVALUE(Data[[#This Row],[CEDULA ]],",","."),_xlfn.NUMBERVALUE(Data[[#This Row],[CEDULA ]],".",",")) -> 72235252 | F16: =_xlfn.XLOOKUP(E16,[1]!Data[CEDULA],[1]!Data[CARGO],"No Existe",0,1) -> MESERO | G16: =_xlfn.XLOOKUP(E16,[1]!Data[CEDULA],[1]!Data[EMPRESA DONDE PRESTA SERVICIO],"No Existe",0,1) -> COMFAMILIAR ATLANTICO | H16: =_xlfn.XLOOKUP(E16,[1]!Data[CEDULA],[1]!Data[UBICACIÓN],"No Existe",0,1) -> CENTRO RECREACIONAL CLL 48 | I16: HOMBRE | J16: =UPPER(TEXT(Data[[#This Row],[F. INICIO]],"mmmm")) -> ENERO | K16: 1 | L16: EPS | M16: ENFERMENDAD GENERAL | N16: =_xlfn.XLOOKUP(D16,[1]!Data[CEDULA],[1]!Data[EPS/SURA],"No Existe",0,1) -> EPS/SURA | O16: =YEAR(Data[[#This Row],[F. INICIO]]) -> 2024 | P16: 45296 | Q16: 45296 | R16: N390 | S16: =IF(Data[[#This Row],[TIPO DE INCAPACIDAD]]="LICENCIA DE PATERNIDAD","Licencia de paternidad",IF(Data[[#This Row],[TIPO DE INCAPACIDAD]]="LICENCIA DE LUTO","Licencia de Luto",_xlfn.IFNA(VLOOKUP(R16,'CIE-10 PARA RIPS'!$A$6:B13182,2,0),"No especificado"))) -> Infeccion de vias urinarias, sitio no especificado | T16: =IF(P16<>"", IF(P16>0, IF(P16<=DATE(YEAR(P16),MONTH(P16),DAY(P16)), IF(P16>=DATE(YEAR(P16),MONTH(P16),1), IF(K16>10, C16, IF(SUMIFS($K:$K, $C:$C, C16, $P:$P, ">="&DATE(YEAR(P16),MONTH(P16),1), $P:$P, "<="&EOMONTH(P16,0))>10, C16, "")), ""))), "") | U16: =IF(AND(P16<>"", P16>=DATE(YEAR(P16),MONTH(P16),1), SUMIFS($K:$K, $C:$C, C16, $P:$P, ">="&DATE(YEAR(P16),MONTH(P16),1), $P:$P, "<="&EOMONTH(P16,0))>10), K16, "") | V16: =IF(AND(P16<>"", P16>=DATE(YEAR(P16),MONTH(P16),1), SUMIFS($K:$K, $C:$C, C16, $P:$P, ">="&DATE(YEAR(P16),MONTH(P16),1), $P:$P, "<="&EOMONTH(P16,0))>10), YEAR(P16), "") | W16: =IF(AND(P16<>"", P16>=DATE(YEAR(P16),MONTH(P16),1), SUMIFS($K:$K, $C:$C, C16, $P:$P, ">="&DATE(YEAR(P16),MONTH(P16),1), $P:$P, "<="&EOMONTH(P16,0))>10), TEXT(P16, "MMMM"), "") | X16: {=IF(AND(P16<>"", P16>=DATE(YEAR(P16),MONTH(P16),1), SUMIFS($K:$K, $C:$C, C16, $P:$P, ">="&DATE(YEAR(P16),MONTH(P16),1), $P:$P, "<="&EOMONTH(P16,0))>10), _xlfn.TEXTJOIN(", ", TRUE, _xlfn._xlws.FILTER($R:$R, ($C:$C=C16) * ($P:$P>=DATE(YEAR(P16),MONTH(P16),1)) * ($P:$P<=EOMONTH(P16,0)))), "")} | Y16: {=IF(AND(P16<>"", P16>=DATE(YEAR(P16),MONTH(P16),1), SUMIFS($K:$K, $C:$C, C16, $P:$P, ">="&DATE(YEAR(P16),MONTH(P16),1), $P:$P, "<="&EOMONTH(P16,0))>10), _xlfn.TEXTJOIN(", ", TRUE, _xlfn._xlws.FILTER($S:$S, ($C:$C=C16) * ($P:$P>=DATE(YEAR(P16),MONTH(P16),1)) * ($P:$P<=EOMONTH(P16,0)))), "")}
A17: 10 | B17: TEMPOACTIVA | C17: =_xlfn.XLOOKUP(D17,[1]!Data[CEDULA],[1]!Data[Nombre Completo],"No Existe",0,1) -> ELIANA GISSELA CHARRIS GARCIA | D17: 1044392082 | E17: =IFERROR(_xlfn.NUMBERVALUE(Data[[#This Row],[CEDULA ]],",","."),_xlfn.NUMBERVALUE(Data[[#This Row],[CEDULA ]],".",",")) -> 1044392082 | F17: =_xlfn.XLOOKUP(E17,[1]!Data[CEDULA],[1]!Data[CARGO],"No Existe",0,1) -> AUXILIAR DE COCINA | G17: =_xlfn.XLOOKUP(E17,[1]!Data[CEDULA],[1]!Data[EMPRESA DONDE PRESTA SERVICIO],"No Existe",0,1) -> COMFAMILIAR ATLANTICO | H17: =_xlfn.XLOOKUP(E17,[1]!Data[CEDULA],[1]!Data[UBICACIÓN],"No Existe",0,1) -> TURIPANA MERCADEO | I17: MUJER | J17: =UPPER(TEXT(Data[[#This Row],[F. INICIO]],"mmmm")) -> ENERO | K17: 2 | L17: EPS | M17: ENFERMENDAD GENERAL | N17: =_xlfn.XLOOKUP(D17,[1]!Data[CEDULA],[1]!Data[EPS/SURA],"No Existe",0,1) -> NUEVA E.P.S. | O17: =YEAR(Data[[#This Row],[F. INICIO]]) -> 2024 | P17: 45298 | Q17: 45299 | R17: R101 | S17: =IF(Data[[#This Row],[TIPO DE INCAPACIDAD]]="LICENCIA DE PATERNIDAD","Licencia de paternidad",IF(Data[[#This Row],[TIPO DE INCAPACIDAD]]="LICENCIA DE LUTO","Licencia de Luto",_xlfn.IFNA(VLOOKUP(R17,'CIE-10 PARA RIPS'!$A$6:B13183,2,0),"No especificado"))) -> Dolor abdominal localizado en parte superior | T17: =IF(P17<>"", IF(P17>0, IF(P17<=DATE(YEAR(P17),MONTH(P17),DAY(P17)), IF(P17>=DATE(YEAR(P17),MONTH(P17),1), IF(K17>10, C17, IF(SUMIFS($K:$K, $C:$C, C17, $P:$P, ">="&DATE(YEAR(P17),MONTH(P17),1), $P:$P, "<="&EOMONTH(P17,0))>10, C17, "")), ""))), "") | U17: =IF(AND(P17<>"", P17>=DATE(YEAR(P17),MONTH(P17),1), SUMIFS($K:$K, $C:$C, C17, $P:$P, ">="&DATE(YEAR(P17),MONTH(P17),1), $P:$P, "<="&EOMONTH(P17,0))>10), K17, "") | V17: =IF(AND(P17<>"", P17>=DATE(YEAR(P17),MONTH(P17),1), SUMIFS($K:$K, $C:$C, C17, $P:$P, ">="&DATE(YEAR(P17),MONTH(P17),1), $P:$P, "<="&EOMONTH(P17,0))>10), YEAR(P17), "") | W17: =IF(AND(P17<>"", P17>=DATE(YEAR(P17),MONTH(P17),1), SUMIFS($K:$K, $C:$C, C17, $P:$P, ">="&DATE(YEAR(P17),MONTH(P17),1), $P:$P, "<="&EOMONTH(P17,0))>10), TEXT(P17, "MMMM"), "") | X17: {=IF(AND(P17<>"", P17>=DATE(YEAR(P17),MONTH(P17),1), SUMIFS($K:$K, $C:$C, C17, $P:$P, ">="&DATE(YEAR(P17),MONTH(P17),1), $P:$P, "<="&EOMONTH(P17,0))>10), _xlfn.TEXTJOIN(", ", TRUE, _xlfn._xlws.FILTER($R:$R, ($C:$C=C17) * ($P:$P>=DATE(YEAR(P17),MONTH(P17),1)) * ($P:$P<=EOMONTH(P17,0)))), "")} | Y17: {=IF(AND(P17<>"", P17>=DATE(YEAR(P17),MONTH(P17),1), SUMIFS($K:$K, $C:$C, C17, $P:$P, ">="&DATE(YEAR(P17),MONTH(P17),1), $P:$P, "<="&EOMONTH(P17,0))>10), _xlfn.TEXTJOIN(", ", TRUE, _xlfn._xlws.FILTER($S:$S, ($C:$C=C17) * ($P:$P>=DATE(YEAR(P17),MONTH(P17),1)) * ($P:$P<=EOMONTH(P17,0)))), "")}
A18: 11 | B18: TEMPOACTIVA | C18: =_xlfn.XLOOKUP(D18,[1]!Data[CEDULA],[1]!Data[Nombre Completo],"No Existe",0,1) -> MARICELA CALDERIN PERTUZ | D18: 32869679 | E18: =IFERROR(_xlfn.NUMBERVALUE(Data[[#This Row],[CEDULA ]],",","."),_xlfn.NUMBERVALUE(Data[[#This Row],[CEDULA ]],".",",")) -> 32869679 | F18: =_xlfn.XLOOKUP(E18,[1]!Data[CEDULA],[1]!Data[CARGO],"No Existe",0,1) -> SUPERNUMERARIO(A) | G18: =_xlfn.XLOOKUP(E18,[1]!Data[CEDULA],[1]!Data[EMPRESA DONDE PRESTA SERVICIO],"No Existe",0,1) -> COMFAMILIAR ATLANTICO | H18: =_xlfn.XLOOKUP(E18,[1]!Data[CEDULA],[1]!Data[UBICACIÓN],"No Existe",0,1) -> SEDE CARIBE | I18: MUJER | J18: =UPPER(TEXT(Data[[#This Row],[F. INICIO]],"mmmm")) -> ENERO | K18: 1 | L18: EPS | M18: ENFERMENDAD GENERAL | N18: =_xlfn.XLOOKUP(D18,[1]!Data[CEDULA],[1]!Data[EPS/SURA],"No Existe",0,1) -> EPS/SURA | O18: =YEAR(Data[[#This Row],[F. INICIO]]) -> 2024 | P18: 45295 | Q18: 45295 | R18: H82X | S18: =IF(Data[[#This Row],[TIPO DE INCAPACIDAD]]="LICENCIA DE PATERNIDAD","Licencia de paternidad",IF(Data[[#This Row],[TIPO DE INCAPACIDAD]]="LICENCIA DE LUTO","Licencia de Luto",_xlfn.IFNA(VLOOKUP(R18,'CIE-10 PARA RIPS'!$A$6:B13184,2,0),"No especificado"))) -> Sindromes vertiginosos en enfermedades clasificadas en otra parte | T18: =IF(P18<>"", IF(P18>0, IF(P18<=DATE(YEAR(P18),MONTH(P18),DAY(P18)), IF(P18>=DATE(YEAR(P18),MONTH(P18),1), IF(K18>10, C18, IF(SUMIFS($K:$K, $C:$C, C18, $P:$P, ">="&DATE(YEAR(P18),MONTH(P18),1), $P:$P, "<="&EOMONTH(P18,0))>10, C18, "")), ""))), "") | U18: =IF(AND(P18<>"", P18>=DATE(YEAR(P18),MONTH(P18),1), SUMIFS($K:$K, $C:$C, C18, $P:$P, ">="&DATE(YEAR(P18),MONTH(P18),1), $P:$P, "<="&EOMONTH(P18,0))>10), K18, "") | V18: =IF(AND(P18<>"", P18>=DATE(YEAR(P18),MONTH(P18),1), SUMIFS($K:$K, $C:$C, C18, $P:$P, ">="&DATE(YEAR(P18),MONTH(P18),1), $P:$P, "<="&EOMONTH(P18,0))>10), YEAR(P18), "") | W18: =IF(AND(P18<>"", P18>=DATE(YEAR(P18),MONTH(P18),1), SUMIFS($K:$K, $C:$C, C18, $P:$P, ">="&DATE(YEAR(P18),MONTH(P18),1), $P:$P, "<="&EOMONTH(P18,0))>10), TEXT(P18, "MMMM"), "") | X18: {=IF(AND(P18<>"", P18>=DATE(YEAR(P18),MONTH(P18),1), SUMIFS($K:$K, $C:$C, C18, $P:$P, ">="&DATE(YEAR(P18),MONTH(P18),1), $P:$P, "<="&EOMONTH(P18,0))>10), _xlfn.TEXTJOIN(", ", TRUE, _xlfn._xlws.FILTER($R:$R, ($C:$C=C18) * ($P:$P>=DATE(YEAR(P18),MONTH(P18),1)) * ($P:$P<=EOMONTH(P18,0)))), "")} | Y18: {=IF(AND(P18<>"", P18>=DATE(YEAR(P18),MONTH(P18),1), SUMIFS($K:$K, $C:$C, C18, $P:$P, ">="&DATE(YEAR(P18),MONTH(P18),1), $P:$P, "<="&EOMONTH(P18,0))>10), _xlfn.TEXTJOIN(", ", TRUE, _xlfn._xlws.FILTER($S:$S, ($C:$C=C18) * ($P:$P>=DATE(YEAR(P18),MONTH(P18),1)) * ($P:$P<=EOMONTH(P18,0)))), "")}
A19: 12 | B19: TEMPOACTIVA | C19: =_xlfn.XLOOKUP(D19,[1]!Data[CEDULA],[1]!Data[Nombre Completo],"No Existe",0,1) -> DIONI DE JESUS ECHEVERRIA CASTRO | D19: 1129566741 | E19: =IFERROR(_xlfn.NUMBERVALUE(Data[[#This Row],[CEDULA ]],",","."),_xlfn.NUMBERVALUE(Data[[#This Row],[CEDULA ]],".",",")) -> 1129566741 | F19: =_xlfn.XLOOKUP(E19,[1]!Data[CEDULA],[1]!Data[CARGO],"No Existe",0,1) -> COCINERO 1 | G19: =_xlfn.XLOOKUP(E19,[1]!Data[CEDULA],[1]!Data[EMPRESA DONDE PRESTA SERVICIO],"No Existe",0,1) -> COMFAMILIAR ATLANTICO | H19: =_xlfn.XLOOKUP(E19,[1]!Data[CEDULA],[1]!Data[UBICACIÓN],"No Existe",0,1) -> SEDE NORTE MERCADEO | I19: HOMBRE | J19: =UPPER(TEXT(Data[[#This Row],[F. INICIO]],"mmmm")) -> ENERO | K19: 2 | L19: EPS | M19: ENFERMENDAD GENERAL | N19: =_xlfn.XLOOKUP(D19,[1]!Data[CEDULA],[1]!Data[EPS/SURA],"No Existe",0,1) -> SALUD TOTAL | O19: =YEAR(Data[[#This Row],[F. INICIO]]) -> 2024 | P19: 45292 | Q19: 45293 | R19: A90X | S19: =IF(Data[[#This Row],[TIPO DE INCAPACIDAD]]="LICENCIA DE PATERNIDAD","Licencia de paternidad",IF(Data[[#This Row],[TIPO DE INCAPACIDAD]]="LICENCIA DE LUTO","Licencia de Luto",_xlfn.IFNA(VLOOKUP(R19,'CIE-10 PARA RIPS'!$A$6:B13185,2,0),"No especificado"))) -> Ciertas enfermedades infecciosas y parasitarias (A00-B99). | T19: =IF(P19<>"", IF(P19>0, IF(P19<=DATE(YEAR(P19),MONTH(P19),DAY(P19)), IF(P19>=DATE(YEAR(P19),MONTH(P19),1), IF(K19>10, C19, IF(SUMIFS($K:$K, $C:$C, C19, $P:$P, ">="&DATE(YEAR(P19),MONTH(P19),1), $P:$P, "<="&EOMONTH(P19,0))>10, C19, "")), ""))), "") | U19: =IF(AND(P19<>"", P19>=DATE(YEAR(P19),MONTH(P19),1), SUMIFS($K:$K, $C:$C, C19, $P:$P, ">="&DATE(YEAR(P19),MONTH(P19),1), $P:$P, "<="&EOMONTH(P19,0))>10), K19, "") | V19: =IF(AND(P19<>"", P19>=DATE(YEAR(P19),MONTH(P19),1), SUMIFS($K:$K, $C:$C, C19, $P:$P, ">="&DATE(YEAR(P19),MONTH(P19),1), $P:$P, "<="&EOMONTH(P19,0))>10), YEAR(P19), "") | W19: =IF(AND(P19<>"", P19>=DATE(YEAR(P19),MONTH(P19),1), SUMIFS($K:$K, $C:$C, C19, $P:$P, ">="&DATE(YEAR(P19),MONTH(P19),1), $P:$P, "<="&EOMONTH(P19,0))>10), TEXT(P19, "MMMM"), "") | X19: {=IF(AND(P19<>"", P19>=DATE(YEAR(P19),MONTH(P19),1), SUMIFS($K:$K, $C:$C, C19, $P:$P, ">="&DATE(YEAR(P19),MONTH(P19),1), $P:$P, "<="&EOMONTH(P19,0))>10), _xlfn.TEXTJOIN(", ", TRUE, _xlfn._xlws.FILTER($R:$R, ($C:$C=C19) * ($P:$P>=DATE(YEAR(P19),MONTH(P19),1)) * ($P:$P<=EOMONTH(P19,0)))), "")} | Y19: {=IF(AND(P19<>"", P19>=DATE(YEAR(P19),MONTH(P19),1), SUMIFS($K:$K, $C:$C, C19, $P:$P, ">="&DATE(YEAR(P19),MONTH(P19),1), $P:$P, "<="&EOMONTH(P19,0))>10), _xlfn.TEXTJOIN(", ", TRUE, _xlfn._xlws.FILTER($S:$S, ($C:$C=C19) * ($P:$P>=DATE(YEAR(P19),MONTH(P19),1)) * ($P:$P<=EOMONTH(P19,0)))), "")}
A20: 13 | B20: TEMPOACTIVA | C20: =_xlfn.XLOOKUP(D20,[1]!Data[CEDULA],[1]!Data[Nombre Completo],"No Existe",0,1) -> LILIAN PAOLA NARVAEZ REDONDO | D20: 1007176091 | E20: =IFERROR(_xlfn.NUMBERVALUE(Data[[#This Row],[CEDULA ]],",","."),_xlfn.NUMBERVALUE(Data[[#This Row],[CEDULA ]],".",",")) -> 1007176091 | F20: =_xlfn.XLOOKUP(E20,[1]!Data[CEDULA],[1]!Data[CARGO],"No Existe",0,1) -> AUXILIAR DE ARCHIVO | G20: =_xlfn.XLOOKUP(E20,[1]!Data[CEDULA],[1]!Data[EMPRESA DONDE PRESTA SERVICIO],"No Existe",0,1) -> TEMPOACTIVA EST S.A.S. | H20: =_xlfn.XLOOKUP(E20,[1]!Data[CEDULA],[1]!Data[UBICACIÓN],"No Existe",0,1) -> SISTEMAS | I20: MUJER | J20: =UPPER(TEXT(Data[[#This Row],[F. INICIO]],"mmmm")) -> ENERO | K20: 2 | L20: EPS | M20: ENFERMENDAD GENERAL | N20: =_xlfn.XLOOKUP(D20,[1]!Data[CEDULA],[1]!Data[EPS/SURA],"No Existe",0,1) -> EPS/SURA | O20: =YEAR(Data[[#This Row],[F. INICIO]]) -> 2024 | P20: 45303 | Q20: 45304 | R20: A970 | S20: =IF(Data[[#This Row],[TIPO DE INCAPACIDAD]]="LICENCIA DE PATERNIDAD","Licencia de paternidad",IF(Data[[#This Row],[TIPO DE INCAPACIDAD]]="LICENCIA DE LUTO","Licencia de Luto",_xlfn.IFNA(VLOOKUP(R20,'CIE-10 PARA RIPS'!$A$6:B13186,2,0),"No especificado"))) -> Dengue sin signos de alarma | T20: =IF(P20<>"", IF(P20>0, IF(P20<=DATE(YEAR(P20),MONTH(P20),DAY(P20)), IF(P20>=DATE(YEAR(P20),MONTH(P20),1), IF(K20>10, C20, IF(SUMIFS($K:$K, $C:$C, C20, $P:$P, ">="&DATE(YEAR(P20),MONTH(P20),1), $P:$P, "<="&EOMONTH(P20,0))>10, C20, "")), ""))), "") | U20: =IF(AND(P20<>"", P20>=DATE(YEAR(P20),MONTH(P20),1), SUMIFS($K:$K, $C:$C, C20, $P:$P, ">="&DATE(YEAR(P20),MONTH(P20),1), $P:$P, "<="&EOMONTH(P20,0))>10), K20, "") | V20: =IF(AND(P20<>"", P20>=DATE(YEAR(P20),MONTH(P20),1), SUMIFS($K:$K, $C:$C, C20, $P:$P, ">="&DATE(YEAR(P20),MONTH(P20),1), $P:$P, "<="&EOMONTH(P20,0))>10), YEAR(P20), "") | W20: =IF(AND(P20<>"", P20>=DATE(YEAR(P20),MONTH(P20),1), SUMIFS($K:$K, $C:$C, C20, $P:$P, ">="&DATE(YEAR(P20),MONTH(P20),1), $P:$P, "<="&EOMONTH(P20,0))>10), TEXT(P20, "MMMM"), "") | X20: {=IF(AND(P20<>"", P20>=DATE(YEAR(P20),MONTH(P20),1), SUMIFS($K:$K, $C:$C, C20, $P:$P, ">="&DATE(YEAR(P20),MONTH(P20),1), $P:$P, "<="&EOMONTH(P20,0))>10), _xlfn.TEXTJOIN(", ", TRUE, _xlfn._xlws.FILTER($R:$R, ($C:$C=C20) * ($P:$P>=DATE(YEAR(P20),MONTH(P20),1)) * ($P:$P<=EOMONTH(P20,0)))), "")} | Y20: {=IF(AND(P20<>"", P20>=DATE(YEAR(P20),MONTH(P20),1), SUMIFS($K:$K, $C:$C, C20, $P:$P, ">="&DATE(YEAR(P20),MONTH(P20),1), $P:$P, "<="&EOMONTH(P20,0))>10), _xlfn.TEXTJOIN(", ", TRUE, _xlfn._xlws.FILTER($S:$S, ($C:$C=C20) * ($P:$P>=DATE(YEAR(P20),MONTH(P20),1)) * ($P:$P<=EOMONTH(P20,0)))), "")}
A21: 14 | B21: TEMPOACTIVA | C21: =_xlfn.XLOOKUP(D21,[1]!Data[CEDULA],[1]!Data[Nombre Completo],"No Existe",0,1) -> CARELIS DEL CARMEN CARIDAD CALDERON | D21: 1047239028 | E21: =IFERROR(_xlfn.NUMBERVALUE(Data[[#This Row],[CEDULA ]],",","."),_xlfn.NUMBERVALUE(Data[[#This Row],[CEDULA ]],".",",")) -> 1047239028 | F21: =_xlfn.XLOOKUP(E21,[1]!Data[CEDULA],[1]!Data[CARGO],"No Existe",0,1) -> SUPERNUMERARIO(A) | G21: =_xlfn.XLOOKUP(E21,[1]!Data[CEDULA],[1]!Data[EMPRESA DONDE PRESTA SERVICIO],"No Existe",0,1) -> COMFAMILIAR ATLANTICO | H21: =_xlfn.XLOOKUP(E21,[1]!Data[CEDULA],[1]!Data[UBICACIÓN],"No Existe",0,1) -> SEDE CARIBE MERCADEO | I21: MUJER | J21: =UPPER(TEXT(Data[[#This Row],[F. INICIO]],"mmmm")) -> ENERO | K21: 2 | L21: EPS | M21: ENFERMENDAD GENERAL | N21: =_xlfn.XLOOKUP(D21,[1]!Data[CEDULA],[1]!Data[EPS/SURA],"No Existe",0,1) -> MUTUALSER | O21: =YEAR(Data[[#This Row],[F. INICIO]]) -> 2024 | P21: 45308 | Q21: 45309 | R21: J00X | S21: =IF(Data[[#This Row],[TIPO DE INCAPACIDAD]]="LICENCIA DE PATERNIDAD","Licencia de paternidad",IF(Data[[#This Row],[TIPO DE INCAPACIDAD]]="LICENCIA DE LUTO","Licencia de Luto",_xlfn.IFNA(VLOOKUP(R21,'CIE-10 PARA RIPS'!$A$6:B13187,2,0),"No especificado"))) -> Rinofaringitis aguda [resfriado comun] | T21: =IF(P21<>"", IF(P21>0, IF(P21<=DATE(YEAR(P21),MONTH(P21),DAY(P21)), IF(P21>=DATE(YEAR(P21),MONTH(P21),1), IF(K21>10, C21, IF(SUMIFS($K:$K, $C:$C, C21, $P:$P, ">="&DATE(YEAR(P21),MONTH(P21),1), $P:$P, "<="&EOMONTH(P21,0))>10, C21, "")), ""))), "") | U21: =IF(AND(P21<>"", P21>=DATE(YEAR(P21),MONTH(P21),1), SUMIFS($K:$K, $C:$C, C21, $P:$P, ">="&DATE(YEAR(P21),MONTH(P21),1), $P:$P, "<="&EOMONTH(P21,0))>10), K21, "") | V21: =IF(AND(P21<>"", P21>=DATE(YEAR(P21),MONTH(P21),1), SUMIFS($K:$K, $C:$C, C21, $P:$P, ">="&DATE(YEAR(P21),MONTH(P21),1), $P:$P, "<="&EOMONTH(P21,0))>10), YEAR(P21), "") | W21: =IF(AND(P21<>"", P21>=DATE(YEAR(P21),MONTH(P21),1), SUMIFS($K:$K, $C:$C, C21, $P:$P, ">="&DATE(YEAR(P21),MONTH(P21),1), $P:$P, "<="&EOMONTH(P21,0))>10), TEXT(P21, "MMMM"), "") | X21: {=IF(AND(P21<>"", P21>=DATE(YEAR(P21),MONTH(P21),1), SUMIFS($K:$K, $C:$C, C21, $P:$P, ">="&DATE(YEAR(P21),MONTH(P21),1), $P:$P, "<="&EOMONTH(P21,0))>10), _xlfn.TEXTJOIN(", ", TRUE, _xlfn._xlws.FILTER($R:$R, ($C:$C=C21) * ($P:$P>=DATE(YEAR(P21),MONTH(P21),1)) * ($P:$P<=EOMONTH(P21,0)))), "")} | Y21: {=IF(AND(P21<>"", P21>=DATE(YEAR(P21),MONTH(P21),1), SUMIFS($K:$K, $C:$C, C21, $P:$P, ">="&DATE(YEAR(P21),MONTH(P21),1), $P:$P, "<="&EOMONTH(P21,0))>10), _xlfn.TEXTJOIN(", ", TRUE, _xlfn._xlws.FILTER($S:$S, ($C:$C=C21) * ($P:$P>=DATE(YEAR(P21),MONTH(P21),1)) * ($P:$P<=EOMONTH(P21,0)))), "")}
A22: 15 | B22: TEMPOACTIVA | C22: =_xlfn.XLOOKUP(D22,[1]!Data[CEDULA],[1]!Data[Nombre Completo],"No Existe",0,1) -> CARELIS DEL CARMEN CARIDAD CALDERON | D22: 1047239028 | E22: =IFERROR(_xlfn.NUMBERVALUE(Data[[#This Row],[CEDULA ]],",","."),_xlfn.NUMBERVALUE(Data[[#This Row],[CEDULA ]],".",",")) -> 1047239028 | F22: =_xlfn.XLOOKUP(E22,[1]!Data[CEDULA],[1]!Data[CARGO],"No Existe",0,1) -> SUPERNUMERARIO(A) | G22: =_xlfn.XLOOKUP(E22,[1]!Data[CEDULA],[1]!Data[EMPRESA DONDE PRESTA SERVICIO],"No Existe",0,1) -> COMFAMILIAR ATLANTICO | H22: =_xlfn.XLOOKUP(E22,[1]!Data[CEDULA],[1]!Data[UBICACIÓN],"No Existe",0,1) -> SEDE CARIBE MERCADEO | I22: MUJER | J22: =UPPER(TEXT(Data[[#This Row],[F. INICIO]],"mmmm")) -> ENERO | K22: 2 | L22: EPS | M22: ENFERMENDAD GENERAL | N22: =_xlfn.XLOOKUP(D22,[1]!Data[CEDULA],[1]!Data[EPS/SURA],"No Existe",0,1) -> MUTUALSER | O22: =YEAR(Data[[#This Row],[F. INICIO]]) -> 2024 | P22: 45310 | Q22: 45311 | R22: J039 | S22: =IF(Data[[#This Row],[TIPO DE INCAPACIDAD]]="LICENCIA DE PATERNIDAD","Licencia de paternidad",IF(Data[[#This Row],[TIPO DE INCAPACIDAD]]="LICENCIA DE LUTO","Licencia de Luto",_xlfn.IFNA(VLOOKUP(R22,'CIE-10 PARA RIPS'!$A$6:B13188,2,0),"No especificado"))) -> Amigdalitis aguda, no especificada | T22: =IF(P22<>"", IF(P22>0, IF(P22<=DATE(YEAR(P22),MONTH(P22),DAY(P22)), IF(P22>=DATE(YEAR(P22),MONTH(P22),1), IF(K22>10, C22, IF(SUMIFS($K:$K, $C:$C, C22, $P:$P, ">="&DATE(YEAR(P22),MONTH(P22),1), $P:$P, "<="&EOMONTH(P22,0))>10, C22, "")), ""))), "") | U22: =IF(AND(P22<>"", P22>=DATE(YEAR(P22),MONTH(P22),1), SUMIFS($K:$K, $C:$C, C22, $P:$P, ">="&DATE(YEAR(P22),MONTH(P22),1), $P:$P, "<="&EOMONTH(P22,0))>10), K22, "") | V22: =IF(AND(P22<>"", P22>=DATE(YEAR(P22),MONTH(P22),1), SUMIFS($K:$K, $C:$C, C22, $P:$P, ">="&DATE(YEAR(P22),MONTH(P22),1), $P:$P, "<="&EOMONTH(P22,0))>10), YEAR(P22), "") | W22: =IF(AND(P22<>"", P22>=DATE(YEAR(P22),MONTH(P22),1), SUMIFS($K:$K, $C:$C, C22, $P:$P, ">="&DATE(YEAR(P22),MONTH(P22),1), $P:$P, "<="&EOMONTH(P22,0))>10), TEXT(P22, "MMMM"), "") | X22: {=IF(AND(P22<>"", P22>=DATE(YEAR(P22),MONTH(P22),1), SUMIFS($K:$K, $C:$C, C22, $P:$P, ">="&DATE(YEAR(P22),MONTH(P22),1), $P:$P, "<="&EOMONTH(P22,0))>10), _xlfn.TEXTJOIN(", ", TRUE, _xlfn._xlws.FILTER($R:$R, ($C:$C=C22) * ($P:$P>=DATE(YEAR(P22),MONTH(P22),1)) * ($P:$P<=EOMONTH(P22,0)))), "")} | Y22: {=IF(AND(P22<>"", P22>=DATE(YEAR(P22),MONTH(P22),1), SUMIFS($K:$K, $C:$C, C22, $P:$P, ">="&DATE(YEAR(P22),MONTH(P22),1), $P:$P, "<="&EOMONTH(P22,0))>10), _xlfn.TEXTJOIN(", ", TRUE, _xlfn._xlws.FILTER($S:$S, ($C:$C=C22) * ($P:$P>=DATE(YEAR(P22),MONTH(P22),1)) * ($P:$P<=EOMONTH(P22,0)))), "")}
A23: 16 | B23: TEMPOACTIVA | C23: =_xlfn.XLOOKUP(D23,[1]!Data[CEDULA],[1]!Data[Nombre Completo],"No Existe",0,1) -> ZENITH SUAREZ PEREZ | D23: 22583181 | E23: =IFERROR(_xlfn.NUMBERVALUE(Data[[#This Row],[CEDULA ]],",","."),_xlfn.NUMBERVALUE(Data[[#This Row],[CEDULA ]],".",",")) -> 22583181 | F23: =_xlfn.XLOOKUP(E23,[1]!Data[CEDULA],[1]!Data[CARGO],"No Existe",0,1) -> SUPERNUMERARIO(A) | G23: =_xlfn.XLOOKUP(E23,[1]!Data[CEDULA],[1]!Data[EMPRESA DONDE PRESTA SERVICIO],"No Existe",0,1) -> COMFAMILIAR ATLANTICO | H23: =_xlfn.XLOOKUP(E23,[1]!Data[CEDULA],[1]!Data[UBICACIÓN],"No Existe",0,1) -> SALGARITO MERCADEO | I23: MUJER | J23: =UPPER(TEXT(Data[[#This Row],[F. INICIO]],"mmmm")) -> ENERO | K23: 6 | L23: ARL | M23: ACCIDENTE LABORAL | N23: =_xlfn.XLOOKUP(D23,[1]!Data[CEDULA],[1]!Data[EPS/SURA],"No Existe",0,1) -> NUEVA E.P.S. | O23: =YEAR(Data[[#This Row],[F. INICIO]]) -> 2024 | P23: 45307 | Q23: 45312 | R23: S611 | S23: =IF(Data[[#This Row],[TIPO DE INCAPACIDAD]]="LICENCIA DE PATERNIDAD","Licencia de paternidad",IF(Data[[#This Row],[TIPO DE INCAPACIDAD]]="LICENCIA DE LUTO","Licencia de Luto",_xlfn.IFNA(VLOOKUP(R23,'CIE-10 PARA RIPS'!$A$6:B13189,2,0),"No especificado"))) -> Herida de dedo(s) de la mano, con dano de la(s) una(s) | T23: =IF(P23<>"", IF(P23>0, IF(P23<=DATE(YEAR(P23),MONTH(P23),DAY(P23)), IF(P23>=DATE(YEAR(P23),MONTH(P23),1), IF(K23>10, C23, IF(SUMIFS($K:$K, $C:$C, C23, $P:$P, ">="&DATE(YEAR(P23),MONTH(P23),1), $P:$P, "<="&EOMONTH(P23,0))>10, C23, "")), ""))), "") | U23: =IF(AND(P23<>"", P23>=DATE(YEAR(P23),MONTH(P23),1), SUMIFS($K:$K, $C:$C, C23, $P:$P, ">="&DATE(YEAR(P23),MONTH(P23),1), $P:$P, "<="&EOMONTH(P23,0))>10), K23, "") | V23: =IF(AND(P23<>"", P23>=DATE(YEAR(P23),MONTH(P23),1), SUMIFS($K:$K, $C:$C, C23, $P:$P, ">="&DATE(YEAR(P23),MONTH(P23),1), $P:$P, "<="&EOMONTH(P23,0))>10), YEAR(P23), "") | W23: =IF(AND(P23<>"", P23>=DATE(YEAR(P23),MONTH(P23),1), SUMIFS($K:$K, $C:$C, C23, $P:$P, ">="&DATE(YEAR(P23),MONTH(P23),1), $P:$P, "<="&EOMONTH(P23,0))>10), TEXT(P23, "MMMM"), "") | X23: {=IF(AND(P23<>"", P23>=DATE(YEAR(P23),MONTH(P23),1), SUMIFS($K:$K, $C:$C, C23, $P:$P, ">="&DATE(YEAR(P23),MONTH(P23),1), $P:$P, "<="&EOMONTH(P23,0))>10), _xlfn.TEXTJOIN(", ", TRUE, _xlfn._xlws.FILTER($R:$R, ($C:$C=C23) * ($P:$P>=DATE(YEAR(P23),MONTH(P23),1)) * ($P:$P<=EOMONTH(P23,0)))), "")} | Y23: {=IF(AND(P23<>"", P23>=DATE(YEAR(P23),MONTH(P23),1), SUMIFS($K:$K, $C:$C, C23, $P:$P, ">="&DATE(YEAR(P23),MONTH(P23),1), $P:$P, "<="&EOMONTH(P23,0))>10), _xlfn.TEXTJOIN(", ", TRUE, _xlfn._xlws.FILTER($S:$S, ($C:$C=C23) * ($P:$P>=DATE(YEAR(P23),MONTH(P23),1)) * ($P:$P<=EOMONTH(P23,0)))), "")}
A24: 17 | B24: TEMPOACTIVA | C24: =_xlfn.XLOOKUP(D24,[1]!Data[CEDULA],[1]!Data[Nombre Completo],"No Existe",0,1) -> CARLOS ALBERTO TORRES LEON | D24: 72051803 | E24: =IFERROR(_xlfn.NUMBERVALUE(Data[[#This Row],[CEDULA ]],",","."),_xlfn.NUMBERVALUE(Data[[#This Row],[CEDULA ]],".",",")) -> 72051803 | F24: =_xlfn.XLOOKUP(E24,[1]!Data[CEDULA],[1]!Data[CARGO],"No Existe",0,1) -> BARMAN | G24: =_xlfn.XLOOKUP(E24,[1]!Data[CEDULA],[1]!Data[EMPRESA DONDE PRESTA SERVICIO],"No Existe",0,1) -> COMFAMILIAR ATLANTICO | H24: =_xlfn.XLOOKUP(E24,[1]!Data[CEDULA],[1]!Data[UBICACIÓN],"No Existe",0,1) -> SEDE CARIBE | I24: HOMBRE | J24: =UPPER(TEXT(Data[[#This Row],[F. INICIO]],"mmmm")) -> ENERO | K24: 2 | L24: EPS | M24: ENFERMENDAD GENERAL | N24: =_xlfn.XLOOKUP(D24,[1]!Data[CEDULA],[1]!Data[EPS/SURA],"No Existe",0,1) -> E.P.S SANITAS | O24: =YEAR(Data[[#This Row],[F. INICIO]]) -> 2024 | P24: 45316 | Q24: 45317 | R24: R101 | S24: =IF(Data[[#This Row],[TIPO DE INCAPACIDAD]]="LICENCIA DE PATERNIDAD","Licencia de paternidad",IF(Data[[#This Row],[TIPO DE INCAPACIDAD]]="LICENCIA DE LUTO","Licencia de Luto",_xlfn.IFNA(VLOOKUP(R24,'CIE-10 PARA RIPS'!$A$6:B13190,2,0),"No especificado"))) -> Dolor abdominal localizado en parte superior | T24: =IF(P24<>"", IF(P24>0, IF(P24<=DATE(YEAR(P24),MONTH(P24),DAY(P24)), IF(P24>=DATE(YEAR(P24),MONTH(P24),1), IF(K24>10, C24, IF(SUMIFS($K:$K, $C:$C, C24, $P:$P, ">="&DATE(YEAR(P24),MONTH(P24),1), $P:$P, "<="&EOMONTH(P24,0))>10, C24, "")), ""))), "") | U24: =IF(AND(P24<>"", P24>=DATE(YEAR(P24),MONTH(P24),1), SUMIFS($K:$K, $C:$C, C24, $P:$P, ">="&DATE(YEAR(P24),MONTH(P24),1), $P:$P, "<="&EOMONTH(P24,0))>10), K24, "") | V24: =IF(AND(P24<>"", P24>=DATE(YEAR(P24),MONTH(P24),1), SUMIFS($K:$K, $C:$C, C24, $P:$P, ">="&DATE(YEAR(P24),MONTH(P24),1), $P:$P, "<="&EOMONTH(P24,0))>10), YEAR(P24), "") | W24: =IF(AND(P24<>"", P24>=DATE(YEAR(P24),MONTH(P24),1), SUMIFS($K:$K, $C:$C, C24, $P:$P, ">="&DATE(YEAR(P24),MONTH(P24),1), $P:$P, "<="&EOMONTH(P24,0))>10), TEXT(P24, "MMMM"), "") | X24: {=IF(AND(P24<>"", P24>=DATE(YEAR(P24),MONTH(P24),1), SUMIFS($K:$K, $C:$C, C24, $P:$P, ">="&DATE(YEAR(P24),MONTH(P24),1), $P:$P, "<="&EOMONTH(P24,0))>10), _xlfn.TEXTJOIN(", ", TRUE, _xlfn._xlws.FILTER($R:$R, ($C:$C=C24) * ($P:$P>=DATE(YEAR(P24),MONTH(P24),1)) * ($P:$P<=EOMONTH(P24,0)))), "")} | Y24: {=IF(AND(P24<>"", P24>=DATE(YEAR(P24),MONTH(P24),1), SUMIFS($K:$K, $C:$C, C24, $P:$P, ">="&DATE(YEAR(P24),MONTH(P24),1), $P:$P, "<="&EOMONTH(P24,0))>10), _xlfn.TEXTJOIN(", ", TRUE, _xlfn._xlws.FILTER($S:$S, ($C:$C=C24) * ($P:$P>=DATE(YEAR(P24),MONTH(P24),1)) * ($P:$P<=EOMONTH(P24,0)))), "")}
A25: 18 | B25: TEMPOACTIVA | C25: =_xlfn.XLOOKUP(D25,[1]!Data[CEDULA],[1]!Data[Nombre Completo],"No Existe",0,1) -> LORAINNE PAOLA MOLINA PADILLA | D25: 1044392755 | E25: =IFERROR(_xlfn.NUMBERVALUE(Data[[#This Row],[CEDULA ]],",","."),_xlfn.NUMBERVALUE(Data[[#This Row],[CEDULA ]],".",",")) -> 1044392755 | F25: =_xlfn.XLOOKUP(E25,[1]!Data[CEDULA],[1]!Data[CARGO],"No Existe",0,1) -> COCINERO 1 | G25: =_xlfn.XLOOKUP(E25,[1]!Data[CEDULA],[1]!Data[EMPRESA DONDE PRESTA SERVICIO],"No Existe",0,1) -> COMFAMILIAR ATLANTICO | H25: =_xlfn.XLOOKUP(E25,[1]!Data[CEDULA],[1]!Data[UBICACIÓN],"No Existe",0,1) -> TURIPANA MERCADEO | I25: MUJER | J25: =UPPER(TEXT(Data[[#This Row],[F. INICIO]],"mmmm")) -> ENERO | K25: 1 | L25: EPS | M25: ENFERMENDAD GENERAL | N25: =_xlfn.XLOOKUP(D25,[1]!Data[CEDULA],[1]!Data[EPS/SURA],"No Existe",0,1) -> FAMISANAR | O25: =YEAR(Data[[#This Row],[F. INICIO]]) -> 2024 | P25: 45322 | Q25: 45322 | R25: J068 | S25: =IF(Data[[#This Row],[TIPO DE INCAPACIDAD]]="LICENCIA DE PATERNIDAD","Licencia de paternidad",IF(Data[[#This Row],[TIPO DE INCAPACIDAD]]="LICENCIA DE LUTO","Licencia de Luto",_xlfn.IFNA(VLOOKUP(R25,'CIE-10 PARA RIPS'!$A$6:B13193,2,0),"No especificado"))) -> Otras infecciones agudas de sitios multiples de las vias respiratorias superiores | T25: =IF(P25<>"", IF(P25>0, IF(P25<=DATE(YEAR(P25),MONTH(P25),DAY(P25)), IF(P25>=DATE(YEAR(P25),MONTH(P25),1), IF(K25>10, C25, IF(SUMIFS($K:$K, $C:$C, C25, $P:$P, ">="&DATE(YEAR(P25),MONTH(P25),1), $P:$P, "<="&EOMONTH(P25,0))>10, C25, "")), ""))), "") | U25: =IF(AND(P25<>"", P25>=DATE(YEAR(P25),MONTH(P25),1), SUMIFS($K:$K, $C:$C, C25, $P:$P, ">="&DATE(YEAR(P25),MONTH(P25),1), $P:$P, "<="&EOMONTH(P25,0))>10), K25, "") | V25: =IF(AND(P25<>"", P25>=DATE(YEAR(P25),MONTH(P25),1), SUMIFS($K:$K, $C:$C, C25, $P:$P, ">="&DATE(YEAR(P25),MONTH(P25),1), $P:$P, "<="&EOMONTH(P25,0))>10), YEAR(P25), "") | W25: =IF(AND(P25<>"", P25>=DATE(YEAR(P25),MONTH(P25),1), SUMIFS($K:$K, $C:$C, C25, $P:$P, ">="&DATE(YEAR(P25),MONTH(P25),1), $P:$P, "<="&EOMONTH(P25,0))>10), TEXT(P25, "MMMM"), "") | X25: {=IF(AND(P25<>"", P25>=DATE(YEAR(P25),MONTH(P25),1), SUMIFS($K:$K, $C:$C, C25, $P:$P, ">="&DATE(YEAR(P25),MONTH(P25),1), $P:$P, "<="&EOMONTH(P25,0))>10), _xlfn.TEXTJOIN(", ", TRUE, _xlfn._xlws.FILTER($R:$R, ($C:$C=C25) * ($P:$P>=DATE(YEAR(P25),MONTH(P25),1)) * ($P:$P<=EOMONTH(P25,0)))), "")} | Y25: {=IF(AND(P25<>"", P25>=DATE(YEAR(P25),MONTH(P25),1), SUMIFS($K:$K, $C:$C, C25, $P:$P, ">="&DATE(YEAR(P25),MONTH(P25),1), $P:$P, "<="&EOMONTH(P25,0))>10), _xlfn.TEXTJOIN(", ", TRUE, _xlfn._xlws.FILTER($S:$S, ($C:$C=C25) * ($P:$P>=DATE(YEAR(P25),MONTH(P25),1)) * ($P:$P<=EOMONTH(P25,0)))), "")}
A26: 19 | B26: TEMPOACTIVA | C26: =_xlfn.XLOOKUP(D26,[1]!Data[CEDULA],[1]!Data[Nombre Completo],"No Existe",0,1) -> ALBERTO JULIO GUTIERREZ PERTUZ | D26: 8486407 | E26: =IFERROR(_xlfn.NUMBERVALUE(Data[[#This Row],[CEDULA ]],",","."),_xlfn.NUMBERVALUE(Data[[#This Row],[CEDULA ]],".",",")) -> 8486407 | F26: =_xlfn.XLOOKUP(E26,[1]!Data[CEDULA],[1]!Data[CARGO],"No Existe",0,1) -> AYUDANTE COCINA | G26: =_xlfn.XLOOKUP(E26,[1]!Data[CEDULA],[1]!Data[EMPRESA DONDE PRESTA SERVICIO],"No Existe",0,1) -> COMFAMILIAR ATLANTICO | H26: =_xlfn.XLOOKUP(E26,[1]!Data[CEDULA],[1]!Data[UBICACIÓN],"No Existe",0,1) -> SALGARITO MERCADEO | I26: HOMBRE | J26: =UPPER(TEXT(Data[[#This Row],[F. INICIO]],"mmmm")) -> JULIO | K26: 8 | L26: EPS | M26: ENFERMENDAD GENERAL | N26: =_xlfn.XLOOKUP(D26,[1]!Data[CEDULA],[1]!Data[EPS/SURA],"No Existe",0,1) -> EPS/SURA | O26: =YEAR(Data[[#This Row],[F. INICIO]]) -> 2023 | P26: 45110 | Q26: 45117 | R26: L039 | S26: =IF(Data[[#This Row],[TIPO DE INCAPACIDAD]]="LICENCIA DE PATERNIDAD","Licencia de paternidad",IF(Data[[#This Row],[TIPO DE INCAPACIDAD]]="LICENCIA DE LUTO","Licencia de Luto",_xlfn.IFNA(VLOOKUP(R26,'CIE-10 PARA RIPS'!$A$6:B13191,2,0),"No especificado"))) -> Celulitis de sitio no especificado | T26: =IF(P26<>"", IF(P26>0, IF(P26<=DATE(YEAR(P26),MONTH(P26),DAY(P26)), IF(P26>=DATE(YEAR(P26),MONTH(P26),1), IF(K26>10, C26, IF(SUMIFS($K:$K, $C:$C, C26, $P:$P, ">="&DATE(YEAR(P26),MONTH(P26),1), $P:$P, "<="&EOMONTH(P26,0))>10, C26, "")), ""))), "") | U26: =IF(AND(P26<>"", P26>=DATE(YEAR(P26),MONTH(P26),1), SUMIFS($K:$K, $C:$C, C26, $P:$P, ">="&DATE(YEAR(P26),MONTH(P26),1), $P:$P, "<="&EOMONTH(P26,0))>10), K26, "") | V26: =IF(AND(P26<>"", P26>=DATE(YEAR(P26),MONTH(P26),1), SUMIFS($K:$K, $C:$C, C26, $P:$P, ">="&DATE(YEAR(P26),MONTH(P26),1), $P:$P, "<="&EOMONTH(P26,0))>10), YEAR(P26), "") | W26: =IF(AND(P26<>"", P26>=DATE(YEAR(P26),MONTH(P26),1), SUMIFS($K:$K, $C:$C, C26, $P:$P, ">="&DATE(YEAR(P26),MONTH(P26),1), $P:$P, "<="&EOMONTH(P26,0))>10), TEXT(P26, "MMMM"), "") | X26: {=IF(AND(P26<>"", P26>=DATE(YEAR(P26),MONTH(P26),1), SUMIFS($K:$K, $C:$C, C26, $P:$P, ">="&DATE(YEAR(P26),MONTH(P26),1), $P:$P, "<="&EOMONTH(P26,0))>10), _xlfn.TEXTJOIN(", ", TRUE, _xlfn._xlws.FILTER($R:$R, ($C:$C=C26) * ($P:$P>=DATE(YEAR(P26),MONTH(P26),1)) * ($P:$P<=EOMONTH(P26,0)))), "")} | Y26: {=IF(AND(P26<>"", P26>=DATE(YEAR(P26),MONTH(P26),1), SUMIFS($K:$K, $C:$C, C26, $P:$P, ">="&DATE(YEAR(P26),MONTH(P26),1), $P:$P, "<="&EOMONTH(P26,0))>10), _xlfn.TEXTJOIN(", ", TRUE, _xlfn._xlws.FILTER($S:$S, ($C:$C=C26) * ($P:$P>=DATE(YEAR(P26),MONTH(P26),1)) * ($P:$P<=EOMONTH(P26,0)))), "")}
A27: 20 | B27: TEMPOACTIVA | C27: =_xlfn.XLOOKUP(D27,[1]!Data[CEDULA],[1]!Data[Nombre Completo],"No Existe",0,1) -> KARINA GREGORIA SALAS BROCHERO | D27: 1007096798 | E27: =IFERROR(_xlfn.NUMBERVALUE(Data[[#This Row],[CEDULA ]],",","."),_xlfn.NUMBERVALUE(Data[[#This Row],[CEDULA ]],".",",")) -> 1007096798 | F27: =_xlfn.XLOOKUP(E27,[1]!Data[CEDULA],[1]!Data[CARGO],"No Existe",0,1) -> SUPERNUMERARIO(A) | G27: =_xlfn.XLOOKUP(E27,[1]!Data[CEDULA],[1]!Data[EMPRESA DONDE PRESTA SERVICIO],"No Existe",0,1) -> COMFAMILIAR ATLANTICO | H27: =_xlfn.XLOOKUP(E27,[1]!Data[CEDULA],[1]!Data[UBICACIÓN],"No Existe",0,1) -> SEDE NORTE | I27: MUJER | J27: =UPPER(TEXT(Data[[#This Row],[F. INICIO]],"mmmm")) -> FEBRERO | K27: 29 | L27: EPS | M27: LICENCIA DE MATERNIDAD | N27: =_xlfn.XLOOKUP(D27,[1]!Data[CEDULA],[1]!Data[EPS/SURA],"No Existe",0,1) -> E.P.S SANITAS | O27: =YEAR(Data[[#This Row],[F. INICIO]]) -> 2024 | P27: 45323 | Q27: 45351 | R27: O829 | S27: =IF(Data[[#This Row],[TIPO DE INCAPACIDAD]]="LICENCIA DE PATERNIDAD","Licencia de paternidad",IF(Data[[#This Row],[TIPO DE INCAPACIDAD]]="LICENCIA DE LUTO","Licencia de Luto",_xlfn.IFNA(VLOOKUP(R27,'CIE-10 PARA RIPS'!$A$6:B13174,2,0),"No especificado"))) -> Parto por cesarea, sin otra especificacion | T27: =IF(P27<>"", IF(P27>0, IF(P27<=DATE(YEAR(P27),MONTH(P27),DAY(P27)), IF(P27>=DATE(YEAR(P27),MONTH(P27),1), IF(K27>10, C27, IF(SUMIFS($K:$K, $C:$C, C27, $P:$P, ">="&DATE(YEAR(P27),MONTH(P27),1), $P:$P, "<="&EOMONTH(P27,0))>10, C27, "")), ""))), "") -> KARINA GREGORIA SALAS BROCHERO | U27: =IF(AND(P27<>"", P27>=DATE(YEAR(P27),MONTH(P27),1), SUMIFS($K:$K, $C:$C, C27, $P:$P, ">="&DATE(YEAR(P27),MONTH(P27),1), $P:$P, "<="&EOMONTH(P27,0))>10), K27, "") -> 29 | V27: =IF(AND(P27<>"", P27>=DATE(YEAR(P27),MONTH(P27),1), SUMIFS($K:$K, $C:$C, C27, $P:$P, ">="&DATE(YEAR(P27),MONTH(P27),1), $P:$P, "<="&EOMONTH(P27,0))>10), YEAR(P27), "") -> 2024 | W27: =IF(AND(P27<>"", P27>=DATE(YEAR(P27),MONTH(P27),1), SUMIFS($K:$K, $C:$C, C27, $P:$P, ">="&DATE(YEAR(P27),MONTH(P27),1), $P:$P, "<="&EOMONTH(P27,0))>10), TEXT(P27, "MMMM"), "") -> febrero | X27: {=IF(AND(P27<>"", P27>=DATE(YEAR(P27),MONTH(P27),1), SUMIFS($K:$K, $C:$C, C27, $P:$P, ">="&DATE(YEAR(P27),MONTH(P27),1), $P:$P, "<="&EOMONTH(P27,0))>10), _xlfn.TEXTJOIN(", ", TRUE, _xlfn._xlws.FILTER($R:$R, ($C:$C=C27) * ($P:$P>=DATE(YEAR(P27),MONTH(P27),1)) * ($P:$P<=EOMONTH(P27,0)))), "")} -> O829 | Y27: {=IF(AND(P27<>"", P27>=DATE(YEAR(P27),MONTH(P27),1), SUMIFS($K:$K, $C:$C, C27, $P:$P, ">="&DATE(YEAR(P27),MONTH(P27),1), $P:$P, "<="&EOMONTH(P27,0))>10), _xlfn.TEXTJOIN(", ", TRUE, _xlfn._xlws.FILTER($S:$S, ($C:$C=C27) * ($P:$P>=DATE(YEAR(P27),MONTH(P27),1)) * ($P:$P<=EOMONTH(P27,0)))), "")} -> Parto por cesarea, sin otra especificacion
A28: 21 | B28: TEMPOACTIVA | C28: =_xlfn.XLOOKUP(D28,[1]!Data[CEDULA],[1]!Data[Nombre Completo],"No Existe",0,1) -> GENISIS MARIA CANTILLO TORRES | D28: 1002228922 | E28: =IFERROR(_xlfn.NUMBERVALUE(Data[[#This Row],[CEDULA ]],",","."),_xlfn.NUMBERVALUE(Data[[#This Row],[CEDULA ]],".",",")) -> 1002228922 | F28: =_xlfn.XLOOKUP(E28,[1]!Data[CEDULA],[1]!Data[CARGO],"No Existe",0,1) -> MESERO | G28: =_xlfn.XLOOKUP(E28,[1]!Data[CEDULA],[1]!Data[EMPRESA DONDE PRESTA SERVICIO],"No Existe",0,1) -> COMFAMILIAR ATLANTICO | H28: =_xlfn.XLOOKUP(E28,[1]!Data[CEDULA],[1]!Data[UBICACIÓN],"No Existe",0,1) -> SEDE SPORT GYM | I28: MUJER | J28: =UPPER(TEXT(Data[[#This Row],[F. INICIO]],"mmmm")) -> FEBRERO | K28: 29 | L28: EPS | M28: LICENCIA DE MATERNIDAD | N28: =_xlfn.XLOOKUP(D28,[1]!Data[CEDULA],[1]!Data[EPS/SURA],"No Existe",0,1) -> MUTUALSER | O28: =YEAR(Data[[#This Row],[F. INICIO]]) -> 2024 | P28: 45323 | Q28: 29/2/2023 | R28: O829 | S28: =IF(Data[[#This Row],[TIPO DE INCAPACIDAD]]="LICENCIA DE PATERNIDAD","Licencia de paternidad",IF(Data[[#This Row],[TIPO DE INCAPACIDAD]]="LICENCIA DE LUTO","Licencia de Luto",_xlfn.IFNA(VLOOKUP(R28,'CIE-10 PARA RIPS'!$A$6:B13178,2,0),"No especificado"))) -> Parto por cesarea, sin otra especificacion | T28: =IF(P28<>"", IF(P28>0, IF(P28<=DATE(YEAR(P28),MONTH(P28),DAY(P28)), IF(P28>=DATE(YEAR(P28),MONTH(P28),1), IF(K28>10, C28, IF(SUMIFS($K:$K, $C:$C, C28, $P:$P, ">="&DATE(YEAR(P28),MONTH(P28),1), $P:$P, "<="&EOMONTH(P28,0))>10, C28, "")), ""))), "") -> GENISIS MARIA CANTILLO TORRES | U28: =IF(AND(P28<>"", P28>=DATE(YEAR(P28),MONTH(P28),1), SUMIFS($K:$K, $C:$C, C28, $P:$P, ">="&DATE(YEAR(P28),MONTH(P28),1), $P:$P, "<="&EOMONTH(P28,0))>10), K28, "") -> 29 | V28: =IF(AND(P28<>"", P28>=DATE(YEAR(P28),MONTH(P28),1), SUMIFS($K:$K, $C:$C, C28, $P:$P, ">="&DATE(YEAR(P28),MONTH(P28),1), $P:$P, "<="&EOMONTH(P28,0))>10), YEAR(P28), "") -> 2024 | W28: =IF(AND(P28<>"", P28>=DATE(YEAR(P28),MONTH(P28),1), SUMIFS($K:$K, $C:$C, C28, $P:$P, ">="&DATE(YEAR(P28),MONTH(P28),1), $P:$P, "<="&EOMONTH(P28,0))>10), TEXT(P28, "MMMM"), "") -> febrero | X28: {=IF(AND(P28<>"", P28>=DATE(YEAR(P28),MONTH(P28),1), SUMIFS($K:$K, $C:$C, C28, $P:$P, ">="&DATE(YEAR(P28),MONTH(P28),1), $P:$P, "<="&EOMONTH(P28,0))>10), _xlfn.TEXTJOIN(", ", TRUE, _xlfn._xlws.FILTER($R:$R, ($C:$C=C28) * ($P:$P>=DATE(YEAR(P28),MONTH(P28),1)) * ($P:$P<=EOMONTH(P28,0)))), "")} -> O829 | Y28: {=IF(AND(P28<>"", P28>=DATE(YEAR(P28),MONTH(P28),1), SUMIFS($K:$K, $C:$C, C28, $P:$P, ">="&DATE(YEAR(P28),MONTH(P28),1), $P:$P, "<="&EOMONTH(P28,0))>10), _xlfn.TEXTJOIN(", ", TRUE, _xlfn._xlws.FILTER($S:$S, ($C:$C=C28) * ($P:$P>=DATE(YEAR(P28),MONTH(P28),1)) * ($P:$P<=EOMONTH(P28,0)))), "")} -> Parto por cesarea, sin otra especificacion
A29: 22 | B29: TEMPOACTIVA | C29: =_xlfn.XLOOKUP(D29,[1]!Data[CEDULA],[1]!Data[Nombre Completo],"No Existe",0,1) -> OLGA PATRICIA MOLINA JIMENEZ | D29: 22510938 | E29: =IFERROR(_xlfn.NUMBERVALUE(Data[[#This Row],[CEDULA ]],",","."),_xlfn.NUMBERVALUE(Data[[#This Row],[CEDULA ]],".",",")) -> 22510938 | F29: =_xlfn.XLOOKUP(E29,[1]!Data[CEDULA],[1]!Data[CARGO],"No Existe",0,1) -> AMA DE LLAVES | G29: =_xlfn.XLOOKUP(E29,[1]!Data[CEDULA],[1]!Data[EMPRESA DONDE PRESTA SERVICIO],"No Existe",0,1) -> COMFAMILIAR ATLANTICO | H29: =_xlfn.XLOOKUP(E29,[1]!Data[CEDULA],[1]!Data[UBICACIÓN],"No Existe",0,1) -> CENTRO RECREACIONAL TURIPANA | I29: MUJER | J29: =UPPER(TEXT(Data[[#This Row],[F. INICIO]],"mmmm")) -> FEBRERO | K29: 7 | L29: EPS | M29: ENFERMENDAD GENERAL | N29: =_xlfn.XLOOKUP(D29,[1]!Data[CEDULA],[1]!Data[EPS/SURA],"No Existe",0,1) -> E.P.S SANITAS | O29: =YEAR(Data[[#This Row],[F. INICIO]]) -> 2024 | P29: 45324 | Q29: 45330 | R29: D390 | S29: =IF(Data[[#This Row],[TIPO DE INCAPACIDAD]]="LICENCIA DE PATERNIDAD","Licencia de paternidad",IF(Data[[#This Row],[TIPO DE INCAPACIDAD]]="LICENCIA DE LUTO","Licencia de Luto",_xlfn.IFNA(VLOOKUP(R29,'CIE-10 PARA RIPS'!$A$6:B13192,2,0),"No especificado"))) -> Tumor de comportamiento incierto o desconocido del utero | T29: =IF(P29<>"", IF(P29>0, IF(P29<=DATE(YEAR(P29),MONTH(P29),DAY(P29)), IF(P29>=DATE(YEAR(P29),MONTH(P29),1), IF(K29>10, C29, IF(SUMIFS($K:$K, $C:$C, C29, $P:$P, ">="&DATE(YEAR(P29),MONTH(P29),1), $P:$P, "<="&EOMONTH(P29,0))>10, C29, "")), ""))), "") | U29: =IF(AND(P29<>"", P29>=DATE(YEAR(P29),MONTH(P29),1), SUMIFS($K:$K, $C:$C, C29, $P:$P, ">="&DATE(YEAR(P29),MONTH(P29),1), $P:$P, "<="&EOMONTH(P29,0))>10), K29, "") | V29: =IF(AND(P29<>"", P29>=DATE(YEAR(P29),MONTH(P29),1), SUMIFS($K:$K, $C:$C, C29, $P:$P, ">="&DATE(YEAR(P29),MONTH(P29),1), $P:$P, "<="&EOMONTH(P29,0))>10), YEAR(P29), "") | W29: =IF(AND(P29<>"", P29>=DATE(YEAR(P29),MONTH(P29),1), SUMIFS($K:$K, $C:$C, C29, $P:$P, ">="&DATE(YEAR(P29),MONTH(P29),1), $P:$P, "<="&EOMONTH(P29,0))>10), TEXT(P29, "MMMM"), "") | X29: {=IF(AND(P29<>"", P29>=DATE(YEAR(P29),MONTH(P29),1), SUMIFS($K:$K, $C:$C, C29, $P:$P, ">="&DATE(YEAR(P29),MONTH(P29),1), $P:$P, "<="&EOMONTH(P29,0))>10), _xlfn.TEXTJOIN(", ", TRUE, _xlfn._xlws.FILTER($R:$R, ($C:$C=C29) * ($P:$P>=DATE(YEAR(P29),MONTH(P29),1)) * ($P:$P<=EOMONTH(P29,0)))), "")} | Y29: {=IF(AND(P29<>"", P29>=DATE(YEAR(P29),MONTH(P29),1), SUMIFS($K:$K, $C:$C, C29, $P:$P, ">="&DATE(YEAR(P29),MONTH(P29),1), $P:$P, "<="&EOMONTH(P29,0))>10), _xlfn.TEXTJOIN(", ", TRUE, _xlfn._xlws.FILTER($S:$S, ($C:$C=C29) * ($P:$P>=DATE(YEAR(P29),MONTH(P29),1)) * ($P:$P<=EOMONTH(P29,0)))), "")}
A30: 23 | B30: TEMPOACTIVA | C30: =_xlfn.XLOOKUP(D30,[1]!Data[CEDULA],[1]!Data[Nombre Completo],"No Existe",0,1) -> LORAINNE PAOLA MOLINA PADILLA | D30: 1044392755 | E30: =IFERROR(_xlfn.NUMBERVALUE(Data[[#This Row],[CEDULA ]],",","."),_xlfn.NUMBERVALUE(Data[[#This Row],[CEDULA ]],".",",")) -> 1044392755 | F30: =_xlfn.XLOOKUP(E30,[1]!Data[CEDULA],[1]!Data[CARGO],"No Existe",0,1) -> COCINERO 1 | G30: =_xlfn.XLOOKUP(E30,[1]!Data[CEDULA],[1]!Data[EMPRESA DONDE PRESTA SERVICIO],"No Existe",0,1) -> COMFAMILIAR ATLANTICO | H30: =_xlfn.XLOOKUP(E30,[1]!Data[CEDULA],[1]!Data[UBICACIÓN],"No Existe",0,1) -> TURIPANA MERCADEO | I30: MUJER | J30: =UPPER(TEXT(Data[[#This Row],[F. INICIO]],"mmmm")) -> FEBRERO | K30: 1 | L30: EPS | M30: ENFERMENDAD GENERAL | N30: =_xlfn.XLOOKUP(D30,[1]!Data[CEDULA],[1]!Data[EPS/SURA],"No Existe",0,1) -> FAMISANAR | O30: =YEAR(Data[[#This Row],[F. INICIO]]) -> 2024 | P30: 45323 | Q30: 45323 | R30: J068 | S30: =IF(Data[[#This Row],[TIPO DE INCAPACIDAD]]="LICENCIA DE PATERNIDAD","Licencia de paternidad",IF(Data[[#This Row],[TIPO DE INCAPACIDAD]]="LICENCIA DE LUTO","Licencia de Luto",_xlfn.IFNA(VLOOKUP(R30,'CIE-10 PARA RIPS'!$A$6:B13194,2,0),"No especificado"))) -> Otras infecciones agudas de sitios multiples de las vias respiratorias superiores | T30: =IF(P30<>"", IF(P30>0, IF(P30<=DATE(YEAR(P30),MONTH(P30),DAY(P30)), IF(P30>=DATE(YEAR(P30),MONTH(P30),1), IF(K30>10, C30, IF(SUMIFS($K:$K, $C:$C, C30, $P:$P, ">="&DATE(YEAR(P30),MONTH(P30),1), $P:$P, "<="&EOMONTH(P30,0))>10, C30, "")), ""))), "") | U30: =IF(AND(P30<>"", P30>=DATE(YEAR(P30),MONTH(P30),1), SUMIFS($K:$K, $C:$C, C30, $P:$P, ">="&DATE(YEAR(P30),MONTH(P30),1), $P:$P, "<="&EOMONTH(P30,0))>10), K30, "") | V30: =IF(AND(P30<>"", P30>=DATE(YEAR(P30),MONTH(P30),1), SUMIFS($K:$K, $C:$C, C30, $P:$P, ">="&DATE(YEAR(P30),MONTH(P30),1), $P:$P, "<="&EOMONTH(P30,0))>10), YEAR(P30), "") | W30: =IF(AND(P30<>"", P30>=DATE(YEAR(P30),MONTH(P30),1), SUMIFS($K:$K, $C:$C, C30, $P:$P, ">="&DATE(YEAR(P30),MONTH(P30),1), $P:$P, "<="&EOMONTH(P30,0))>10), TEXT(P30, "MMMM"), "") | X30: {=IF(AND(P30<>"", P30>=DATE(YEAR(P30),MONTH(P30),1), SUMIFS($K:$K, $C:$C, C30, $P:$P, ">="&DATE(YEAR(P30),MONTH(P30),1), $P:$P, "<="&EOMONTH(P30,0))>10), _xlfn.TEXTJOIN(", ", TRUE, _xlfn._xlws.FILTER($R:$R, ($C:$C=C30) * ($P:$P>=DATE(YEAR(P30),MONTH(P30),1)) * ($P:$P<=EOMONTH(P30,0)))), "")} | Y30: {=IF(AND(P30<>"", P30>=DATE(YEAR(P30),MONTH(P30),1), SUMIFS($K:$K, $C:$C, C30, $P:$P, ">="&DATE(YEAR(P30),MONTH(P30),1), $P:$P, "<="&EOMONTH(P30,0))>10), _xlfn.TEXTJOIN(", ", TRUE, _xlfn._xlws.FILTER($S:$S, ($C:$C=C30) * ($P:$P>=DATE(YEAR(P30),MONTH(P30),1)) * ($P:$P<=EOMONTH(P30,0)))), "")}
A31: 24 | B31: TEMPOACTIVA | C31: =_xlfn.XLOOKUP(D31,[1]!Data[CEDULA],[1]!Data[Nombre Completo],"No Existe",0,1) -> CARELIS DEL CARMEN CARIDAD CALDERON | D31: 1047239028 | E31: =IFERROR(_xlfn.NUMBERVALUE(Data[[#This Row],[CEDULA ]],",","."),_xlfn.NUMBERVALUE(Data[[#This Row],[CEDULA ]],".",",")) -> 1047239028 | F31: =_xlfn.XLOOKUP(E31,[1]!Data[CEDULA],[1]!Data[CARGO],"No Existe",0,1) -> SUPERNUMERARIO(A) | G31: =_xlfn.XLOOKUP(E31,[1]!Data[CEDULA],[1]!Data[EMPRESA DONDE PRESTA SERVICIO],"No Existe",0,1) -> COMFAMILIAR ATLANTICO | H31: =_xlfn.XLOOKUP(E31,[1]!Data[CEDULA],[1]!Data[UBICACIÓN],"No Existe",0,1) -> SEDE CARIBE MERCADEO | I31: MUJER | J31: =UPPER(TEXT(Data[[#This Row],[F. INICIO]],"mmmm")) -> FEBRERO | K31: 2 | L31: EPS | M31: ENFERMENDAD GENERAL | N31: =_xlfn.XLOOKUP(D31,[1]!Data[CEDULA],[1]!Data[EPS/SURA],"No Existe",0,1) -> MUTUALSER | O31: =YEAR(Data[[#This Row],[F. INICIO]]) -> 2024 | P31: 45330 | Q31: 45331 | R31: K083 | S31: =IF(Data[[#This Row],[TIPO DE INCAPACIDAD]]="LICENCIA DE PATERNIDAD","Licencia de paternidad",IF(Data[[#This Row],[TIPO DE INCAPACIDAD]]="LICENCIA DE LUTO","Licencia de Luto",_xlfn.IFNA(VLOOKUP(R31,'CIE-10 PARA RIPS'!$A$6:B13373,2,0),"No especificado"))) -> Raiz dental retenida | T31: =IF(P31<>"", IF(P31>0, IF(P31<=DATE(YEAR(P31),MONTH(P31),DAY(P31)), IF(P31>=DATE(YEAR(P31),MONTH(P31),1), IF(K31>10, C31, IF(SUMIFS($K:$K, $C:$C, C31, $P:$P, ">="&DATE(YEAR(P31),MONTH(P31),1), $P:$P, "<="&EOMONTH(P31,0))>10, C31, "")), ""))), "") | U31: =IF(AND(P31<>"", P31>=DATE(YEAR(P31),MONTH(P31),1), SUMIFS($K:$K, $C:$C, C31, $P:$P, ">="&DATE(YEAR(P31),MONTH(P31),1), $P:$P, "<="&EOMONTH(P31,0))>10), K31, "") | V31: =IF(AND(P31<>"", P31>=DATE(YEAR(P31),MONTH(P31),1), SUMIFS($K:$K, $C:$C, C31, $P:$P, ">="&DATE(YEAR(P31),MONTH(P31),1), $P:$P, "<="&EOMONTH(P31,0))>10), YEAR(P31), "") | W31: =IF(AND(P31<>"", P31>=DATE(YEAR(P31),MONTH(P31),1), SUMIFS($K:$K, $C:$C, C31, $P:$P, ">="&DATE(YEAR(P31),MONTH(P31),1), $P:$P, "<="&EOMONTH(P31,0))>10), TEXT(P31, "MMMM"), "") | X31: {=IF(AND(P31<>"", P31>=DATE(YEAR(P31),MONTH(P31),1), SUMIFS($K:$K, $C:$C, C31, $P:$P, ">="&DATE(YEAR(P31),MONTH(P31),1), $P:$P, "<="&EOMONTH(P31,0))>10), _xlfn.TEXTJOIN(", ", TRUE, _xlfn._xlws.FILTER($R:$R, ($C:$C=C31) * ($P:$P>=DATE(YEAR(P31),MONTH(P31),1)) * ($P:$P<=EOMONTH(P31,0)))), "")} | Y31: {=IF(AND(P31<>"", P31>=DATE(YEAR(P31),MONTH(P31),1), SUMIFS($K:$K, $C:$C, C31, $P:$P, ">="&DATE(YEAR(P31),MONTH(P31),1), $P:$P, "<="&EOMONTH(P31,0))>10), _xlfn.TEXTJOIN(", ", TRUE, _xlfn._xlws.FILTER($S:$S, ($C:$C=C31) * ($P:$P>=DATE(YEAR(P31),MONTH(P31),1)) * ($P:$P<=EOMONTH(P31,0)))), "")}
A32: 25 | B32: TEMPOACTIVA | C32: =_xlfn.XLOOKUP(D32,[1]!Data[CEDULA],[1]!Data[Nombre Completo],"No Existe",0,1) -> PEDRO FABIAN ARIZA MAESTRE | D32: 1045228765 | E32: =IFERROR(_xlfn.NUMBERVALUE(Data[[#This Row],[CEDULA ]],",","."),_xlfn.NUMBERVALUE(Data[[#This Row],[CEDULA ]],".",",")) -> 1045228765 | F32: =_xlfn.XLOOKUP(E32,[1]!Data[CEDULA],[1]!Data[CARGO],"No Existe",0,1) -> STEWARD | G32: =_xlfn.XLOOKUP(E32,[1]!Data[CEDULA],[1]!Data[EMPRESA DONDE PRESTA SERVICIO],"No Existe",0,1) -> COMFAMILIAR ATLANTICO | H32: =_xlfn.XLOOKUP(E32,[1]!Data[CEDULA],[1]!Data[UBICACIÓN],"No Existe",0,1) -> CENTRO DE PROCESAMIENTO | I32: HOMBRE | J32: =UPPER(TEXT(Data[[#This Row],[F. INICIO]],"mmmm")) -> JULIO | K32: 7 | L32: EPS | M32: ENFERMENDAD GENERAL | N32: =_xlfn.XLOOKUP(D32,[1]!Data[CEDULA],[1]!Data[EPS/SURA],"No Existe",0,1) -> NUEVA E.P.S. | O32: =YEAR(Data[[#This Row],[F. INICIO]]) -> 2024 | P32: 45483 | Q32: 45489 | R32: S618 | S32: =IF(Data[[#This Row],[TIPO DE INCAPACIDAD]]="LICENCIA DE PATERNIDAD","Licencia de paternidad",IF(Data[[#This Row],[TIPO DE INCAPACIDAD]]="LICENCIA DE LUTO","Licencia de Luto",_xlfn.IFNA(VLOOKUP(R32,'CIE-10 PARA RIPS'!$A$6:B13226,2,0),"No especificado"))) -> Herida de otras partes de la muneca y de la mano | T32: =IF(P32<>"", IF(P32>0, IF(P32<=DATE(YEAR(P32),MONTH(P32),DAY(P32)), IF(P32>=DATE(YEAR(P32),MONTH(P32),1), IF(K32>10, C32, IF(SUMIFS($K:$K, $C:$C, C32, $P:$P, ">="&DATE(YEAR(P32),MONTH(P32),1), $P:$P, "<="&EOMONTH(P32,0))>10, C32, "")), ""))), "") | U32: =IF(AND(P32<>"", P32>=DATE(YEAR(P32),MONTH(P32),1), SUMIFS($K:$K, $C:$C, C32, $P:$P, ">="&DATE(YEAR(P32),MONTH(P32),1), $P:$P, "<="&EOMONTH(P32,0))>10), K32, "") | V32: =IF(AND(P32<>"", P32>=DATE(YEAR(P32),MONTH(P32),1), SUMIFS($K:$K, $C:$C, C32, $P:$P, ">="&DATE(YEAR(P32),MONTH(P32),1), $P:$P, "<="&EOMONTH(P32,0))>10), YEAR(P32), "") | W32: =IF(AND(P32<>"", P32>=DATE(YEAR(P32),MONTH(P32),1), SUMIFS($K:$K, $C:$C, C32, $P:$P, ">="&DATE(YEAR(P32),MONTH(P32),1), $P:$P, "<="&EOMONTH(P32,0))>10), TEXT(P32, "MMMM"), "") | X32: {=IF(AND(P32<>"", P32>=DATE(YEAR(P32),MONTH(P32),1), SUMIFS($K:$K, $C:$C, C32, $P:$P, ">="&DATE(YEAR(P32),MONTH(P32),1), $P:$P, "<="&EOMONTH(P32,0))>10), _xlfn.TEXTJOIN(", ", TRUE, _xlfn._xlws.FILTER($R:$R, ($C:$C=C32) * ($P:$P>=DATE(YEAR(P32),MONTH(P32),1)) * ($P:$P<=EOMONTH(P32,0)))), "")} | Y32: {=IF(AND(P32<>"", P32>=DATE(YEAR(P32),MONTH(P32),1), SUMIFS($K:$K, $C:$C, C32, $P:$P, ">="&DATE(YEAR(P32),MONTH(P32),1), $P:$P, "<="&EOMONTH(P32,0))>10), _xlfn.TEXTJOIN(", ", TRUE, _xlfn._xlws.FILTER($S:$S, ($C:$C=C32) * ($P:$P>=DATE(YEAR(P32),MONTH(P32),1)) * ($P:$P<=EOMONTH(P32,0)))), "")}
A33: 26 | B33: TEMPOACTIVA | C33: =_xlfn.XLOOKUP(D33,[1]!Data[CEDULA],[1]!Data[Nombre Completo],"No Existe",0,1) -> MIGUEL DE JESUS RAMOS ARTETA | D33: 1044394141 | E33: =IFERROR(_xlfn.NUMBERVALUE(Data[[#This Row],[CEDULA ]],",","."),_xlfn.NUMBERVALUE(Data[[#This Row],[CEDULA ]],".",",")) -> 1044394141 | F33: =_xlfn.XLOOKUP(E33,[1]!Data[CEDULA],[1]!Data[CARGO],"No Existe",0,1) -> SUPERNUMERARIO(A) | G33: =_xlfn.XLOOKUP(E33,[1]!Data[CEDULA],[1]!Data[EMPRESA DONDE PRESTA SERVICIO],"No Existe",0,1) -> COMFAMILIAR ATLANTICO | H33: =_xlfn.XLOOKUP(E33,[1]!Data[CEDULA],[1]!Data[UBICACIÓN],"No Existe",0,1) -> CENTRO RECREACIONAL TURIPANA | I33: HOMBRE | J33: =UPPER(TEXT(Data[[#This Row],[F. INICIO]],"mmmm")) -> JULIO | K33: 1 | L33: EPS | M33: ENFERMENDAD GENERAL | N33: =_xlfn.XLOOKUP(D33,[1]!Data[CEDULA],[1]!Data[EPS/SURA],"No Existe",0,1) -> NUEVA E.P.S. | O33: =YEAR(Data[[#This Row],[F. INICIO]]) -> 2024 | P33: 45474 | Q33: 45474 | R33: J039 | S33: =IF(Data[[#This Row],[TIPO DE INCAPACIDAD]]="LICENCIA DE PATERNIDAD","Licencia de paternidad",IF(Data[[#This Row],[TIPO DE INCAPACIDAD]]="LICENCIA DE LUTO","Licencia de Luto",_xlfn.IFNA(VLOOKUP(R33,'CIE-10 PARA RIPS'!$A$6:B13228,2,0),"No especificado"))) -> Amigdalitis aguda, no especificada | T33: =IF(P33<>"", IF(P33>0, IF(P33<=DATE(YEAR(P33),MONTH(P33),DAY(P33)), IF(P33>=DATE(YEAR(P33),MONTH(P33),1), IF(K33>10, C33, IF(SUMIFS($K:$K, $C:$C, C33, $P:$P, ">="&DATE(YEAR(P33),MONTH(P33),1), $P:$P, "<="&EOMONTH(P33,0))>10, C33, "")), ""))), "") | U33: =IF(AND(P33<>"", P33>=DATE(YEAR(P33),MONTH(P33),1), SUMIFS($K:$K, $C:$C, C33, $P:$P, ">="&DATE(YEAR(P33),MONTH(P33),1), $P:$P, "<="&EOMONTH(P33,0))>10), K33, "") | V33: =IF(AND(P33<>"", P33>=DATE(YEAR(P33),MONTH(P33),1), SUMIFS($K:$K, $C:$C, C33, $P:$P, ">="&DATE(YEAR(P33),MONTH(P33),1), $P:$P, "<="&EOMONTH(P33,0))>10), YEAR(P33), "") | W33: =IF(AND(P33<>"", P33>=DATE(YEAR(P33),MONTH(P33),1), SUMIFS($K:$K, $C:$C, C33, $P:$P, ">="&DATE(YEAR(P33),MONTH(P33),1), $P:$P, "<="&EOMONTH(P33,0))>10), TEXT(P33, "MMMM"), "") | X33: {=IF(AND(P33<>"", P33>=DATE(YEAR(P33),MONTH(P33),1), SUMIFS($K:$K, $C:$C, C33, $P:$P, ">="&DATE(YEAR(P33),MONTH(P33),1), $P:$P, "<="&EOMONTH(P33,0))>10), _xlfn.TEXTJOIN(", ", TRUE, _xlfn._xlws.FILTER($R:$R, ($C:$C=C33) * ($P:$P>=DATE(YEAR(P33),MONTH(P33),1)) * ($P:$P<=EOMONTH(P33,0)))), "")} | Y33: {=IF(AND(P33<>"", P33>=DATE(YEAR(P33),MONTH(P33),1), SUMIFS($K:$K, $C:$C, C33, $P:$P, ">="&DATE(YEAR(P33),MONTH(P33),1), $P:$P, "<="&EOMONTH(P33,0))>10), _xlfn.TEXTJOIN(", ", TRUE, _xlfn._xlws.FILTER($S:$S, ($C:$C=C33) * ($P:$P>=DATE(YEAR(P33),MONTH(P33),1)) * ($P:$P<=EOMONTH(P33,0)))), "")}
A34: 27 | B34: TEMPOACTIVA | C34: =_xlfn.XLOOKUP(D34,[1]!Data[CEDULA],[1]!Data[Nombre Completo],"No Existe",0,1) -> ALDEMAR ENRIQUE ORTIZ CARPINTERO | D34: 72310167 | E34: =IFERROR(_xlfn.NUMBERVALUE(Data[[#This Row],[CEDULA ]],",","."),_xlfn.NUMBERVALUE(Data[[#This Row],[CEDULA ]],".",",")) -> 72310167 | F34: =_xlfn.XLOOKUP(E34,[1]!Data[CEDULA],[1]!Data[CARGO],"No Existe",0,1) -> SUPERNUMERARIO(A) | G34: =_xlfn.XLOOKUP(E34,[1]!Data[CEDULA],[1]!Data[EMPRESA DONDE PRESTA SERVICIO],"No Existe",0,1) -> COMFAMILIAR ATLANTICO | H34: =_xlfn.XLOOKUP(E34,[1]!Data[CEDULA],[1]!Data[UBICACIÓN],"No Existe",0,1) -> SALGARITO | I34: HOMBRE | J34: =UPPER(TEXT(Data[[#This Row],[F. INICIO]],"mmmm")) -> SEPTIEMBRE | K34: 1 | L34: EPS | M34: ENFERMENDAD GENERAL | N34: =_xlfn.XLOOKUP(D34,[1]!Data[CEDULA],[1]!Data[EPS/SURA],"No Existe",0,1) -> SALUD TOTAL | O34: =YEAR(Data[[#This Row],[F. INICIO]]) -> 2018 | P34: 43362 | Q34: 43362 | R34: G442 | S34: =IF(Data[[#This Row],[TIPO DE INCAPACIDAD]]="LICENCIA DE PATERNIDAD","Licencia de paternidad",IF(Data[[#This Row],[TIPO DE INCAPACIDAD]]="LICENCIA DE LUTO","Licencia de Luto",_xlfn.IFNA(VLOOKUP(R34,'CIE-10 PARA RIPS'!$A$6:B13199,2,0),"No especificado"))) -> Cefalea debida a tension | T34: =IF(P34<>"", IF(P34>0, IF(P34<=DATE(YEAR(P34),MONTH(P34),DAY(P34)), IF(P34>=DATE(YEAR(P34),MONTH(P34),1), IF(K34>10, C34, IF(SUMIFS($K:$K, $C:$C, C34, $P:$P, ">="&DATE(YEAR(P34),MONTH(P34),1), $P:$P, "<="&EOMONTH(P34,0))>10, C34, "")), ""))), "") | U34: =IF(AND(P34<>"", P34>=DATE(YEAR(P34),MONTH(P34),1), SUMIFS($K:$K, $C:$C, C34, $P:$P, ">="&DATE(YEAR(P34),MONTH(P34),1), $P:$P, "<="&EOMONTH(P34,0))>10), K34, "") | V34: =IF(AND(P34<>"", P34>=DATE(YEAR(P34),MONTH(P34),1), SUMIFS($K:$K, $C:$C, C34, $P:$P, ">="&DATE(YEAR(P34),MONTH(P34),1), $P:$P, "<="&EOMONTH(P34,0))>10), YEAR(P34), "") | W34: =IF(AND(P34<>"", P34>=DATE(YEAR(P34),MONTH(P34),1), SUMIFS($K:$K, $C:$C, C34, $P:$P, ">="&DATE(YEAR(P34),MONTH(P34),1), $P:$P, "<="&EOMONTH(P34,0))>10), TEXT(P34, "MMMM"), "") | X34: {=IF(AND(P34<>"", P34>=DATE(YEAR(P34),MONTH(P34),1), SUMIFS($K:$K, $C:$C, C34, $P:$P, ">="&DATE(YEAR(P34),MONTH(P34),1), $P:$P, "<="&EOMONTH(P34,0))>10), _xlfn.TEXTJOIN(", ", TRUE, _xlfn._xlws.FILTER($R:$R, ($C:$C=C34) * ($P:$P>=DATE(YEAR(P34),MONTH(P34),1)) * ($P:$P<=EOMONTH(P34,0)))), "")} | Y34: {=IF(AND(P34<>"", P34>=DATE(YEAR(P34),MONTH(P34),1), SUMIFS($K:$K, $C:$C, C34, $P:$P, ">="&DATE(YEAR(P34),MONTH(P34),1), $P:$P, "<="&EOMONTH(P34,0))>10), _xlfn.TEXTJOIN(", ", TRUE, _xlfn._xlws.FILTER($S:$S, ($C:$C=C34) * ($P:$P>=DATE(YEAR(P34),MONTH(P34),1)) * ($P:$P<=EOMONTH(P34,0)))), "")}
A35: 28 | B35: TEMPOACTIVA | C35: =_xlfn.XLOOKUP(D35,[1]!Data[CEDULA],[1]!Data[Nombre Completo],"No Existe",0,1) -> HELIS MARI RAMIREZ PATIÑO | D35: 1140868628 | E35: =IFERROR(_xlfn.NUMBERVALUE(Data[[#This Row],[CEDULA ]],",","."),_xlfn.NUMBERVALUE(Data[[#This Row],[CEDULA ]],".",",")) -> 1140868628 | F35: =_xlfn.XLOOKUP(E35,[1]!Data[CEDULA],[1]!Data[CARGO],"No Existe",0,1) -> SUPERNUMERARIO(A) | G35: =_xlfn.XLOOKUP(E35,[1]!Data[CEDULA],[1]!Data[EMPRESA DONDE PRESTA SERVICIO],"No Existe",0,1) -> COMFAMILIAR ATLANTICO | H35: =_xlfn.XLOOKUP(E35,[1]!Data[CEDULA],[1]!Data[UBICACIÓN],"No Existe",0,1) -> SEDE NORTE | I35: MUJER | J35: =UPPER(TEXT(Data[[#This Row],[F. INICIO]],"mmmm")) -> JULIO | K35: 31 | L35: EPS | M35: LICENCIA DE MATERNIDAD | N35: =_xlfn.XLOOKUP(D35,[1]!Data[CEDULA],[1]!Data[EPS/SURA],"No Existe",0,1) -> MUTUALSER | O35: =YEAR(Data[[#This Row],[F. INICIO]]) -> 2024 | P35: 45474 | Q35: 45504 | R35: O821 | S35: =IF(Data[[#This Row],[TIPO DE INCAPACIDAD]]="LICENCIA DE PATERNIDAD","Licencia de paternidad",IF(Data[[#This Row],[TIPO DE INCAPACIDAD]]="LICENCIA DE LUTO","Licencia de Luto",_xlfn.IFNA(VLOOKUP(R35,'CIE-10 PARA RIPS'!$A$6:B13235,2,0),"No especificado"))) -> Parto por cesarea de emergencia | T35: =IF(P35<>"", IF(P35>0, IF(P35<=DATE(YEAR(P35),MONTH(P35),DAY(P35)), IF(P35>=DATE(YEAR(P35),MONTH(P35),1), IF(K35>10, C35, IF(SUMIFS($K:$K, $C:$C, C35, $P:$P, ">="&DATE(YEAR(P35),MONTH(P35),1), $P:$P, "<="&EOMONTH(P35,0))>10, C35, "")), ""))), "") -> HELIS MARI RAMIREZ PATIÑO | U35: =IF(AND(P35<>"", P35>=DATE(YEAR(P35),MONTH(P35),1), SUMIFS($K:$K, $C:$C, C35, $P:$P, ">="&DATE(YEAR(P35),MONTH(P35),1), $P:$P, "<="&EOMONTH(P35,0))>10), K35, "") -> 31 | V35: =IF(AND(P35<>"", P35>=DATE(YEAR(P35),MONTH(P35),1), SUMIFS($K:$K, $C:$C, C35, $P:$P, ">="&DATE(YEAR(P35),MONTH(P35),1), $P:$P, "<="&EOMONTH(P35,0))>10), YEAR(P35), "") -> 2024 | W35: =IF(AND(P35<>"", P35>=DATE(YEAR(P35),MONTH(P35),1), SUMIFS($K:$K, $C:$C, C35, $P:$P, ">="&DATE(YEAR(P35),MONTH(P35),1), $P:$P, "<="&EOMONTH(P35,0))>10), TEXT(P35, "MMMM"), "") -> julio | X35: {=IF(AND(P35<>"", P35>=DATE(YEAR(P35),MONTH(P35),1), SUMIFS($K:$K, $C:$C, C35, $P:$P, ">="&DATE(YEAR(P35),MONTH(P35),1), $P:$P, "<="&EOMONTH(P35,0))>10), _xlfn.TEXTJOIN(", ", TRUE, _xlfn._xlws.FILTER($R:$R, ($C:$C=C35) * ($P:$P>=DATE(YEAR(P35),MONTH(P35),1)) * ($P:$P<=EOMONTH(P35,0)))), "")} -> O821 | Y35: {=IF(AND(P35<>"", P35>=DATE(YEAR(P35),MONTH(P35),1), SUMIFS($K:$K, $C:$C, C35, $P:$P, ">="&DATE(YEAR(P35),MONTH(P35),1), $P:$P, "<="&EOMONTH(P35,0))>10), _xlfn.TEXTJOIN(", ", TRUE, _xlfn._xlws.FILTER($S:$S, ($C:$C=C35) * ($P:$P>=DATE(YEAR(P35),MONTH(P35),1)) * ($P:$P<=EOMONTH(P35,0)))), "")} -> Parto por cesarea de emergencia
A36: 29 | B36: TEMPOACTIVA | C36: =_xlfn.XLOOKUP(D36,[1]!Data[CEDULA],[1]!Data[Nombre Completo],"No Existe",0,1) -> ROYBER ALBERTO ARRIETA RODRIGUEZ | D36: 1143427863 | E36: =IFERROR(_xlfn.NUMBERVALUE(Data[[#This Row],[CEDULA ]],",","."),_xlfn.NUMBERVALUE(Data[[#This Row],[CEDULA ]],".",",")) -> 1143427863 | F36: =_xlfn.XLOOKUP(E36,[1]!Data[CEDULA],[1]!Data[CARGO],"No Existe",0,1) -> SUPERNUMERARIO(A) | G36: =_xlfn.XLOOKUP(E36,[1]!Data[CEDULA],[1]!Data[EMPRESA DONDE PRESTA SERVICIO],"No Existe",0,1) -> COMFAMILIAR ATLANTICO | H36: =_xlfn.XLOOKUP(E36,[1]!Data[CEDULA],[1]!Data[UBICACIÓN],"No Existe",0,1) -> PROGRAMAS RECREATIVOS | I36: HOMBRE | J36: =UPPER(TEXT(Data[[#This Row],[F. INICIO]],"mmmm")) -> JULIO | K36: 10 | L36: ARL | M36: ACCIDENTE LABORAL | N36: =_xlfn.XLOOKUP(D36,[1]!Data[CEDULA],[1]!Data[EPS/SURA],"No Existe",0,1) -> NUEVA E.P.S. | O36: =YEAR(Data[[#This Row],[F. INICIO]]) -> 2024 | P36: 45486 | Q36: 45495 | R36: S934 | S36: =IF(Data[[#This Row],[TIPO DE INCAPACIDAD]]="LICENCIA DE PATERNIDAD","Licencia de paternidad",IF(Data[[#This Row],[TIPO DE INCAPACIDAD]]="LICENCIA DE LUTO","Licencia de Luto",_xlfn.IFNA(VLOOKUP(R36,'CIE-10 PARA RIPS'!$A$6:B13238,2,0),"No especificado"))) -> Esguinces y torceduras del tobillo | T36: =IF(P36<>"", IF(P36>0, IF(P36<=DATE(YEAR(P36),MONTH(P36),DAY(P36)), IF(P36>=DATE(YEAR(P36),MONTH(P36),1), IF(K36>10, C36, IF(SUMIFS($K:$K, $C:$C, C36, $P:$P, ">="&DATE(YEAR(P36),MONTH(P36),1), $P:$P, "<="&EOMONTH(P36,0))>10, C36, "")), ""))), "") -> ROYBER ALBERTO ARRIETA RODRIGUEZ | U36: =IF(AND(P36<>"", P36>=DATE(YEAR(P36),MONTH(P36),1), SUMIFS($K:$K, $C:$C, C36, $P:$P, ">="&DATE(YEAR(P36),MONTH(P36),1), $P:$P, "<="&EOMONTH(P36,0))>10), K36, "") -> 10 | V36: =IF(AND(P36<>"", P36>=DATE(YEAR(P36),MONTH(P36),1), SUMIFS($K:$K, $C:$C, C36, $P:$P, ">="&DATE(YEAR(P36),MONTH(P36),1), $P:$P, "<="&EOMONTH(P36,0))>10), YEAR(P36), "") -> 2024 | W36: =IF(AND(P36<>"", P36>=DATE(YEAR(P36),MONTH(P36),1), SUMIFS($K:$K, $C:$C, C36, $P:$P, ">="&DATE(YEAR(P36),MONTH(P36),1), $P:$P, "<="&EOMONTH(P36,0))>10), TEXT(P36, "MMMM"), "") -> julio | X36: {=IF(AND(P36<>"", P36>=DATE(YEAR(P36),MONTH(P36),1), SUMIFS($K:$K, $C:$C, C36, $P:$P, ">="&DATE(YEAR(P36),MONTH(P36),1), $P:$P, "<="&EOMONTH(P36,0))>10), _xlfn.TEXTJOIN(", ", TRUE, _xlfn._xlws.FILTER($R:$R, ($C:$C=C36) * ($P:$P>=DATE(YEAR(P36),MONTH(P36),1)) * ($P:$P<=EOMONTH(P36,0)))), "")} -> S934, S934 | Y36: {=IF(AND(P36<>"", P36>=DATE(YEAR(P36),MONTH(P36),1), SUMIFS($K:$K, $C:$C, C36, $P:$P, ">="&DATE(YEAR(P36),MONTH(P36),1), $P:$P, "<="&EOMONTH(P36,0))>10), _xlfn.TEXTJOIN(", ", TRUE, _xlfn._xlws.FILTER($S:$S, ($C:$C=C36) * ($P:$P>=DATE(YEAR(P36),MONTH(P36),1)) * ($P:$P<=EOMONTH(P36,0)))), "")} -> Esguinces y torceduras del tobillo, Esguinces y torceduras del tobillo
A37: 30 | B37: TEMPOACTIVA | C37: =_xlfn.XLOOKUP(D37,[1]!Data[CEDULA],[1]!Data[Nombre Completo],"No Existe",0,1) -> MARIA ESTHER VARGAS MARQUEZ | D37: 1044394039 | E37: =IFERROR(_xlfn.NUMBERVALUE(Data[[#This Row],[CEDULA ]],",","."),_xlfn.NUMBERVALUE(Data[[#This Row],[CEDULA ]],".",",")) -> 1044394039 | F37: =_xlfn.XLOOKUP(E37,[1]!Data[CEDULA],[1]!Data[CARGO],"No Existe",0,1) -> SUPERNUMERARIO(A) | G37: =_xlfn.XLOOKUP(E37,[1]!Data[CEDULA],[1]!Data[EMPRESA DONDE PRESTA SERVICIO],"No Existe",0,1) -> COMFAMILIAR ATLANTICO | H37: =_xlfn.XLOOKUP(E37,[1]!Data[CEDULA],[1]!Data[UBICACIÓN],"No Existe",0,1) -> CENTRO RECREACIONAL TURIPANA | I37: MUJER | J37: =UPPER(TEXT(Data[[#This Row],[F. INICIO]],"mmmm")) -> JULIO | K37: 3 | L37: EPS | M37: ENFERMENDAD GENERAL | N37: =_xlfn.XLOOKUP(D37,[1]!Data[CEDULA],[1]!Data[EPS/SURA],"No Existe",0,1) -> NUEVA E.P.S. | O37: =YEAR(Data[[#This Row],[F. INICIO]]) -> 2024 | P37: 45483 | Q37: 45485 | R37: K040 | S37: =IF(Data[[#This Row],[TIPO DE INCAPACIDAD]]="LICENCIA DE PATERNIDAD","Licencia de paternidad",IF(Data[[#This Row],[TIPO DE INCAPACIDAD]]="LICENCIA DE LUTO","Licencia de Luto",_xlfn.IFNA(VLOOKUP(R37,'CIE-10 PARA RIPS'!$A$6:B13239,2,0),"No especificado"))) -> Pulpitis | T37: =IF(P37<>"", IF(P37>0, IF(P37<=DATE(YEAR(P37),MONTH(P37),DAY(P37)), IF(P37>=DATE(YEAR(P37),MONTH(P37),1), IF(K37>10, C37, IF(SUMIFS($K:$K, $C:$C, C37, $P:$P, ">="&DATE(YEAR(P37),MONTH(P37),1), $P:$P, "<="&EOMONTH(P37,0))>10, C37, "")), ""))), "") | U37: =IF(AND(P37<>"", P37>=DATE(YEAR(P37),MONTH(P37),1), SUMIFS($K:$K, $C:$C, C37, $P:$P, ">="&DATE(YEAR(P37),MONTH(P37),1), $P:$P, "<="&EOMONTH(P37,0))>10), K37, "") | V37: =IF(AND(P37<>"", P37>=DATE(YEAR(P37),MONTH(P37),1), SUMIFS($K:$K, $C:$C, C37, $P:$P, ">="&DATE(YEAR(P37),MONTH(P37),1), $P:$P, "<="&EOMONTH(P37,0))>10), YEAR(P37), "") | W37: =IF(AND(P37<>"", P37>=DATE(YEAR(P37),MONTH(P37),1), SUMIFS($K:$K, $C:$C, C37, $P:$P, ">="&DATE(YEAR(P37),MONTH(P37),1), $P:$P, "<="&EOMONTH(P37,0))>10), TEXT(P37, "MMMM"), "") | X37: {=IF(AND(P37<>"", P37>=DATE(YEAR(P37),MONTH(P37),1), SUMIFS($K:$K, $C:$C, C37, $P:$P, ">="&DATE(YEAR(P37),MONTH(P37),1), $P:$P, "<="&EOMONTH(P37,0))>10), _xlfn.TEXTJOIN(", ", TRUE, _xlfn._xlws.FILTER($R:$R, ($C:$C=C37) * ($P:$P>=DATE(YEAR(P37),MONTH(P37),1)) * ($P:$P<=EOMONTH(P37,0)))), "")} | Y37: {=IF(AND(P37<>"", P37>=DATE(YEAR(P37),MONTH(P37),1), SUMIFS($K:$K, $C:$C, C37, $P:$P, ">="&DATE(YEAR(P37),MONTH(P37),1), $P:$P, "<="&EOMONTH(P37,0))>10), _xlfn.TEXTJOIN(", ", TRUE, _xlfn._xlws.FILTER($S:$S, ($C:$C=C37) * ($P:$P>=DATE(YEAR(P37),MONTH(P37),1)) * ($P:$P<=EOMONTH(P37,0)))), "")}
A38: 31 | B38: TEMPOACTIVA | C38: =_xlfn.XLOOKUP(D38,[1]!Data[CEDULA],[1]!Data[Nombre Completo],"No Existe",0,1) -> NATALIA ISABEL CARDOZO MARTINEZ | D38: 1143454486 | E38: =IFERROR(_xlfn.NUMBERVALUE(Data[[#This Row],[CEDULA ]],",","."),_xlfn.NUMBERVALUE(Data[[#This Row],[CEDULA ]],".",",")) -> 1143454486 | F38: =_xlfn.XLOOKUP(E38,[1]!Data[CEDULA],[1]!Data[CARGO],"No Existe",0,1) -> SUPERNUMERARIO(A) | G38: =_xlfn.XLOOKUP(E38,[1]!Data[CEDULA],[1]!Data[EMPRESA DONDE PRESTA SERVICIO],"No Existe",0,1) -> COMFAMILIAR ATLANTICO | H38: =_xlfn.XLOOKUP(E38,[1]!Data[CEDULA],[1]!Data[UBICACIÓN],"No Existe",0,1) -> PROGRAMAS RECREATIVOS | I38: MUJER | J38: =UPPER(TEXT(Data[[#This Row],[F. INICIO]],"mmmm")) -> JULIO | K38: 2 | L38: ARL | M38: ACCIDENTE LABORAL | N38: =_xlfn.XLOOKUP(D38,[1]!Data[CEDULA],[1]!Data[EPS/SURA],"No Existe",0,1) -> SALUD TOTAL | O38: =YEAR(Data[[#This Row],[F. INICIO]]) -> 2024 | P38: 45497 | Q38: 45498 | R38: S800 | S38: =IF(Data[[#This Row],[TIPO DE INCAPACIDAD]]="LICENCIA DE PATERNIDAD","Licencia de paternidad",IF(Data[[#This Row],[TIPO DE INCAPACIDAD]]="LICENCIA DE LUTO","Licencia de Luto",_xlfn.IFNA(VLOOKUP(R38,'CIE-10 PARA RIPS'!$A$6:B13240,2,0),"No especificado"))) -> Contusion de la rodilla | T38: =IF(P38<>"", IF(P38>0, IF(P38<=DATE(YEAR(P38),MONTH(P38),DAY(P38)), IF(P38>=DATE(YEAR(P38),MONTH(P38),1), IF(K38>10, C38, IF(SUMIFS($K:$K, $C:$C, C38, $P:$P, ">="&DATE(YEAR(P38),MONTH(P38),1), $P:$P, "<="&EOMONTH(P38,0))>10, C38, "")), ""))), "") | U38: =IF(AND(P38<>"", P38>=DATE(YEAR(P38),MONTH(P38),1), SUMIFS($K:$K, $C:$C, C38, $P:$P, ">="&DATE(YEAR(P38),MONTH(P38),1), $P:$P, "<="&EOMONTH(P38,0))>10), K38, "") | V38: =IF(AND(P38<>"", P38>=DATE(YEAR(P38),MONTH(P38),1), SUMIFS($K:$K, $C:$C, C38, $P:$P, ">="&DATE(YEAR(P38),MONTH(P38),1), $P:$P, "<="&EOMONTH(P38,0))>10), YEAR(P38), "") | W38: =IF(AND(P38<>"", P38>=DATE(YEAR(P38),MONTH(P38),1), SUMIFS($K:$K, $C:$C, C38, $P:$P, ">="&DATE(YEAR(P38),MONTH(P38),1), $P:$P, "<="&EOMONTH(P38,0))>10), TEXT(P38, "MMMM"), "") | X38: {=IF(AND(P38<>"", P38>=DATE(YEAR(P38),MONTH(P38),1), SUMIFS($K:$K, $C:$C, C38, $P:$P, ">="&DATE(YEAR(P38),MONTH(P38),1), $P:$P, "<="&EOMONTH(P38,0))>10), _xlfn.TEXTJOIN(", ", TRUE, _xlfn._xlws.FILTER($R:$R, ($C:$C=C38) * ($P:$P>=DATE(YEAR(P38),MONTH(P38),1)) * ($P:$P<=EOMONTH(P38,0)))), "")} | Y38: {=IF(AND(P38<>"", P38>=DATE(YEAR(P38),MONTH(P38),1), SUMIFS($K:$K, $C:$C, C38, $P:$P, ">="&DATE(YEAR(P38),MONTH(P38),1), $P:$P, "<="&EOMONTH(P38,0))>10), _xlfn.TEXTJOIN(", ", TRUE, _xlfn._xlws.FILTER($S:$S, ($C:$C=C38) * ($P:$P>=DATE(YEAR(P38),MONTH(P38),1)) * ($P:$P<=EOMONTH(P38,0)))), "")}
A39: 32 | B39: TEMPOACTIVA | C39: =_xlfn.XLOOKUP(D39,[1]!Data[CEDULA],[1]!Data[Nombre Completo],"No Existe",0,1) -> NICK MEDRANO VERGARA | D39: 1143268971 | E39: =IFERROR(_xlfn.NUMBERVALUE(Data[[#This Row],[CEDULA ]],",","."),_xlfn.NUMBERVALUE(Data[[#This Row],[CEDULA ]],".",",")) -> 1143268971 | F39: =_xlfn.XLOOKUP(E39,[1]!Data[CEDULA],[1]!Data[CARGO],"No Existe",0,1) -> SUPERNUMERARIO(A) | G39: =_xlfn.XLOOKUP(E39,[1]!Data[CEDULA],[1]!Data[EMPRESA DONDE PRESTA SERVICIO],"No Existe",0,1) -> COMFAMILIAR ATLANTICO | H39: =_xlfn.XLOOKUP(E39,[1]!Data[CEDULA],[1]!Data[UBICACIÓN],"No Existe",0,1) -> SEDE CARIBE | I39: HOMBRE | J39: =UPPER(TEXT(Data[[#This Row],[F. INICIO]],"mmmm")) -> JUNIO | K39: 2 | L39: EPS | M39: ENFERMENDAD GENERAL | N39: =_xlfn.XLOOKUP(D39,[1]!Data[CEDULA],[1]!Data[EPS/SURA],"No Existe",0,1) -> EPS/SURA | O39: =YEAR(Data[[#This Row],[F. INICIO]]) -> 2024 | P39: 45447 | Q39: 45448 | R39: S934 | S39: =IF(Data[[#This Row],[TIPO DE INCAPACIDAD]]="LICENCIA DE PATERNIDAD","Licencia de paternidad",IF(Data[[#This Row],[TIPO DE INCAPACIDAD]]="LICENCIA DE LUTO","Licencia de Luto",_xlfn.IFNA(VLOOKUP(R39,'CIE-10 PARA RIPS'!$A$6:B13204,2,0),"No especificado"))) -> Esguinces y torceduras del tobillo | T39: =IF(P39<>"", IF(P39>0, IF(P39<=DATE(YEAR(P39),MONTH(P39),DAY(P39)), IF(P39>=DATE(YEAR(P39),MONTH(P39),1), IF(K39>10, C39, IF(SUMIFS($K:$K, $C:$C, C39, $P:$P, ">="&DATE(YEAR(P39),MONTH(P39),1), $P:$P, "<="&EOMONTH(P39,0))>10, C39, "")), ""))), "") | U39: =IF(AND(P39<>"", P39>=DATE(YEAR(P39),MONTH(P39),1), SUMIFS($K:$K, $C:$C, C39, $P:$P, ">="&DATE(YEAR(P39),MONTH(P39),1), $P:$P, "<="&EOMONTH(P39,0))>10), K39, "") | V39: =IF(AND(P39<>"", P39>=DATE(YEAR(P39),MONTH(P39),1), SUMIFS($K:$K, $C:$C, C39, $P:$P, ">="&DATE(YEAR(P39),MONTH(P39),1), $P:$P, "<="&EOMONTH(P39,0))>10), YEAR(P39), "") | W39: =IF(AND(P39<>"", P39>=DATE(YEAR(P39),MONTH(P39),1), SUMIFS($K:$K, $C:$C, C39, $P:$P, ">="&DATE(YEAR(P39),MONTH(P39),1), $P:$P, "<="&EOMONTH(P39,0))>10), TEXT(P39, "MMMM"), "") | X39: {=IF(AND(P39<>"", P39>=DATE(YEAR(P39),MONTH(P39),1), SUMIFS($K:$K, $C:$C, C39, $P:$P, ">="&DATE(YEAR(P39),MONTH(P39),1), $P:$P, "<="&EOMONTH(P39,0))>10), _xlfn.TEXTJOIN(", ", TRUE, _xlfn._xlws.FILTER($R:$R, ($C:$C=C39) * ($P:$P>=DATE(YEAR(P39),MONTH(P39),1)) * ($P:$P<=EOMONTH(P39,0)))), "")} | Y39: {=IF(AND(P39<>"", P39>=DATE(YEAR(P39),MONTH(P39),1), SUMIFS($K:$K, $C:$C, C39, $P:$P, ">="&DATE(YEAR(P39),MONTH(P39),1), $P:$P, "<="&EOMONTH(P39,0))>10), _xlfn.TEXTJOIN(", ", TRUE, _xlfn._xlws.FILTER($S:$S, ($C:$C=C39) * ($P:$P>=DATE(YEAR(P39),MONTH(P39),1)) * ($P:$P<=EOMONTH(P39,0)))), "")}
A40: 33 | B40: TEMPOACTIVA | C40: =_xlfn.XLOOKUP(D40,[1]!Data[CEDULA],[1]!Data[Nombre Completo],"No Existe",0,1) -> JOSE GREGORIO MARTINEZ MEJIA | D40: 72236916 | E40: =IFERROR(_xlfn.NUMBERVALUE(Data[[#This Row],[CEDULA ]],",","."),_xlfn.NUMBERVALUE(Data[[#This Row],[CEDULA ]],".",",")) -> 72236916 | F40: =_xlfn.XLOOKUP(E40,[1]!Data[CEDULA],[1]!Data[CARGO],"No Existe",0,1) -> CHEF | G40: =_xlfn.XLOOKUP(E40,[1]!Data[CEDULA],[1]!Data[EMPRESA DONDE PRESTA SERVICIO],"No Existe",0,1) -> COMFAMILIAR ATLANTICO | H40: =_xlfn.XLOOKUP(E40,[1]!Data[CEDULA],[1]!Data[UBICACIÓN],"No Existe",0,1) -> SEDE CARIBE MERCADEO | I40: HOMBRE | J40: =UPPER(TEXT(Data[[#This Row],[F. INICIO]],"mmmm")) -> JUNIO | K40: 2 | L40: EPS | M40: ENFERMENDAD GENERAL | N40: =_xlfn.XLOOKUP(D40,[1]!Data[CEDULA],[1]!Data[EPS/SURA],"No Existe",0,1) -> EPS/SURA | O40: =YEAR(Data[[#This Row],[F. INICIO]]) -> 2024 | P40: 45450 | Q40: 45451 | R40: J00X | S40: =IF(Data[[#This Row],[TIPO DE INCAPACIDAD]]="LICENCIA DE PATERNIDAD","Licencia de paternidad",IF(Data[[#This Row],[TIPO DE INCAPACIDAD]]="LICENCIA DE LUTO","Licencia de Luto",_xlfn.IFNA(VLOOKUP(R40,'CIE-10 PARA RIPS'!$A$6:B13205,2,0),"No especificado"))) -> Rinofaringitis aguda [resfriado comun] | T40: =IF(P40<>"", IF(P40>0, IF(P40<=DATE(YEAR(P40),MONTH(P40),DAY(P40)), IF(P40>=DATE(YEAR(P40),MONTH(P40),1), IF(K40>10, C40, IF(SUMIFS($K:$K, $C:$C, C40, $P:$P, ">="&DATE(YEAR(P40),MONTH(P40),1), $P:$P, "<="&EOMONTH(P40,0))>10, C40, "")), ""))), "") | U40: =IF(AND(P40<>"", P40>=DATE(YEAR(P40),MONTH(P40),1), SUMIFS($K:$K, $C:$C, C40, $P:$P, ">="&DATE(YEAR(P40),MONTH(P40),1), $P:$P, "<="&EOMONTH(P40,0))>10), K40, "") | V40: =IF(AND(P40<>"", P40>=DATE(YEAR(P40),MONTH(P40),1), SUMIFS($K:$K, $C:$C, C40, $P:$P, ">="&DATE(YEAR(P40),MONTH(P40),1), $P:$P, "<="&EOMONTH(P40,0))>10), YEAR(P40), "") | W40: =IF(AND(P40<>"", P40>=DATE(YEAR(P40),MONTH(P40),1), SUMIFS($K:$K, $C:$C, C40, $P:$P, ">="&DATE(YEAR(P40),MONTH(P40),1), $P:$P, "<="&EOMONTH(P40,0))>10), TEXT(P40, "MMMM"), "") | X40: {=IF(AND(P40<>"", P40>=DATE(YEAR(P40),MONTH(P40),1), SUMIFS($K:$K, $C:$C, C40, $P:$P, ">="&DATE(YEAR(P40),MONTH(P40),1), $P:$P, "<="&EOMONTH(P40,0))>10), _xlfn.TEXTJOIN(", ", TRUE, _xlfn._xlws.FILTER($R:$R, ($C:$C=C40) * ($P:$P>=DATE(YEAR(P40),MONTH(P40),1)) * ($P:$P<=EOMONTH(P40,0)))), "")} | Y40: {=IF(AND(P40<>"", P40>=DATE(YEAR(P40),MONTH(P40),1), SUMIFS($K:$K, $C:$C, C40, $P:$P, ">="&DATE(YEAR(P40),MONTH(P40),1), $P:$P, "<="&EOMONTH(P40,0))>10), _xlfn.TEXTJOIN(", ", TRUE, _xlfn._xlws.FILTER($S:$S, ($C:$C=C40) * ($P:$P>=DATE(YEAR(P40),MONTH(P40),1)) * ($P:$P<=EOMONTH(P40,0)))), "")}
A41: 34 | B41: TEMPOACTIVA | C41: =_xlfn.XLOOKUP(D41,[1]!Data[CEDULA],[1]!Data[Nombre Completo],"No Existe",0,1) -> CARLOS ALFREDO DAZA MOLINA | D41: 1044395232 | E41: =IFERROR(_xlfn.NUMBERVALUE(Data[[#This Row],[CEDULA ]],",","."),_xlfn.NUMBERVALUE(Data[[#This Row],[CEDULA ]],".",",")) -> 1044395232 | F41: =_xlfn.XLOOKUP(E41,[1]!Data[CEDULA],[1]!Data[CARGO],"No Existe",0,1) -> SUPERNUMERARIO(A) | G41: =_xlfn.XLOOKUP(E41,[1]!Data[CEDULA],[1]!Data[EMPRESA DONDE PRESTA SERVICIO],"No Existe",0,1) -> COMFAMILIAR ATLANTICO | H41: =_xlfn.XLOOKUP(E41,[1]!Data[CEDULA],[1]!Data[UBICACIÓN],"No Existe",0,1) -> CENTRO RECREACIONAL TURIPANA | I41: HOMBRE | J41: =UPPER(TEXT(Data[[#This Row],[F. INICIO]],"mmmm")) -> JUNIO | K41: 2 | L41: EPS | M41: ENFERMENDAD GENERAL | N41: =_xlfn.XLOOKUP(D41,[1]!Data[CEDULA],[1]!Data[EPS/SURA],"No Existe",0,1) -> NUEVA E.P.S. | O41: =YEAR(Data[[#This Row],[F. INICIO]]) -> 2024 | P41: 45450 | Q41: 45451 | R41: J00X | S41: =IF(Data[[#This Row],[TIPO DE INCAPACIDAD]]="LICENCIA DE PATERNIDAD","Licencia de paternidad",IF(Data[[#This Row],[TIPO DE INCAPACIDAD]]="LICENCIA DE LUTO","Licencia de Luto",_xlfn.IFNA(VLOOKUP(R41,'CIE-10 PARA RIPS'!$A$6:B13206,2,0),"No especificado"))) -> Rinofaringitis aguda [resfriado comun] | T41: =IF(P41<>"", IF(P41>0, IF(P41<=DATE(YEAR(P41),MONTH(P41),DAY(P41)), IF(P41>=DATE(YEAR(P41),MONTH(P41),1), IF(K41>10, C41, IF(SUMIFS($K:$K, $C:$C, C41, $P:$P, ">="&DATE(YEAR(P41),MONTH(P41),1), $P:$P, "<="&EOMONTH(P41,0))>10, C41, "")), ""))), "") | U41: =IF(AND(P41<>"", P41>=DATE(YEAR(P41),MONTH(P41),1), SUMIFS($K:$K, $C:$C, C41, $P:$P, ">="&DATE(YEAR(P41),MONTH(P41),1), $P:$P, "<="&EOMONTH(P41,0))>10), K41, "") | V41: =IF(AND(P41<>"", P41>=DATE(YEAR(P41),MONTH(P41),1), SUMIFS($K:$K, $C:$C, C41, $P:$P, ">="&DATE(YEAR(P41),MONTH(P41),1), $P:$P, "<="&EOMONTH(P41,0))>10), YEAR(P41), "") | W41: =IF(AND(P41<>"", P41>=DATE(YEAR(P41),MONTH(P41),1), SUMIFS($K:$K, $C:$C, C41, $P:$P, ">="&DATE(YEAR(P41),MONTH(P41),1), $P:$P, "<="&EOMONTH(P41,0))>10), TEXT(P41, "MMMM"), "") | X41: {=IF(AND(P41<>"", P41>=DATE(YEAR(P41),MONTH(P41),1), SUMIFS($K:$K, $C:$C, C41, $P:$P, ">="&DATE(YEAR(P41),MONTH(P41),1), $P:$P, "<="&EOMONTH(P41,0))>10), _xlfn.TEXTJOIN(", ", TRUE, _xlfn._xlws.FILTER($R:$R, ($C:$C=C41) * ($P:$P>=DATE(YEAR(P41),MONTH(P41),1)) * ($P:$P<=EOMONTH(P41,0)))), "")} | Y41: {=IF(AND(P41<>"", P41>=DATE(YEAR(P41),MONTH(P41),1), SUMIFS($K:$K, $C:$C, C41, $P:$P, ">="&DATE(YEAR(P41),MONTH(P41),1), $P:$P, "<="&EOMONTH(P41,0))>10), _xlfn.TEXTJOIN(", ", TRUE, _xlfn._xlws.FILTER($S:$S, ($C:$C=C41) * ($P:$P>=DATE(YEAR(P41),MONTH(P41),1)) * ($P:$P<=EOMONTH(P41,0)))), "")}
A42: 35 | B42: TEMPOACTIVA | C42: =_xlfn.XLOOKUP(D42,[1]!Data[CEDULA],[1]!Data[Nombre Completo],"No Existe",0,1) -> GENILZON DE JESUS BARRAZA OROZCO | D42: 1044424983 | E42: =IFERROR(_xlfn.NUMBERVALUE(Data[[#This Row],[CEDULA ]],",","."),_xlfn.NUMBERVALUE(Data[[#This Row],[CEDULA ]],".",",")) -> 1044424983 | F42: =_xlfn.XLOOKUP(E42,[1]!Data[CEDULA],[1]!Data[CARGO],"No Existe",0,1) -> SALVAVIDAS | G42: =_xlfn.XLOOKUP(E42,[1]!Data[CEDULA],[1]!Data[EMPRESA DONDE PRESTA SERVICIO],"No Existe",0,1) -> COMFAMILIAR ATLANTICO | H42: =_xlfn.XLOOKUP(E42,[1]!Data[CEDULA],[1]!Data[UBICACIÓN],"No Existe",0,1) -> SEDE CARIBE | I42: HOMBRE | J42: =UPPER(TEXT(Data[[#This Row],[F. INICIO]],"mmmm")) -> JUNIO | K42: 1 | L42: EPS | M42: ENFERMENDAD GENERAL | N42: =_xlfn.XLOOKUP(D42,[1]!Data[CEDULA],[1]!Data[EPS/SURA],"No Existe",0,1) -> MUTUALSER | O42: =YEAR(Data[[#This Row],[F. INICIO]]) -> 2024 | P42: 45451 | Q42: 45451 | R42: A09X | S42: =IF(Data[[#This Row],[TIPO DE INCAPACIDAD]]="LICENCIA DE PATERNIDAD","Licencia de paternidad",IF(Data[[#This Row],[TIPO DE INCAPACIDAD]]="LICENCIA DE LUTO","Licencia de Luto",_xlfn.IFNA(VLOOKUP(R42,'CIE-10 PARA RIPS'!$A$6:B13207,2,0),"No especificado"))) -> Diarrea y gastroenteritis de presunto origen infeccioso | T42: =IF(P42<>"", IF(P42>0, IF(P42<=DATE(YEAR(P42),MONTH(P42),DAY(P42)), IF(P42>=DATE(YEAR(P42),MONTH(P42),1), IF(K42>10, C42, IF(SUMIFS($K:$K, $C:$C, C42, $P:$P, ">="&DATE(YEAR(P42),MONTH(P42),1), $P:$P, "<="&EOMONTH(P42,0))>10, C42, "")), ""))), "") | U42: =IF(AND(P42<>"", P42>=DATE(YEAR(P42),MONTH(P42),1), SUMIFS($K:$K, $C:$C, C42, $P:$P, ">="&DATE(YEAR(P42),MONTH(P42),1), $P:$P, "<="&EOMONTH(P42,0))>10), K42, "") | V42: =IF(AND(P42<>"", P42>=DATE(YEAR(P42),MONTH(P42),1), SUMIFS($K:$K, $C:$C, C42, $P:$P, ">="&DATE(YEAR(P42),MONTH(P42),1), $P:$P, "<="&EOMONTH(P42,0))>10), YEAR(P42), "") | W42: =IF(AND(P42<>"", P42>=DATE(YEAR(P42),MONTH(P42),1), SUMIFS($K:$K, $C:$C, C42, $P:$P, ">="&DATE(YEAR(P42),MONTH(P42),1), $P:$P, "<="&EOMONTH(P42,0))>10), TEXT(P42, "MMMM"), "") | X42: {=IF(AND(P42<>"", P42>=DATE(YEAR(P42),MONTH(P42),1), SUMIFS($K:$K, $C:$C, C42, $P:$P, ">="&DATE(YEAR(P42),MONTH(P42),1), $P:$P, "<="&EOMONTH(P42,0))>10), _xlfn.TEXTJOIN(", ", TRUE, _xlfn._xlws.FILTER($R:$R, ($C:$C=C42) * ($P:$P>=DATE(YEAR(P42),MONTH(P42),1)) * ($P:$P<=EOMONTH(P42,0)))), "")} | Y42: {=IF(AND(P42<>"", P42>=DATE(YEAR(P42),MONTH(P42),1), SUMIFS($K:$K, $C:$C, C42, $P:$P, ">="&DATE(YEAR(P42),MONTH(P42),1), $P:$P, "<="&EOMONTH(P42,0))>10), _xlfn.TEXTJOIN(", ", TRUE, _xlfn._xlws.FILTER($S:$S, ($C:$C=C42) * ($P:$P>=DATE(YEAR(P42),MONTH(P42),1)) * ($P:$P<=EOMONTH(P42,0)))), "")}
A43: 36 | B43: TEMPOACTIVA | C43: =_xlfn.XLOOKUP(D43,[1]!Data[CEDULA],[1]!Data[Nombre Completo],"No Existe",0,1) -> ROBERTS DE JESUS VIECCO MOLINA | D43: 1042849492 | E43: =IFERROR(_xlfn.NUMBERVALUE(Data[[#This Row],[CEDULA ]],",","."),_xlfn.NUMBERVALUE(Data[[#This Row],[CEDULA ]],".",",")) -> 1042849492 | F43: =_xlfn.XLOOKUP(E43,[1]!Data[CEDULA],[1]!Data[CARGO],"No Existe",0,1) -> AUXILIAR DE COCINA | G43: =_xlfn.XLOOKUP(E43,[1]!Data[CEDULA],[1]!Data[EMPRESA DONDE PRESTA SERVICIO],"No Existe",0,1) -> COMFAMILIAR ATLANTICO | H43: =_xlfn.XLOOKUP(E43,[1]!Data[CEDULA],[1]!Data[UBICACIÓN],"No Existe",0,1) -> SEDE CARIBE MERCADEO | I43: HOMBRE | J43: =UPPER(TEXT(Data[[#This Row],[F. INICIO]],"mmmm")) -> JUNIO | K43: 2 | L43: EPS | M43: ENFERMENDAD GENERAL | N43: =_xlfn.XLOOKUP(D43,[1]!Data[CEDULA],[1]!Data[EPS/SURA],"No Existe",0,1) -> EPS/SURA | O43: =YEAR(Data[[#This Row],[F. INICIO]]) -> 2024 | P43: 45452 | Q43: 45453 | R43: J00X | S43: =IF(Data[[#This Row],[TIPO DE INCAPACIDAD]]="LICENCIA DE PATERNIDAD","Licencia de paternidad",IF(Data[[#This Row],[TIPO DE INCAPACIDAD]]="LICENCIA DE LUTO","Licencia de Luto",_xlfn.IFNA(VLOOKUP(R43,'CIE-10 PARA RIPS'!$A$6:B13208,2,0),"No especificado"))) -> Rinofaringitis aguda [resfriado comun] | T43: =IF(P43<>"", IF(P43>0, IF(P43<=DATE(YEAR(P43),MONTH(P43),DAY(P43)), IF(P43>=DATE(YEAR(P43),MONTH(P43),1), IF(K43>10, C43, IF(SUMIFS($K:$K, $C:$C, C43, $P:$P, ">="&DATE(YEAR(P43),MONTH(P43),1), $P:$P, "<="&EOMONTH(P43,0))>10, C43, "")), ""))), "") | U43: =IF(AND(P43<>"", P43>=DATE(YEAR(P43),MONTH(P43),1), SUMIFS($K:$K, $C:$C, C43, $P:$P, ">="&DATE(YEAR(P43),MONTH(P43),1), $P:$P, "<="&EOMONTH(P43,0))>10), K43, "") | V43: =IF(AND(P43<>"", P43>=DATE(YEAR(P43),MONTH(P43),1), SUMIFS($K:$K, $C:$C, C43, $P:$P, ">="&DATE(YEAR(P43),MONTH(P43),1), $P:$P, "<="&EOMONTH(P43,0))>10), YEAR(P43), "") | W43: =IF(AND(P43<>"", P43>=DATE(YEAR(P43),MONTH(P43),1), SUMIFS($K:$K, $C:$C, C43, $P:$P, ">="&DATE(YEAR(P43),MONTH(P43),1), $P:$P, "<="&EOMONTH(P43,0))>10), TEXT(P43, "MMMM"), "") | X43: {=IF(AND(P43<>"", P43>=DATE(YEAR(P43),MONTH(P43),1), SUMIFS($K:$K, $C:$C, C43, $P:$P, ">="&DATE(YEAR(P43),MONTH(P43),1), $P:$P, "<="&EOMONTH(P43,0))>10), _xlfn.TEXTJOIN(", ", TRUE, _xlfn._xlws.FILTER($R:$R, ($C:$C=C43) * ($P:$P>=DATE(YEAR(P43),MONTH(P43),1)) * ($P:$P<=EOMONTH(P43,0)))), "")} | Y43: {=IF(AND(P43<>"", P43>=DATE(YEAR(P43),MONTH(P43),1), SUMIFS($K:$K, $C:$C, C43, $P:$P, ">="&DATE(YEAR(P43),MONTH(P43),1), $P:$P, "<="&EOMONTH(P43,0))>10), _xlfn.TEXTJOIN(", ", TRUE, _xlfn._xlws.FILTER($S:$S, ($C:$C=C43) * ($P:$P>=DATE(YEAR(P43),MONTH(P43),1)) * ($P:$P<=EOMONTH(P43,0)))), "")}
A44: 37 | B44: TEMPOACTIVA | C44: =_xlfn.XLOOKUP(D44,[1]!Data[CEDULA],[1]!Data[Nombre Completo],"No Existe",0,1) -> PEDRO FABIAN ARIZA MAESTRE | D44: 1045228765 | E44: =IFERROR(_xlfn.NUMBERVALUE(Data[[#This Row],[CEDULA ]],",","."),_xlfn.NUMBERVALUE(Data[[#This Row],[CEDULA ]],".",",")) -> 1045228765 | F44: =_xlfn.XLOOKUP(E44,[1]!Data[CEDULA],[1]!Data[CARGO],"No Existe",0,1) -> STEWARD | G44: =_xlfn.XLOOKUP(E44,[1]!Data[CEDULA],[1]!Data[EMPRESA DONDE PRESTA SERVICIO],"No Existe",0,1) -> COMFAMILIAR ATLANTICO | H44: =_xlfn.XLOOKUP(E44,[1]!Data[CEDULA],[1]!Data[UBICACIÓN],"No Existe",0,1) -> CENTRO DE PROCESAMIENTO | I44: HOMBRE | J44: =UPPER(TEXT(Data[[#This Row],[F. INICIO]],"mmmm")) -> JUNIO | K44: 1 | L44: EPS | M44: ENFERMENDAD GENERAL | N44: =_xlfn.XLOOKUP(D44,[1]!Data[CEDULA],[1]!Data[EPS/SURA],"No Existe",0,1) -> NUEVA E.P.S. | O44: =YEAR(Data[[#This Row],[F. INICIO]]) -> 2024 | P44: 45454 | Q44: 45454 | R44: J069 | S44: =IF(Data[[#This Row],[TIPO DE INCAPACIDAD]]="LICENCIA DE PATERNIDAD","Licencia de paternidad",IF(Data[[#This Row],[TIPO DE INCAPACIDAD]]="LICENCIA DE LUTO","Licencia de Luto",_xlfn.IFNA(VLOOKUP(R44,'CIE-10 PARA RIPS'!$A$6:B13209,2,0),"No especificado"))) -> Infeccion aguda de las vias respiratorias superiores, no especificada | T44: =IF(P44<>"", IF(P44>0, IF(P44<=DATE(YEAR(P44),MONTH(P44),DAY(P44)), IF(P44>=DATE(YEAR(P44),MONTH(P44),1), IF(K44>10, C44, IF(SUMIFS($K:$K, $C:$C, C44, $P:$P, ">="&DATE(YEAR(P44),MONTH(P44),1), $P:$P, "<="&EOMONTH(P44,0))>10, C44, "")), ""))), "") | U44: =IF(AND(P44<>"", P44>=DATE(YEAR(P44),MONTH(P44),1), SUMIFS($K:$K, $C:$C, C44, $P:$P, ">="&DATE(YEAR(P44),MONTH(P44),1), $P:$P, "<="&EOMONTH(P44,0))>10), K44, "") | V44: =IF(AND(P44<>"", P44>=DATE(YEAR(P44),MONTH(P44),1), SUMIFS($K:$K, $C:$C, C44, $P:$P, ">="&DATE(YEAR(P44),MONTH(P44),1), $P:$P, "<="&EOMONTH(P44,0))>10), YEAR(P44), "") | W44: =IF(AND(P44<>"", P44>=DATE(YEAR(P44),MONTH(P44),1), SUMIFS($K:$K, $C:$C, C44, $P:$P, ">="&DATE(YEAR(P44),MONTH(P44),1), $P:$P, "<="&EOMONTH(P44,0))>10), TEXT(P44, "MMMM"), "") | X44: {=IF(AND(P44<>"", P44>=DATE(YEAR(P44),MONTH(P44),1), SUMIFS($K:$K, $C:$C, C44, $P:$P, ">="&DATE(YEAR(P44),MONTH(P44),1), $P:$P, "<="&EOMONTH(P44,0))>10), _xlfn.TEXTJOIN(", ", TRUE, _xlfn._xlws.FILTER($R:$R, ($C:$C=C44) * ($P:$P>=DATE(YEAR(P44),MONTH(P44),1)) * ($P:$P<=EOMONTH(P44,0)))), "")} | Y44: {=IF(AND(P44<>"", P44>=DATE(YEAR(P44),MONTH(P44),1), SUMIFS($K:$K, $C:$C, C44, $P:$P, ">="&DATE(YEAR(P44),MONTH(P44),1), $P:$P, "<="&EOMONTH(P44,0))>10), _xlfn.TEXTJOIN(", ", TRUE, _xlfn._xlws.FILTER($S:$S, ($C:$C=C44) * ($P:$P>=DATE(YEAR(P44),MONTH(P44),1)) * ($P:$P<=EOMONTH(P44,0)))), "")}
A45: 38 | B45: TEMPOACTIVA | C45: =_xlfn.XLOOKUP(D45,[1]!Data[CEDULA],[1]!Data[Nombre Completo],"No Existe",0,1) -> NICK MEDRANO VERGARA | D45: 1143268971 | E45: =IFERROR(_xlfn.NUMBERVALUE(Data[[#This Row],[CEDULA ]],",","."),_xlfn.NUMBERVALUE(Data[[#This Row],[CEDULA ]],".",",")) -> 1143268971 | F45: =_xlfn.XLOOKUP(E45,[1]!Data[CEDULA],[1]!Data[CARGO],"No Existe",0,1) -> SUPERNUMERARIO(A) | G45: =_xlfn.XLOOKUP(E45,[1]!Data[CEDULA],[1]!Data[EMPRESA DONDE PRESTA SERVICIO],"No Existe",0,1) -> COMFAMILIAR ATLANTICO | H45: =_xlfn.XLOOKUP(E45,[1]!Data[CEDULA],[1]!Data[UBICACIÓN],"No Existe",0,1) -> SEDE CARIBE | I45: HOMBRE | J45: =UPPER(TEXT(Data[[#This Row],[F. INICIO]],"mmmm")) -> JUNIO | K45: 2 | L45: EPS | M45: ENFERMENDAD GENERAL | N45: =_xlfn.XLOOKUP(D45,[1]!Data[CEDULA],[1]!Data[EPS/SURA],"No Existe",0,1) -> EPS/SURA | O45: =YEAR(Data[[#This Row],[F. INICIO]]) -> 2024 | P45: 45449 | Q45: 45450 | R45: S934 | S45: =IF(Data[[#This Row],[TIPO DE INCAPACIDAD]]="LICENCIA DE PATERNIDAD","Licencia de paternidad",IF(Data[[#This Row],[TIPO DE INCAPACIDAD]]="LICENCIA DE LUTO","Licencia de Luto",_xlfn.IFNA(VLOOKUP(R45,'CIE-10 PARA RIPS'!$A$6:B13212,2,0),"No especificado"))) -> Esguinces y torceduras del tobillo | T45: =IF(P45<>"", IF(P45>0, IF(P45<=DATE(YEAR(P45),MONTH(P45),DAY(P45)), IF(P45>=DATE(YEAR(P45),MONTH(P45),1), IF(K45>10, C45, IF(SUMIFS($K:$K, $C:$C, C45, $P:$P, ">="&DATE(YEAR(P45),MONTH(P45),1), $P:$P, "<="&EOMONTH(P45,0))>10, C45, "")), ""))), "") | U45: =IF(AND(P45<>"", P45>=DATE(YEAR(P45),MONTH(P45),1), SUMIFS($K:$K, $C:$C, C45, $P:$P, ">="&DATE(YEAR(P45),MONTH(P45),1), $P:$P, "<="&EOMONTH(P45,0))>10), K45, "") | V45: =IF(AND(P45<>"", P45>=DATE(YEAR(P45),MONTH(P45),1), SUMIFS($K:$K, $C:$C, C45, $P:$P, ">="&DATE(YEAR(P45),MONTH(P45),1), $P:$P, "<="&EOMONTH(P45,0))>10), YEAR(P45), "") | W45: =IF(AND(P45<>"", P45>=DATE(YEAR(P45),MONTH(P45),1), SUMIFS($K:$K, $C:$C, C45, $P:$P, ">="&DATE(YEAR(P45),MONTH(P45),1), $P:$P, "<="&EOMONTH(P45,0))>10), TEXT(P45, "MMMM"), "") | X45: {=IF(AND(P45<>"", P45>=DATE(YEAR(P45),MONTH(P45),1), SUMIFS($K:$K, $C:$C, C45, $P:$P, ">="&DATE(YEAR(P45),MONTH(P45),1), $P:$P, "<="&EOMONTH(P45,0))>10), _xlfn.TEXTJOIN(", ", TRUE, _xlfn._xlws.FILTER($R:$R, ($C:$C=C45) * ($P:$P>=DATE(YEAR(P45),MONTH(P45),1)) * ($P:$P<=EOMONTH(P45,0)))), "")} | Y45: {=IF(AND(P45<>"", P45>=DATE(YEAR(P45),MONTH(P45),1), SUMIFS($K:$K, $C:$C, C45, $P:$P, ">="&DATE(YEAR(P45),MONTH(P45),1), $P:$P, "<="&EOMONTH(P45,0))>10), _xlfn.TEXTJOIN(", ", TRUE, _xlfn._xlws.FILTER($S:$S, ($C:$C=C45) * ($P:$P>=DATE(YEAR(P45),MONTH(P45),1)) * ($P:$P<=EOMONTH(P45,0)))), "")}
A46: 39 | B46: TEMPOACTIVA | C46: =_xlfn.XLOOKUP(D46,[1]!Data[CEDULA],[1]!Data[Nombre Completo],"No Existe",0,1) -> HILDEMARO JOSE MEJIA OROZCO | D46: 77036603 | E46: =IFERROR(_xlfn.NUMBERVALUE(Data[[#This Row],[CEDULA ]],",","."),_xlfn.NUMBERVALUE(Data[[#This Row],[CEDULA ]],".",",")) -> 77036603 | F46: =_xlfn.XLOOKUP(E46,[1]!Data[CEDULA],[1]!Data[CARGO],"No Existe",0,1) -> OFICIOS VARIOS | G46: =_xlfn.XLOOKUP(E46,[1]!Data[CEDULA],[1]!Data[EMPRESA DONDE PRESTA SERVICIO],"No Existe",0,1) -> COMFAMILIAR ATLANTICO | H46: =_xlfn.XLOOKUP(E46,[1]!Data[CEDULA],[1]!Data[UBICACIÓN],"No Existe",0,1) -> ASEO | I46: HOMBRE | J46: =UPPER(TEXT(Data[[#This Row],[F. INICIO]],"mmmm")) -> JUNIO | K46: 5 | L46: EPS | M46: ENFERMENDAD GENERAL | N46: =_xlfn.XLOOKUP(D46,[1]!Data[CEDULA],[1]!Data[EPS/SURA],"No Existe",0,1) -> NUEVA E.P.S. | O46: =YEAR(Data[[#This Row],[F. INICIO]]) -> 2024 | P46: 45453 | Q46: 45457 | R46: R42X | S46: =IF(Data[[#This Row],[TIPO DE INCAPACIDAD]]="LICENCIA DE PATERNIDAD","Licencia de paternidad",IF(Data[[#This Row],[TIPO DE INCAPACIDAD]]="LICENCIA DE LUTO","Licencia de Luto",_xlfn.IFNA(VLOOKUP(R46,'CIE-10 PARA RIPS'!$A$6:B13216,2,0),"No especificado"))) -> Mareo y desvanecimiento | T46: =IF(P46<>"", IF(P46>0, IF(P46<=DATE(YEAR(P46),MONTH(P46),DAY(P46)), IF(P46>=DATE(YEAR(P46),MONTH(P46),1), IF(K46>10, C46, IF(SUMIFS($K:$K, $C:$C, C46, $P:$P, ">="&DATE(YEAR(P46),MONTH(P46),1), $P:$P, "<="&EOMONTH(P46,0))>10, C46, "")), ""))), "") | U46: =IF(AND(P46<>"", P46>=DATE(YEAR(P46),MONTH(P46),1), SUMIFS($K:$K, $C:$C, C46, $P:$P, ">="&DATE(YEAR(P46),MONTH(P46),1), $P:$P, "<="&EOMONTH(P46,0))>10), K46, "") | V46: =IF(AND(P46<>"", P46>=DATE(YEAR(P46),MONTH(P46),1), SUMIFS($K:$K, $C:$C, C46, $P:$P, ">="&DATE(YEAR(P46),MONTH(P46),1), $P:$P, "<="&EOMONTH(P46,0))>10), YEAR(P46), "") | W46: =IF(AND(P46<>"", P46>=DATE(YEAR(P46),MONTH(P46),1), SUMIFS($K:$K, $C:$C, C46, $P:$P, ">="&DATE(YEAR(P46),MONTH(P46),1), $P:$P, "<="&EOMONTH(P46,0))>10), TEXT(P46, "MMMM"), "") | X46: {=IF(AND(P46<>"", P46>=DATE(YEAR(P46),MONTH(P46),1), SUMIFS($K:$K, $C:$C, C46, $P:$P, ">="&DATE(YEAR(P46),MONTH(P46),1), $P:$P, "<="&EOMONTH(P46,0))>10), _xlfn.TEXTJOIN(", ", TRUE, _xlfn._xlws.FILTER($R:$R, ($C:$C=C46) * ($P:$P>=DATE(YEAR(P46),MONTH(P46),1)) * ($P:$P<=EOMONTH(P46,0)))), "")} | Y46: {=IF(AND(P46<>"", P46>=DATE(YEAR(P46),MONTH(P46),1), SUMIFS($K:$K, $C:$C, C46, $P:$P, ">="&DATE(YEAR(P46),MONTH(P46),1), $P:$P, "<="&EOMONTH(P46,0))>10), _xlfn.TEXTJOIN(", ", TRUE, _xlfn._xlws.FILTER($S:$S, ($C:$C=C46) * ($P:$P>=DATE(YEAR(P46),MONTH(P46),1)) * ($P:$P<=EOMONTH(P46,0)))), "")}
A47: 40 | B47: TEMPOACTIVA | C47: =_xlfn.XLOOKUP(D47,[1]!Data[CEDULA],[1]!Data[Nombre Completo],"No Existe",0,1) -> HILDEMARO JOSE MEJIA OROZCO | D47: 77036603 | E47: =IFERROR(_xlfn.NUMBERVALUE(Data[[#This Row],[CEDULA ]],",","."),_xlfn.NUMBERVALUE(Data[[#This Row],[CEDULA ]],".",",")) -> 77036603 | F47: =_xlfn.XLOOKUP(E47,[1]!Data[CEDULA],[1]!Data[CARGO],"No Existe",0,1) -> OFICIOS VARIOS | G47: =_xlfn.XLOOKUP(E47,[1]!Data[CEDULA],[1]!Data[EMPRESA DONDE PRESTA SERVICIO],"No Existe",0,1) -> COMFAMILIAR ATLANTICO | H47: =_xlfn.XLOOKUP(E47,[1]!Data[CEDULA],[1]!Data[UBICACIÓN],"No Existe",0,1) -> ASEO | I47: HOMBRE | J47: =UPPER(TEXT(Data[[#This Row],[F. INICIO]],"mmmm")) -> JUNIO | K47: 2 | L47: EPS | M47: ENFERMENDAD GENERAL | N47: =_xlfn.XLOOKUP(D47,[1]!Data[CEDULA],[1]!Data[EPS/SURA],"No Existe",0,1) -> NUEVA E.P.S. | O47: =YEAR(Data[[#This Row],[F. INICIO]]) -> 2024 | P47: 45452 | Q47: 45453 | R47: S619 | S47: =IF(Data[[#This Row],[TIPO DE INCAPACIDAD]]="LICENCIA DE PATERNIDAD","Licencia de paternidad",IF(Data[[#This Row],[TIPO DE INCAPACIDAD]]="LICENCIA DE LUTO","Licencia de Luto",_xlfn.IFNA(VLOOKUP(R47,'CIE-10 PARA RIPS'!$A$6:B13217,2,0),"No especificado"))) -> Herida de la muneca y de la mano, parte no especificada | T47: =IF(P47<>"", IF(P47>0, IF(P47<=DATE(YEAR(P47),MONTH(P47),DAY(P47)), IF(P47>=DATE(YEAR(P47),MONTH(P47),1), IF(K47>10, C47, IF(SUMIFS($K:$K, $C:$C, C47, $P:$P, ">="&DATE(YEAR(P47),MONTH(P47),1), $P:$P, "<="&EOMONTH(P47,0))>10, C47, "")), ""))), "") | U47: =IF(AND(P47<>"", P47>=DATE(YEAR(P47),MONTH(P47),1), SUMIFS($K:$K, $C:$C, C47, $P:$P, ">="&DATE(YEAR(P47),MONTH(P47),1), $P:$P, "<="&EOMONTH(P47,0))>10), K47, "") | V47: =IF(AND(P47<>"", P47>=DATE(YEAR(P47),MONTH(P47),1), SUMIFS($K:$K, $C:$C, C47, $P:$P, ">="&DATE(YEAR(P47),MONTH(P47),1), $P:$P, "<="&EOMONTH(P47,0))>10), YEAR(P47), "") | W47: =IF(AND(P47<>"", P47>=DATE(YEAR(P47),MONTH(P47),1), SUMIFS($K:$K, $C:$C, C47, $P:$P, ">="&DATE(YEAR(P47),MONTH(P47),1), $P:$P, "<="&EOMONTH(P47,0))>10), TEXT(P47, "MMMM"), "") | X47: {=IF(AND(P47<>"", P47>=DATE(YEAR(P47),MONTH(P47),1), SUMIFS($K:$K, $C:$C, C47, $P:$P, ">="&DATE(YEAR(P47),MONTH(P47),1), $P:$P, "<="&EOMONTH(P47,0))>10), _xlfn.TEXTJOIN(", ", TRUE, _xlfn._xlws.FILTER($R:$R, ($C:$C=C47) * ($P:$P>=DATE(YEAR(P47),MONTH(P47),1)) * ($P:$P<=EOMONTH(P47,0)))), "")} | Y47: {=IF(AND(P47<>"", P47>=DATE(YEAR(P47),MONTH(P47),1), SUMIFS($K:$K, $C:$C, C47, $P:$P, ">="&DATE(YEAR(P47),MONTH(P47),1), $P:$P, "<="&EOMONTH(P47,0))>10), _xlfn.TEXTJOIN(", ", TRUE, _xlfn._xlws.FILTER($S:$S, ($C:$C=C47) * ($P:$P>=DATE(YEAR(P47),MONTH(P47),1)) * ($P:$P<=EOMONTH(P47,0)))), "")}
A48: 41 | B48: TEMPOACTIVA | C48: =_xlfn.XLOOKUP(D48,[1]!Data[CEDULA],[1]!Data[Nombre Completo],"No Existe",0,1) -> JOSE LUIS MEZA FONSECA | D48: 1143426953 | E48: =IFERROR(_xlfn.NUMBERVALUE(Data[[#This Row],[CEDULA ]],",","."),_xlfn.NUMBERVALUE(Data[[#This Row],[CEDULA ]],".",",")) -> 1143426953 | F48: =_xlfn.XLOOKUP(E48,[1]!Data[CEDULA],[1]!Data[CARGO],"No Existe",0,1) -> INSTRUCTOR | G48: =_xlfn.XLOOKUP(E48,[1]!Data[CEDULA],[1]!Data[EMPRESA DONDE PRESTA SERVICIO],"No Existe",0,1) -> COMFAMILIAR ATLANTICO | H48: =_xlfn.XLOOKUP(E48,[1]!Data[CEDULA],[1]!Data[UBICACIÓN],"No Existe",0,1) -> SEDE SPORT GYM | I48: HOMBRE | J48: =UPPER(TEXT(Data[[#This Row],[F. INICIO]],"mmmm")) -> JUNIO | K48: 15 | L48: EPS | M48: ENFERMENDAD GENERAL | N48: =_xlfn.XLOOKUP(D48,[1]!Data[CEDULA],[1]!Data[EPS/SURA],"No Existe",0,1) -> E.P.S SANITAS | O48: =YEAR(Data[[#This Row],[F. INICIO]]) -> 2024 | P48: 45444 | Q48: 45458 | R48: I219 | S48: =IF(Data[[#This Row],[TIPO DE INCAPACIDAD]]="LICENCIA DE PATERNIDAD","Licencia de paternidad",IF(Data[[#This Row],[TIPO DE INCAPACIDAD]]="LICENCIA DE LUTO","Licencia de Luto",_xlfn.IFNA(VLOOKUP(R48,'CIE-10 PARA RIPS'!$A$6:B13219,2,0),"No especificado"))) -> Infarto agudo del miocardio, sin otra especificacion | T48: =IF(P48<>"", IF(P48>0, IF(P48<=DATE(YEAR(P48),MONTH(P48),DAY(P48)), IF(P48>=DATE(YEAR(P48),MONTH(P48),1), IF(K48>10, C48, IF(SUMIFS($K:$K, $C:$C, C48, $P:$P, ">="&DATE(YEAR(P48),MONTH(P48),1), $P:$P, "<="&EOMONTH(P48,0))>10, C48, "")), ""))), "") -> JOSE LUIS MEZA FONSECA | U48: =IF(AND(P48<>"", P48>=DATE(YEAR(P48),MONTH(P48),1), SUMIFS($K:$K, $C:$C, C48, $P:$P, ">="&DATE(YEAR(P48),MONTH(P48),1), $P:$P, "<="&EOMONTH(P48,0))>10), K48, "") -> 15 | V48: =IF(AND(P48<>"", P48>=DATE(YEAR(P48),MONTH(P48),1), SUMIFS($K:$K, $C:$C, C48, $P:$P, ">="&DATE(YEAR(P48),MONTH(P48),1), $P:$P, "<="&EOMONTH(P48,0))>10), YEAR(P48), "") -> 2024 | W48: =IF(AND(P48<>"", P48>=DATE(YEAR(P48),MONTH(P48),1), SUMIFS($K:$K, $C:$C, C48, $P:$P, ">="&DATE(YEAR(P48),MONTH(P48),1), $P:$P, "<="&EOMONTH(P48,0))>10), TEXT(P48, "MMMM"), "") -> junio | X48: {=IF(AND(P48<>"", P48>=DATE(YEAR(P48),MONTH(P48),1), SUMIFS($K:$K, $C:$C, C48, $P:$P, ">="&DATE(YEAR(P48),MONTH(P48),1), $P:$P, "<="&EOMONTH(P48,0))>10), _xlfn.TEXTJOIN(", ", TRUE, _xlfn._xlws.FILTER($R:$R, ($C:$C=C48) * ($P:$P>=DATE(YEAR(P48),MONTH(P48),1)) * ($P:$P<=EOMONTH(P48,0)))), "")} -> I219 | Y48: {=IF(AND(P48<>"", P48>=DATE(YEAR(P48),MONTH(P48),1), SUMIFS($K:$K, $C:$C, C48, $P:$P, ">="&DATE(YEAR(P48),MONTH(P48),1), $P:$P, "<="&EOMONTH(P48,0))>10), _xlfn.TEXTJOIN(", ", TRUE, _xlfn._xlws.FILTER($S:$S, ($C:$C=C48) * ($P:$P>=DATE(YEAR(P48),MONTH(P48),1)) * ($P:$P<=EOMONTH(P48,0)))), "")} -> Infarto agudo del miocardio, sin otra especificacion
A49: 42 | B49: TEMPOACTIVA | C49: =_xlfn.XLOOKUP(D49,[1]!Data[CEDULA],[1]!Data[Nombre Completo],"No Existe",0,1) -> NESTOR OCHOA MANTILLA | D49: 1042357925 | E49: =IFERROR(_xlfn.NUMBERVALUE(Data[[#This Row],[CEDULA ]],",","."),_xlfn.NUMBERVALUE(Data[[#This Row],[CEDULA ]],".",",")) -> 1042357925 | F49: =_xlfn.XLOOKUP(E49,[1]!Data[CEDULA],[1]!Data[CARGO],"No Existe",0,1) -> STEWARD | G49: =_xlfn.XLOOKUP(E49,[1]!Data[CEDULA],[1]!Data[EMPRESA DONDE PRESTA SERVICIO],"No Existe",0,1) -> COMFAMILIAR ATLANTICO | H49: =_xlfn.XLOOKUP(E49,[1]!Data[CEDULA],[1]!Data[UBICACIÓN],"No Existe",0,1) -> SEDE NORTE MERCADEO | I49: HOMBRE | J49: =UPPER(TEXT(Data[[#This Row],[F. INICIO]],"mmmm")) -> JUNIO | K49: 2 | L49: EPS | M49: ENFERMENDAD GENERAL | N49: =_xlfn.XLOOKUP(D49,[1]!Data[CEDULA],[1]!Data[EPS/SURA],"No Existe",0,1) -> FAMISANAR | O49: =YEAR(Data[[#This Row],[F. INICIO]]) -> 2024 | P49: 45459 | Q49: 45460 | R49: j931 | S49: =IF(Data[[#This Row],[TIPO DE INCAPACIDAD]]="LICENCIA DE PATERNIDAD","Licencia de paternidad",IF(Data[[#This Row],[TIPO DE INCAPACIDAD]]="LICENCIA DE LUTO","Licencia de Luto",_xlfn.IFNA(VLOOKUP(R49,'CIE-10 PARA RIPS'!$A$6:B13220,2,0),"No especificado"))) -> Otros tipos de neumotorax espontaneo | T49: =IF(P49<>"", IF(P49>0, IF(P49<=DATE(YEAR(P49),MONTH(P49),DAY(P49)), IF(P49>=DATE(YEAR(P49),MONTH(P49),1), IF(K49>10, C49, IF(SUMIFS($K:$K, $C:$C, C49, $P:$P, ">="&DATE(YEAR(P49),MONTH(P49),1), $P:$P, "<="&EOMONTH(P49,0))>10, C49, "")), ""))), "") | U49: =IF(AND(P49<>"", P49>=DATE(YEAR(P49),MONTH(P49),1), SUMIFS($K:$K, $C:$C, C49, $P:$P, ">="&DATE(YEAR(P49),MONTH(P49),1), $P:$P, "<="&EOMONTH(P49,0))>10), K49, "") | V49: =IF(AND(P49<>"", P49>=DATE(YEAR(P49),MONTH(P49),1), SUMIFS($K:$K, $C:$C, C49, $P:$P, ">="&DATE(YEAR(P49),MONTH(P49),1), $P:$P, "<="&EOMONTH(P49,0))>10), YEAR(P49), "") | W49: =IF(AND(P49<>"", P49>=DATE(YEAR(P49),MONTH(P49),1), SUMIFS($K:$K, $C:$C, C49, $P:$P, ">="&DATE(YEAR(P49),MONTH(P49),1), $P:$P, "<="&EOMONTH(P49,0))>10), TEXT(P49, "MMMM"), "") | X49: {=IF(AND(P49<>"", P49>=DATE(YEAR(P49),MONTH(P49),1), SUMIFS($K:$K, $C:$C, C49, $P:$P, ">="&DATE(YEAR(P49),MONTH(P49),1), $P:$P, "<="&EOMONTH(P49,0))>10), _xlfn.TEXTJOIN(", ", TRUE, _xlfn._xlws.FILTER($R:$R, ($C:$C=C49) * ($P:$P>=DATE(YEAR(P49),MONTH(P49),1)) * ($P:$P<=EOMONTH(P49,0)))), "")} | Y49: {=IF(AND(P49<>"", P49>=DATE(YEAR(P49),MONTH(P49),1), SUMIFS($K:$K, $C:$C, C49, $P:$P, ">="&DATE(YEAR(P49),MONTH(P49),1), $P:$P, "<="&EOMONTH(P49,0))>10), _xlfn.TEXTJOIN(", ", TRUE, _xlfn._xlws.FILTER($S:$S, ($C:$C=C49) * ($P:$P>=DATE(YEAR(P49),MONTH(P49),1)) * ($P:$P<=EOMONTH(P49,0)))), "")}
A50: 43 | B50: TEMPOACTIVA | C50: =_xlfn.XLOOKUP(D50,[1]!Data[CEDULA],[1]!Data[Nombre Completo],"No Existe",0,1) -> CLARK WILLIAM POLO PALACIO | D50: 1143425851 | E50: =IFERROR(_xlfn.NUMBERVALUE(Data[[#This Row],[CEDULA ]],",","."),_xlfn.NUMBERVALUE(Data[[#This Row],[CEDULA ]],".",",")) -> 1143425851 | F50: =_xlfn.XLOOKUP(E50,[1]!Data[CEDULA],[1]!Data[CARGO],"No Existe",0,1) -> AUXILIAR DE BODEGA | G50: =_xlfn.XLOOKUP(E50,[1]!Data[CEDULA],[1]!Data[EMPRESA DONDE PRESTA SERVICIO],"No Existe",0,1) -> COMFAMILIAR ATLANTICO | H50: =_xlfn.XLOOKUP(E50,[1]!Data[CEDULA],[1]!Data[UBICACIÓN],"No Existe",0,1) -> CENTRO RECREACIONAL CLL 48 | I50: HOMBRE | J50: =UPPER(TEXT(Data[[#This Row],[F. INICIO]],"mmmm")) -> JUNIO | K50: 2 | L50: EPS | M50: ENFERMENDAD GENERAL | N50: =_xlfn.XLOOKUP(D50,[1]!Data[CEDULA],[1]!Data[EPS/SURA],"No Existe",0,1) -> SALUD TOTAL | O50: =YEAR(Data[[#This Row],[F. INICIO]]) -> 2024 | P50: 45460 | Q50: 45461 | R50: A083 | S50: =IF(Data[[#This Row],[TIPO DE INCAPACIDAD]]="LICENCIA DE PATERNIDAD","Licencia de paternidad",IF(Data[[#This Row],[TIPO DE INCAPACIDAD]]="LICENCIA DE LUTO","Licencia de Luto",_xlfn.IFNA(VLOOKUP(R50,'CIE-10 PARA RIPS'!$A$6:B13221,2,0),"No especificado"))) -> Otras enteritis virales | T50: =IF(P50<>"", IF(P50>0, IF(P50<=DATE(YEAR(P50),MONTH(P50),DAY(P50)), IF(P50>=DATE(YEAR(P50),MONTH(P50),1), IF(K50>10, C50, IF(SUMIFS($K:$K, $C:$C, C50, $P:$P, ">="&DATE(YEAR(P50),MONTH(P50),1), $P:$P, "<="&EOMONTH(P50,0))>10, C50, "")), ""))), "") | U50: =IF(AND(P50<>"", P50>=DATE(YEAR(P50),MONTH(P50),1), SUMIFS($K:$K, $C:$C, C50, $P:$P, ">="&DATE(YEAR(P50),MONTH(P50),1), $P:$P, "<="&EOMONTH(P50,0))>10), K50, "") | V50: =IF(AND(P50<>"", P50>=DATE(YEAR(P50),MONTH(P50),1), SUMIFS($K:$K, $C:$C, C50, $P:$P, ">="&DATE(YEAR(P50),MONTH(P50),1), $P:$P, "<="&EOMONTH(P50,0))>10), YEAR(P50), "") | W50: =IF(AND(P50<>"", P50>=DATE(YEAR(P50),MONTH(P50),1), SUMIFS($K:$K, $C:$C, C50, $P:$P, ">="&DATE(YEAR(P50),MONTH(P50),1), $P:$P, "<="&EOMONTH(P50,0))>10), TEXT(P50, "MMMM"), "") | X50: {=IF(AND(P50<>"", P50>=DATE(YEAR(P50),MONTH(P50),1), SUMIFS($K:$K, $C:$C, C50, $P:$P, ">="&DATE(YEAR(P50),MONTH(P50),1), $P:$P, "<="&EOMONTH(P50,0))>10), _xlfn.TEXTJOIN(", ", TRUE, _xlfn._xlws.FILTER($R:$R, ($C:$C=C50) * ($P:$P>=DATE(YEAR(P50),MONTH(P50),1)) * ($P:$P<=EOMONTH(P50,0)))), "")} | Y50: {=IF(AND(P50<>"", P50>=DATE(YEAR(P50),MONTH(P50),1), SUMIFS($K:$K, $C:$C, C50, $P:$P, ">="&DATE(YEAR(P50),MONTH(P50),1), $P:$P, "<="&EOMONTH(P50,0))>10), _xlfn.TEXTJOIN(", ", TRUE, _xlfn._xlws.FILTER($S:$S, ($C:$C=C50) * ($P:$P>=DATE(YEAR(P50),MONTH(P50),1)) * ($P:$P<=EOMONTH(P50,0)))), "")}
A51: 44 | B51: TEMPOACTIVA | C51: =_xlfn.XLOOKUP(D51,[1]!Data[CEDULA],[1]!Data[Nombre Completo],"No Existe",0,1) -> JORGE CABARIQUE MANRIQUE | D51: 91242205 | E51: =IFERROR(_xlfn.NUMBERVALUE(Data[[#This Row],[CEDULA ]],",","."),_xlfn.NUMBERVALUE(Data[[#This Row],[CEDULA ]],".",",")) -> 91242205 | F51: =_xlfn.XLOOKUP(E51,[1]!Data[CEDULA],[1]!Data[CARGO],"No Existe",0,1) -> CHEF | G51: =_xlfn.XLOOKUP(E51,[1]!Data[CEDULA],[1]!Data[EMPRESA DONDE PRESTA SERVICIO],"No Existe",0,1) -> COMFAMILIAR ATLANTICO | H51: =_xlfn.XLOOKUP(E51,[1]!Data[CEDULA],[1]!Data[UBICACIÓN],"No Existe",0,1) -> SEDE CARIBE MERCADEO | I51: HOMBRE | J51: =UPPER(TEXT(Data[[#This Row],[F. INICIO]],"mmmm")) -> JUNIO | K51: 2 | L51: EPS | M51: ENFERMENDAD GENERAL | N51: =_xlfn.XLOOKUP(D51,[1]!Data[CEDULA],[1]!Data[EPS/SURA],"No Existe",0,1) -> E.P.S SANITAS | O51: =YEAR(Data[[#This Row],[F. INICIO]]) -> 2024 | P51: 45466 | Q51: 45467 | R51: A09X | S51: =IF(Data[[#This Row],[TIPO DE INCAPACIDAD]]="LICENCIA DE PATERNIDAD","Licencia de paternidad",IF(Data[[#This Row],[TIPO DE INCAPACIDAD]]="LICENCIA DE LUTO","Licencia de Luto",_xlfn.IFNA(VLOOKUP(R51,'CIE-10 PARA RIPS'!$A$6:B13222,2,0),"No especificado"))) -> Diarrea y gastroenteritis de presunto origen infeccioso | T51: =IF(P51<>"", IF(P51>0, IF(P51<=DATE(YEAR(P51),MONTH(P51),DAY(P51)), IF(P51>=DATE(YEAR(P51),MONTH(P51),1), IF(K51>10, C51, IF(SUMIFS($K:$K, $C:$C, C51, $P:$P, ">="&DATE(YEAR(P51),MONTH(P51),1), $P:$P, "<="&EOMONTH(P51,0))>10, C51, "")), ""))), "") | U51: =IF(AND(P51<>"", P51>=DATE(YEAR(P51),MONTH(P51),1), SUMIFS($K:$K, $C:$C, C51, $P:$P, ">="&DATE(YEAR(P51),MONTH(P51),1), $P:$P, "<="&EOMONTH(P51,0))>10), K51, "") | V51: =IF(AND(P51<>"", P51>=DATE(YEAR(P51),MONTH(P51),1), SUMIFS($K:$K, $C:$C, C51, $P:$P, ">="&DATE(YEAR(P51),MONTH(P51),1), $P:$P, "<="&EOMONTH(P51,0))>10), YEAR(P51), "") | W51: =IF(AND(P51<>"", P51>=DATE(YEAR(P51),MONTH(P51),1), SUMIFS($K:$K, $C:$C, C51, $P:$P, ">="&DATE(YEAR(P51),MONTH(P51),1), $P:$P, "<="&EOMONTH(P51,0))>10), TEXT(P51, "MMMM"), "") | X51: {=IF(AND(P51<>"", P51>=DATE(YEAR(P51),MONTH(P51),1), SUMIFS($K:$K, $C:$C, C51, $P:$P, ">="&DATE(YEAR(P51),MONTH(P51),1), $P:$P, "<="&EOMONTH(P51,0))>10), _xlfn.TEXTJOIN(", ", TRUE, _xlfn._xlws.FILTER($R:$R, ($C:$C=C51) * ($P:$P>=DATE(YEAR(P51),MONTH(P51),1)) * ($P:$P<=EOMONTH(P51,0)))), "")} | Y51: {=IF(AND(P51<>"", P51>=DATE(YEAR(P51),MONTH(P51),1), SUMIFS($K:$K, $C:$C, C51, $P:$P, ">="&DATE(YEAR(P51),MONTH(P51),1), $P:$P, "<="&EOMONTH(P51,0))>10), _xlfn.TEXTJOIN(", ", TRUE, _xlfn._xlws.FILTER($S:$S, ($C:$C=C51) * ($P:$P>=DATE(YEAR(P51),MONTH(P51),1)) * ($P:$P<=EOMONTH(P51,0)))), "")}
A52: 45 | B52: TEMPOACTIVA | C52: =_xlfn.XLOOKUP(D52,[1]!Data[CEDULA],[1]!Data[Nombre Completo],"No Existe",0,1) -> MAVERYCK ANDRES GUTIERREZ DE LA HOZ | D52: 1143267771 | E52: =IFERROR(_xlfn.NUMBERVALUE(Data[[#This Row],[CEDULA ]],",","."),_xlfn.NUMBERVALUE(Data[[#This Row],[CEDULA ]],".",",")) -> 1143267771 | F52: =_xlfn.XLOOKUP(E52,[1]!Data[CEDULA],[1]!Data[CARGO],"No Existe",0,1) -> MESERO | G52: =_xlfn.XLOOKUP(E52,[1]!Data[CEDULA],[1]!Data[EMPRESA DONDE PRESTA SERVICIO],"No Existe",0,1) -> COMFAMILIAR ATLANTICO | H52: =_xlfn.XLOOKUP(E52,[1]!Data[CEDULA],[1]!Data[UBICACIÓN],"No Existe",0,1) -> SEDE CARIBE | I52: HOMBRE | J52: =UPPER(TEXT(Data[[#This Row],[F. INICIO]],"mmmm")) -> JUNIO | K52: 1 | L52: EPS | M52: ENFERMENDAD GENERAL | N52: =_xlfn.XLOOKUP(D52,[1]!Data[CEDULA],[1]!Data[EPS/SURA],"No Existe",0,1) -> EPS/SURA | O52: =YEAR(Data[[#This Row],[F. INICIO]]) -> 2024 | P52: 45464 | Q52: 45464 | R52: J00X | S52: =IF(Data[[#This Row],[TIPO DE INCAPACIDAD]]="LICENCIA DE PATERNIDAD","Licencia de paternidad",IF(Data[[#This Row],[TIPO DE INCAPACIDAD]]="LICENCIA DE LUTO","Licencia de Luto",_xlfn.IFNA(VLOOKUP(R52,'CIE-10 PARA RIPS'!$A$6:B13223,2,0),"No especificado"))) -> Rinofaringitis aguda [resfriado comun] | T52: =IF(P52<>"", IF(P52>0, IF(P52<=DATE(YEAR(P52),MONTH(P52),DAY(P52)), IF(P52>=DATE(YEAR(P52),MONTH(P52),1), IF(K52>10, C52, IF(SUMIFS($K:$K, $C:$C, C52, $P:$P, ">="&DATE(YEAR(P52),MONTH(P52),1), $P:$P, "<="&EOMONTH(P52,0))>10, C52, "")), ""))), "") | U52: =IF(AND(P52<>"", P52>=DATE(YEAR(P52),MONTH(P52),1), SUMIFS($K:$K, $C:$C, C52, $P:$P, ">="&DATE(YEAR(P52),MONTH(P52),1), $P:$P, "<="&EOMONTH(P52,0))>10), K52, "") | V52: =IF(AND(P52<>"", P52>=DATE(YEAR(P52),MONTH(P52),1), SUMIFS($K:$K, $C:$C, C52, $P:$P, ">="&DATE(YEAR(P52),MONTH(P52),1), $P:$P, "<="&EOMONTH(P52,0))>10), YEAR(P52), "") | W52: =IF(AND(P52<>"", P52>=DATE(YEAR(P52),MONTH(P52),1), SUMIFS($K:$K, $C:$C, C52, $P:$P, ">="&DATE(YEAR(P52),MONTH(P52),1), $P:$P, "<="&EOMONTH(P52,0))>10), TEXT(P52, "MMMM"), "") | X52: {=IF(AND(P52<>"", P52>=DATE(YEAR(P52),MONTH(P52),1), SUMIFS($K:$K, $C:$C, C52, $P:$P, ">="&DATE(YEAR(P52),MONTH(P52),1), $P:$P, "<="&EOMONTH(P52,0))>10), _xlfn.TEXTJOIN(", ", TRUE, _xlfn._xlws.FILTER($R:$R, ($C:$C=C52) * ($P:$P>=DATE(YEAR(P52),MONTH(P52),1)) * ($P:$P<=EOMONTH(P52,0)))), "")} | Y52: {=IF(AND(P52<>"", P52>=DATE(YEAR(P52),MONTH(P52),1), SUMIFS($K:$K, $C:$C, C52, $P:$P, ">="&DATE(YEAR(P52),MONTH(P52),1), $P:$P, "<="&EOMONTH(P52,0))>10), _xlfn.TEXTJOIN(", ", TRUE, _xlfn._xlws.FILTER($S:$S, ($C:$C=C52) * ($P:$P>=DATE(YEAR(P52),MONTH(P52),1)) * ($P:$P<=EOMONTH(P52,0)))), "")}
A53: 46 | B53: TEMPOACTIVA | C53: =_xlfn.XLOOKUP(D53,[1]!Data[CEDULA],[1]!Data[Nombre Completo],"No Existe",0,1) -> CELIA MARIA MOLINA CORONELL | D53: 1044392321 | E53: =IFERROR(_xlfn.NUMBERVALUE(Data[[#This Row],[CEDULA ]],",","."),_xlfn.NUMBERVALUE(Data[[#This Row],[CEDULA ]],".",",")) -> 1044392321 | F53: =_xlfn.XLOOKUP(E53,[1]!Data[CEDULA],[1]!Data[CARGO],"No Existe",0,1) -> RECEPCIONISTA | G53: =_xlfn.XLOOKUP(E53,[1]!Data[CEDULA],[1]!Data[EMPRESA DONDE PRESTA SERVICIO],"No Existe",0,1) -> COMFAMILIAR ATLANTICO | H53: =_xlfn.XLOOKUP(E53,[1]!Data[CEDULA],[1]!Data[UBICACIÓN],"No Existe",0,1) -> CENTRO RECREACIONAL TURIPANA | I53: MUJER | J53: =UPPER(TEXT(Data[[#This Row],[F. INICIO]],"mmmm")) -> JUNIO | K53: 2 | L53: EPS | M53: ENFERMENDAD GENERAL | N53: =_xlfn.XLOOKUP(D53,[1]!Data[CEDULA],[1]!Data[EPS/SURA],"No Existe",0,1) -> E.P.S SANITAS | O53: =YEAR(Data[[#This Row],[F. INICIO]]) -> 2024 | P53: 45462 | Q53: 45463 | R53: J22X | S53: =IF(Data[[#This Row],[TIPO DE INCAPACIDAD]]="LICENCIA DE PATERNIDAD","Licencia de paternidad",IF(Data[[#This Row],[TIPO DE INCAPACIDAD]]="LICENCIA DE LUTO","Licencia de Luto",_xlfn.IFNA(VLOOKUP(R53,'CIE-10 PARA RIPS'!$A$6:B13224,2,0),"No especificado"))) -> Infeccion aguda no especificada de las vias respiratorias inferiores | T53: =IF(P53<>"", IF(P53>0, IF(P53<=DATE(YEAR(P53),MONTH(P53),DAY(P53)), IF(P53>=DATE(YEAR(P53),MONTH(P53),1), IF(K53>10, C53, IF(SUMIFS($K:$K, $C:$C, C53, $P:$P, ">="&DATE(YEAR(P53),MONTH(P53),1), $P:$P, "<="&EOMONTH(P53,0))>10, C53, "")), ""))), "") | U53: =IF(AND(P53<>"", P53>=DATE(YEAR(P53),MONTH(P53),1), SUMIFS($K:$K, $C:$C, C53, $P:$P, ">="&DATE(YEAR(P53),MONTH(P53),1), $P:$P, "<="&EOMONTH(P53,0))>10), K53, "") | V53: =IF(AND(P53<>"", P53>=DATE(YEAR(P53),MONTH(P53),1), SUMIFS($K:$K, $C:$C, C53, $P:$P, ">="&DATE(YEAR(P53),MONTH(P53),1), $P:$P, "<="&EOMONTH(P53,0))>10), YEAR(P53), "") | W53: =IF(AND(P53<>"", P53>=DATE(YEAR(P53),MONTH(P53),1), SUMIFS($K:$K, $C:$C, C53, $P:$P, ">="&DATE(YEAR(P53),MONTH(P53),1), $P:$P, "<="&EOMONTH(P53,0))>10), TEXT(P53, "MMMM"), "") | X53: {=IF(AND(P53<>"", P53>=DATE(YEAR(P53),MONTH(P53),1), SUMIFS($K:$K, $C:$C, C53, $P:$P, ">="&DATE(YEAR(P53),MONTH(P53),1), $P:$P, "<="&EOMONTH(P53,0))>10), _xlfn.TEXTJOIN(", ", TRUE, _xlfn._xlws.FILTER($R:$R, ($C:$C=C53) * ($P:$P>=DATE(YEAR(P53),MONTH(P53),1)) * ($P:$P<=EOMONTH(P53,0)))), "")} | Y53: {=IF(AND(P53<>"", P53>=DATE(YEAR(P53),MONTH(P53),1), SUMIFS($K:$K, $C:$C, C53, $P:$P, ">="&DATE(YEAR(P53),MONTH(P53),1), $P:$P, "<="&EOMONTH(P53,0))>10), _xlfn.TEXTJOIN(", ", TRUE, _xlfn._xlws.FILTER($S:$S, ($C:$C=C53) * ($P:$P>=DATE(YEAR(P53),MONTH(P53),1)) * ($P:$P<=EOMONTH(P53,0)))), "")}
A54: 47 | B54: TEMPOACTIVA | C54: =_xlfn.XLOOKUP(D54,[1]!Data[CEDULA],[1]!Data[Nombre Completo],"No Existe",0,1) -> KAREN MARGARITA COLPAS ALVAREZ | D54: 1043870216 | E54: =IFERROR(_xlfn.NUMBERVALUE(Data[[#This Row],[CEDULA ]],",","."),_xlfn.NUMBERVALUE(Data[[#This Row],[CEDULA ]],".",",")) -> 1043870216 | F54: =_xlfn.XLOOKUP(E54,[1]!Data[CEDULA],[1]!Data[CARGO],"No Existe",0,1) -> SUPERNUMERARIO(A) | G54: =_xlfn.XLOOKUP(E54,[1]!Data[CEDULA],[1]!Data[EMPRESA DONDE PRESTA SERVICIO],"No Existe",0,1) -> COMFAMILIAR ATLANTICO | H54: =_xlfn.XLOOKUP(E54,[1]!Data[CEDULA],[1]!Data[UBICACIÓN],"No Existe",0,1) -> SALGARITO | I54: MUJER | J54: =UPPER(TEXT(Data[[#This Row],[F. INICIO]],"mmmm")) -> JUNIO | K54: 2 | L54: EPS | M54: ENFERMENDAD GENERAL | N54: =_xlfn.XLOOKUP(D54,[1]!Data[CEDULA],[1]!Data[EPS/SURA],"No Existe",0,1) -> SALUD TOTAL | O54: =YEAR(Data[[#This Row],[F. INICIO]]) -> 2024 | P54: 45454 | Q54: 45455 | R54: j069 | S54: =IF(Data[[#This Row],[TIPO DE INCAPACIDAD]]="LICENCIA DE PATERNIDAD","Licencia de paternidad",IF(Data[[#This Row],[TIPO DE INCAPACIDAD]]="LICENCIA DE LUTO","Licencia de Luto",_xlfn.IFNA(VLOOKUP(R54,'CIE-10 PARA RIPS'!$A$6:B13225,2,0),"No especificado"))) -> Infeccion aguda de las vias respiratorias superiores, no especificada | T54: =IF(P54<>"", IF(P54>0, IF(P54<=DATE(YEAR(P54),MONTH(P54),DAY(P54)), IF(P54>=DATE(YEAR(P54),MONTH(P54),1), IF(K54>10, C54, IF(SUMIFS($K:$K, $C:$C, C54, $P:$P, ">="&DATE(YEAR(P54),MONTH(P54),1), $P:$P, "<="&EOMONTH(P54,0))>10, C54, "")), ""))), "") | U54: =IF(AND(P54<>"", P54>=DATE(YEAR(P54),MONTH(P54),1), SUMIFS($K:$K, $C:$C, C54, $P:$P, ">="&DATE(YEAR(P54),MONTH(P54),1), $P:$P, "<="&EOMONTH(P54,0))>10), K54, "") | V54: =IF(AND(P54<>"", P54>=DATE(YEAR(P54),MONTH(P54),1), SUMIFS($K:$K, $C:$C, C54, $P:$P, ">="&DATE(YEAR(P54),MONTH(P54),1), $P:$P, "<="&EOMONTH(P54,0))>10), YEAR(P54), "") | W54: =IF(AND(P54<>"", P54>=DATE(YEAR(P54),MONTH(P54),1), SUMIFS($K:$K, $C:$C, C54, $P:$P, ">="&DATE(YEAR(P54),MONTH(P54),1), $P:$P, "<="&EOMONTH(P54,0))>10), TEXT(P54, "MMMM"), "") | X54: {=IF(AND(P54<>"", P54>=DATE(YEAR(P54),MONTH(P54),1), SUMIFS($K:$K, $C:$C, C54, $P:$P, ">="&DATE(YEAR(P54),MONTH(P54),1), $P:$P, "<="&EOMONTH(P54,0))>10), _xlfn.TEXTJOIN(", ", TRUE, _xlfn._xlws.FILTER($R:$R, ($C:$C=C54) * ($P:$P>=DATE(YEAR(P54),MONTH(P54),1)) * ($P:$P<=EOMONTH(P54,0)))), "")} | Y54: {=IF(AND(P54<>"", P54>=DATE(YEAR(P54),MONTH(P54),1), SUMIFS($K:$K, $C:$C, C54, $P:$P, ">="&DATE(YEAR(P54),MONTH(P54),1), $P:$P, "<="&EOMONTH(P54,0))>10), _xlfn.TEXTJOIN(", ", TRUE, _xlfn._xlws.FILTER($S:$S, ($C:$C=C54) * ($P:$P>=DATE(YEAR(P54),MONTH(P54),1)) * ($P:$P<=EOMONTH(P54,0)))), "")}
A55: 48 | B55: TEMPOACTIVA | C55: =_xlfn.XLOOKUP(D55,[1]!Data[CEDULA],[1]!Data[Nombre Completo],"No Existe",0,1) -> MIGUEL DE JESUS RAMOS ARTETA | D55: 1044394141 | E55: =IFERROR(_xlfn.NUMBERVALUE(Data[[#This Row],[CEDULA ]],",","."),_xlfn.NUMBERVALUE(Data[[#This Row],[CEDULA ]],".",",")) -> 1044394141 | F55: =_xlfn.XLOOKUP(E55,[1]!Data[CEDULA],[1]!Data[CARGO],"No Existe",0,1) -> SUPERNUMERARIO(A) | G55: =_xlfn.XLOOKUP(E55,[1]!Data[CEDULA],[1]!Data[EMPRESA DONDE PRESTA SERVICIO],"No Existe",0,1) -> COMFAMILIAR ATLANTICO | H55: =_xlfn.XLOOKUP(E55,[1]!Data[CEDULA],[1]!Data[UBICACIÓN],"No Existe",0,1) -> CENTRO RECREACIONAL TURIPANA | I55: HOMBRE | J55: =UPPER(TEXT(Data[[#This Row],[F. INICIO]],"mmmm")) -> JUNIO | K55: 2 | L55: EPS | M55: ENFERMENDAD GENERAL | N55: =_xlfn.XLOOKUP(D55,[1]!Data[CEDULA],[1]!Data[EPS/SURA],"No Existe",0,1) -> NUEVA E.P.S. | O55: =YEAR(Data[[#This Row],[F. INICIO]]) -> 2024 | P55: 45472 | Q55: 45473 | R55: J039 | S55: =IF(Data[[#This Row],[TIPO DE INCAPACIDAD]]="LICENCIA DE PATERNIDAD","Licencia de paternidad",IF(Data[[#This Row],[TIPO DE INCAPACIDAD]]="LICENCIA DE LUTO","Licencia de Luto",_xlfn.IFNA(VLOOKUP(R55,'CIE-10 PARA RIPS'!$A$6:B13227,2,0),"No especificado"))) -> Amigdalitis aguda, no especificada | T55: =IF(P55<>"", IF(P55>0, IF(P55<=DATE(YEAR(P55),MONTH(P55),DAY(P55)), IF(P55>=DATE(YEAR(P55),MONTH(P55),1), IF(K55>10, C55, IF(SUMIFS($K:$K, $C:$C, C55, $P:$P, ">="&DATE(YEAR(P55),MONTH(P55),1), $P:$P, "<="&EOMONTH(P55,0))>10, C55, "")), ""))), "") | U55: =IF(AND(P55<>"", P55>=DATE(YEAR(P55),MONTH(P55),1), SUMIFS($K:$K, $C:$C, C55, $P:$P, ">="&DATE(YEAR(P55),MONTH(P55),1), $P:$P, "<="&EOMONTH(P55,0))>10), K55, "") | V55: =IF(AND(P55<>"", P55>=DATE(YEAR(P55),MONTH(P55),1), SUMIFS($K:$K, $C:$C, C55, $P:$P, ">="&DATE(YEAR(P55),MONTH(P55),1), $P:$P, "<="&EOMONTH(P55,0))>10), YEAR(P55), "") | W55: =IF(AND(P55<>"", P55>=DATE(YEAR(P55),MONTH(P55),1), SUMIFS($K:$K, $C:$C, C55, $P:$P, ">="&DATE(YEAR(P55),MONTH(P55),1), $P:$P, "<="&EOMONTH(P55,0))>10), TEXT(P55, "MMMM"), "") | X55: {=IF(AND(P55<>"", P55>=DATE(YEAR(P55),MONTH(P55),1), SUMIFS($K:$K, $C:$C, C55, $P:$P, ">="&DATE(YEAR(P55),MONTH(P55),1), $P:$P, "<="&EOMONTH(P55,0))>10), _xlfn.TEXTJOIN(", ", TRUE, _xlfn._xlws.FILTER($R:$R, ($C:$C=C55) * ($P:$P>=DATE(YEAR(P55),MONTH(P55),1)) * ($P:$P<=EOMONTH(P55,0)))), "")} | Y55: {=IF(AND(P55<>"", P55>=DATE(YEAR(P55),MONTH(P55),1), SUMIFS($K:$K, $C:$C, C55, $P:$P, ">="&DATE(YEAR(P55),MONTH(P55),1), $P:$P, "<="&EOMONTH(P55,0))>10), _xlfn.TEXTJOIN(", ", TRUE, _xlfn._xlws.FILTER($S:$S, ($C:$C=C55) * ($P:$P>=DATE(YEAR(P55),MONTH(P55),1)) * ($P:$P<=EOMONTH(P55,0)))), "")}
A56: 49 | B56: TEMPOACTIVA | C56: =_xlfn.XLOOKUP(D56,[1]!Data[CEDULA],[1]!Data[Nombre Completo],"No Existe",0,1) -> JOSE GREGORIO MARTINEZ MEJIA | D56: 72236916 | E56: =IFERROR(_xlfn.NUMBERVALUE(Data[[#This Row],[CEDULA ]],",","."),_xlfn.NUMBERVALUE(Data[[#This Row],[CEDULA ]],".",",")) -> 72236916 | F56: =_xlfn.XLOOKUP(E56,[1]!Data[CEDULA],[1]!Data[CARGO],"No Existe",0,1) -> CHEF | G56: =_xlfn.XLOOKUP(E56,[1]!Data[CEDULA],[1]!Data[EMPRESA DONDE PRESTA SERVICIO],"No Existe",0,1) -> COMFAMILIAR ATLANTICO | H56: =_xlfn.XLOOKUP(E56,[1]!Data[CEDULA],[1]!Data[UBICACIÓN],"No Existe",0,1) -> SEDE CARIBE MERCADEO | I56: HOMBRE | J56: =UPPER(TEXT(Data[[#This Row],[F. INICIO]],"mmmm")) -> JUNIO | K56: 1 | L56: ARL | M56: ACCIDENTE LABORAL | N56: =_xlfn.XLOOKUP(D56,[1]!Data[CEDULA],[1]!Data[EPS/SURA],"No Existe",0,1) -> EPS/SURA | O56: =YEAR(Data[[#This Row],[F. INICIO]]) -> 2024 | P56: 45456 | Q56: 45456 | R56: S018 | S56: =IF(Data[[#This Row],[TIPO DE INCAPACIDAD]]="LICENCIA DE PATERNIDAD","Licencia de paternidad",IF(Data[[#This Row],[TIPO DE INCAPACIDAD]]="LICENCIA DE LUTO","Licencia de Luto",_xlfn.IFNA(VLOOKUP(R56,'CIE-10 PARA RIPS'!$A$6:B13229,2,0),"No especificado"))) -> Herida de otras partes de la cabeza | T56: =IF(P56<>"", IF(P56>0, IF(P56<=DATE(YEAR(P56),MONTH(P56),DAY(P56)), IF(P56>=DATE(YEAR(P56),MONTH(P56),1), IF(K56>10, C56, IF(SUMIFS($K:$K, $C:$C, C56, $P:$P, ">="&DATE(YEAR(P56),MONTH(P56),1), $P:$P, "<="&EOMONTH(P56,0))>10, C56, "")), ""))), "") | U56: =IF(AND(P56<>"", P56>=DATE(YEAR(P56),MONTH(P56),1), SUMIFS($K:$K, $C:$C, C56, $P:$P, ">="&DATE(YEAR(P56),MONTH(P56),1), $P:$P, "<="&EOMONTH(P56,0))>10), K56, "") | V56: =IF(AND(P56<>"", P56>=DATE(YEAR(P56),MONTH(P56),1), SUMIFS($K:$K, $C:$C, C56, $P:$P, ">="&DATE(YEAR(P56),MONTH(P56),1), $P:$P, "<="&EOMONTH(P56,0))>10), YEAR(P56), "") | W56: =IF(AND(P56<>"", P56>=DATE(YEAR(P56),MONTH(P56),1), SUMIFS($K:$K, $C:$C, C56, $P:$P, ">="&DATE(YEAR(P56),MONTH(P56),1), $P:$P, "<="&EOMONTH(P56,0))>10), TEXT(P56, "MMMM"), "") | X56: {=IF(AND(P56<>"", P56>=DATE(YEAR(P56),MONTH(P56),1), SUMIFS($K:$K, $C:$C, C56, $P:$P, ">="&DATE(YEAR(P56),MONTH(P56),1), $P:$P, "<="&EOMONTH(P56,0))>10), _xlfn.TEXTJOIN(", ", TRUE, _xlfn._xlws.FILTER($R:$R, ($C:$C=C56) * ($P:$P>=DATE(YEAR(P56),MONTH(P56),1)) * ($P:$P<=EOMONTH(P56,0)))), "")} | Y56: {=IF(AND(P56<>"", P56>=DATE(YEAR(P56),MONTH(P56),1), SUMIFS($K:$K, $C:$C, C56, $P:$P, ">="&DATE(YEAR(P56),MONTH(P56),1), $P:$P, "<="&EOMONTH(P56,0))>10), _xlfn.TEXTJOIN(", ", TRUE, _xlfn._xlws.FILTER($S:$S, ($C:$C=C56) * ($P:$P>=DATE(YEAR(P56),MONTH(P56),1)) * ($P:$P<=EOMONTH(P56,0)))), "")}
A57: 50 | B57: TEMPOACTIVA | C57: =_xlfn.XLOOKUP(D57,[1]!Data[CEDULA],[1]!Data[Nombre Completo],"No Existe",0,1) -> HELIS MARI RAMIREZ PATIÑO | D57: 1140868628 | E57: =IFERROR(_xlfn.NUMBERVALUE(Data[[#This Row],[CEDULA ]],",","."),_xlfn.NUMBERVALUE(Data[[#This Row],[CEDULA ]],".",",")) -> 1140868628 | F57: =_xlfn.XLOOKUP(E57,[1]!Data[CEDULA],[1]!Data[CARGO],"No Existe",0,1) -> SUPERNUMERARIO(A) | G57: =_xlfn.XLOOKUP(E57,[1]!Data[CEDULA],[1]!Data[EMPRESA DONDE PRESTA SERVICIO],"No Existe",0,1) -> COMFAMILIAR ATLANTICO | H57: =_xlfn.XLOOKUP(E57,[1]!Data[CEDULA],[1]!Data[UBICACIÓN],"No Existe",0,1) -> SEDE NORTE | I57: MUJER | J57: =UPPER(TEXT(Data[[#This Row],[F. INICIO]],"mmmm")) -> JUNIO | K57: 30 | L57: EPS | M57: LICENCIA DE MATERNIDAD | N57: =_xlfn.XLOOKUP(D57,[1]!Data[CEDULA],[1]!Data[EPS/SURA],"No Existe",0,1) -> MUTUALSER | O57: =YEAR(Data[[#This Row],[F. INICIO]]) -> 2024 | P57: 45444 | Q57: 45473 | R57: O821 | S57: =IF(Data[[#This Row],[TIPO DE INCAPACIDAD]]="LICENCIA DE PATERNIDAD","Licencia de paternidad",IF(Data[[#This Row],[TIPO DE INCAPACIDAD]]="LICENCIA DE LUTO","Licencia de Luto",_xlfn.IFNA(VLOOKUP(R57,'CIE-10 PARA RIPS'!$A$6:B13234,2,0),"No especificado"))) -> Parto por cesarea de emergencia | T57: =IF(P57<>"", IF(P57>0, IF(P57<=DATE(YEAR(P57),MONTH(P57),DAY(P57)), IF(P57>=DATE(YEAR(P57),MONTH(P57),1), IF(K57>10, C57, IF(SUMIFS($K:$K, $C:$C, C57, $P:$P, ">="&DATE(YEAR(P57),MONTH(P57),1), $P:$P, "<="&EOMONTH(P57,0))>10, C57, "")), ""))), "") -> HELIS MARI RAMIREZ PATIÑO | U57: =IF(AND(P57<>"", P57>=DATE(YEAR(P57),MONTH(P57),1), SUMIFS($K:$K, $C:$C, C57, $P:$P, ">="&DATE(YEAR(P57),MONTH(P57),1), $P:$P, "<="&EOMONTH(P57,0))>10), K57, "") -> 30 | V57: =IF(AND(P57<>"", P57>=DATE(YEAR(P57),MONTH(P57),1), SUMIFS($K:$K, $C:$C, C57, $P:$P, ">="&DATE(YEAR(P57),MONTH(P57),1), $P:$P, "<="&EOMONTH(P57,0))>10), YEAR(P57), "") -> 2024 | W57: =IF(AND(P57<>"", P57>=DATE(YEAR(P57),MONTH(P57),1), SUMIFS($K:$K, $C:$C, C57, $P:$P, ">="&DATE(YEAR(P57),MONTH(P57),1), $P:$P, "<="&EOMONTH(P57,0))>10), TEXT(P57, "MMMM"), "") -> junio | X57: {=IF(AND(P57<>"", P57>=DATE(YEAR(P57),MONTH(P57),1), SUMIFS($K:$K, $C:$C, C57, $P:$P, ">="&DATE(YEAR(P57),MONTH(P57),1), $P:$P, "<="&EOMONTH(P57,0))>10), _xlfn.TEXTJOIN(", ", TRUE, _xlfn._xlws.FILTER($R:$R, ($C:$C=C57) * ($P:$P>=DATE(YEAR(P57),MONTH(P57),1)) * ($P:$P<=EOMONTH(P57,0)))), "")} -> O821 | Y57: {=IF(AND(P57<>"", P57>=DATE(YEAR(P57),MONTH(P57),1), SUMIFS($K:$K, $C:$C, C57, $P:$P, ">="&DATE(YEAR(P57),MONTH(P57),1), $P:$P, "<="&EOMONTH(P57,0))>10), _xlfn.TEXTJOIN(", ", TRUE, _xlfn._xlws.FILTER($S:$S, ($C:$C=C57) * ($P:$P>=DATE(YEAR(P57),MONTH(P57),1)) * ($P:$P<=EOMONTH(P57,0)))), "")} -> Parto por cesarea de emergencia
A58: 51 | B58: TEMPOACTIVA | C58: =_xlfn.XLOOKUP(D58,[1]!Data[CEDULA],[1]!Data[Nombre Completo],"No Existe",0,1) -> KARINA GREGORIA SALAS BROCHERO | D58: 1007096798 | E58: =IFERROR(_xlfn.NUMBERVALUE(Data[[#This Row],[CEDULA ]],",","."),_xlfn.NUMBERVALUE(Data[[#This Row],[CEDULA ]],".",",")) -> 1007096798 | F58: =_xlfn.XLOOKUP(E58,[1]!Data[CEDULA],[1]!Data[CARGO],"No Existe",0,1) -> SUPERNUMERARIO(A) | G58: =_xlfn.XLOOKUP(E58,[1]!Data[CEDULA],[1]!Data[EMPRESA DONDE PRESTA SERVICIO],"No Existe",0,1) -> COMFAMILIAR ATLANTICO | H58: =_xlfn.XLOOKUP(E58,[1]!Data[CEDULA],[1]!Data[UBICACIÓN],"No Existe",0,1) -> SEDE NORTE | I58: MUJER | J58: =UPPER(TEXT(Data[[#This Row],[F. INICIO]],"mmmm")) -> MARZO | K58: 31 | L58: EPS | M58: LICENCIA DE MATERNIDAD | N58: =_xlfn.XLOOKUP(D58,[1]!Data[CEDULA],[1]!Data[EPS/SURA],"No Existe",0,1) -> E.P.S SANITAS | O58: =YEAR(Data[[#This Row],[F. INICIO]]) -> 2024 | P58: 45352 | Q58: 45382 | R58: O829 | S58: =IF(Data[[#This Row],[TIPO DE INCAPACIDAD]]="LICENCIA DE PATERNIDAD","Licencia de paternidad",IF(Data[[#This Row],[TIPO DE INCAPACIDAD]]="LICENCIA DE LUTO","Licencia de Luto",_xlfn.IFNA(VLOOKUP(R58,'CIE-10 PARA RIPS'!$A$6:B13175,2,0),"No especificado"))) -> Parto por cesarea, sin otra especificacion | T58: =IF(P58<>"", IF(P58>0, IF(P58<=DATE(YEAR(P58),MONTH(P58),DAY(P58)), IF(P58>=DATE(YEAR(P58),MONTH(P58),1), IF(K58>10, C58, IF(SUMIFS($K:$K, $C:$C, C58, $P:$P, ">="&DATE(YEAR(P58),MONTH(P58),1), $P:$P, "<="&EOMONTH(P58,0))>10, C58, "")), ""))), "") -> KARINA GREGORIA SALAS BROCHERO | U58: =IF(AND(P58<>"", P58>=DATE(YEAR(P58),MONTH(P58),1), SUMIFS($K:$K, $C:$C, C58, $P:$P, ">="&DATE(YEAR(P58),MONTH(P58),1), $P:$P, "<="&EOMONTH(P58,0))>10), K58, "") -> 31 | V58: =IF(AND(P58<>"", P58>=DATE(YEAR(P58),MONTH(P58),1), SUMIFS($K:$K, $C:$C, C58, $P:$P, ">="&DATE(YEAR(P58),MONTH(P58),1), $P:$P, "<="&EOMONTH(P58,0))>10), YEAR(P58), "") -> 2024 | W58: =IF(AND(P58<>"", P58>=DATE(YEAR(P58),MONTH(P58),1), SUMIFS($K:$K, $C:$C, C58, $P:$P, ">="&DATE(YEAR(P58),MONTH(P58),1), $P:$P, "<="&EOMONTH(P58,0))>10), TEXT(P58, "MMMM"), "") -> marzo | X58: {=IF(AND(P58<>"", P58>=DATE(YEAR(P58),MONTH(P58),1), SUMIFS($K:$K, $C:$C, C58, $P:$P, ">="&DATE(YEAR(P58),MONTH(P58),1), $P:$P, "<="&EOMONTH(P58,0))>10), _xlfn.TEXTJOIN(", ", TRUE, _xlfn._xlws.FILTER($R:$R, ($C:$C=C58) * ($P:$P>=DATE(YEAR(P58),MONTH(P58),1)) * ($P:$P<=EOMONTH(P58,0)))), "")} -> O829 | Y58: {=IF(AND(P58<>"", P58>=DATE(YEAR(P58),MONTH(P58),1), SUMIFS($K:$K, $C:$C, C58, $P:$P, ">="&DATE(YEAR(P58),MONTH(P58),1), $P:$P, "<="&EOMONTH(P58,0))>10), _xlfn.TEXTJOIN(", ", TRUE, _xlfn._xlws.FILTER($S:$S, ($C:$C=C58) * ($P:$P>=DATE(YEAR(P58),MONTH(P58),1)) * ($P:$P<=EOMONTH(P58,0)))), "")} -> Parto por cesarea, sin otra especificacion
A59: 52 | B59: TEMPOACTIVA | C59: =_xlfn.XLOOKUP(D59,[1]!Data[CEDULA],[1]!Data[Nombre Completo],"No Existe",0,1) -> GENISIS MARIA CANTILLO TORRES | D59: 1002228922 | E59: =IFERROR(_xlfn.NUMBERVALUE(Data[[#This Row],[CEDULA ]],",","."),_xlfn.NUMBERVALUE(Data[[#This Row],[CEDULA ]],".",",")) -> 1002228922 | F59: =_xlfn.XLOOKUP(E59,[1]!Data[CEDULA],[1]!Data[CARGO],"No Existe",0,1) -> MESERO | G59: =_xlfn.XLOOKUP(E59,[1]!Data[CEDULA],[1]!Data[EMPRESA DONDE PRESTA SERVICIO],"No Existe",0,1) -> COMFAMILIAR ATLANTICO | H59: =_xlfn.XLOOKUP(E59,[1]!Data[CEDULA],[1]!Data[UBICACIÓN],"No Existe",0,1) -> SEDE SPORT GYM | I59: MUJER | J59: =UPPER(TEXT(Data[[#This Row],[F. INICIO]],"mmmm")) -> MARZO | K59: 28 | L59: EPS | M59: LICENCIA DE MATERNIDAD | N59: =_xlfn.XLOOKUP(D59,[1]!Data[CEDULA],[1]!Data[EPS/SURA],"No Existe",0,1) -> MUTUALSER | O59: =YEAR(Data[[#This Row],[F. INICIO]]) -> 2024 | P59: 45352 | Q59: 45379 | R59: O829 | S59: =IF(Data[[#This Row],[TIPO DE INCAPACIDAD]]="LICENCIA DE PATERNIDAD","Licencia de paternidad",IF(Data[[#This Row],[TIPO DE INCAPACIDAD]]="LICENCIA DE LUTO","Licencia de Luto",_xlfn.IFNA(VLOOKUP(R59,'CIE-10 PARA RIPS'!$A$6:B13179,2,0),"No especificado"))) -> Parto por cesarea, sin otra especificacion | T59: =IF(P59<>"", IF(P59>0, IF(P59<=DATE(YEAR(P59),MONTH(P59),DAY(P59)), IF(P59>=DATE(YEAR(P59),MONTH(P59),1), IF(K59>10, C59, IF(SUMIFS($K:$K, $C:$C, C59, $P:$P, ">="&DATE(YEAR(P59),MONTH(P59),1), $P:$P, "<="&EOMONTH(P59,0))>10, C59, "")), ""))), "") -> GENISIS MARIA CANTILLO TORRES | U59: =IF(AND(P59<>"", P59>=DATE(YEAR(P59),MONTH(P59),1), SUMIFS($K:$K, $C:$C, C59, $P:$P, ">="&DATE(YEAR(P59),MONTH(P59),1), $P:$P, "<="&EOMONTH(P59,0))>10), K59, "") -> 28 | V59: =IF(AND(P59<>"", P59>=DATE(YEAR(P59),MONTH(P59),1), SUMIFS($K:$K, $C:$C, C59, $P:$P, ">="&DATE(YEAR(P59),MONTH(P59),1), $P:$P, "<="&EOMONTH(P59,0))>10), YEAR(P59), "") -> 2024 | W59: =IF(AND(P59<>"", P59>=DATE(YEAR(P59),MONTH(P59),1), SUMIFS($K:$K, $C:$C, C59, $P:$P, ">="&DATE(YEAR(P59),MONTH(P59),1), $P:$P, "<="&EOMONTH(P59,0))>10), TEXT(P59, "MMMM"), "") -> marzo | X59: {=IF(AND(P59<>"", P59>=DATE(YEAR(P59),MONTH(P59),1), SUMIFS($K:$K, $C:$C, C59, $P:$P, ">="&DATE(YEAR(P59),MONTH(P59),1), $P:$P, "<="&EOMONTH(P59,0))>10), _xlfn.TEXTJOIN(", ", TRUE, _xlfn._xlws.FILTER($R:$R, ($C:$C=C59) * ($P:$P>=DATE(YEAR(P59),MONTH(P59),1)) * ($P:$P<=EOMONTH(P59,0)))), "")} -> O829 | Y59: {=IF(AND(P59<>"", P59>=DATE(YEAR(P59),MONTH(P59),1), SUMIFS($K:$K, $C:$C, C59, $P:$P, ">="&DATE(YEAR(P59),MONTH(P59),1), $P:$P, "<="&EOMONTH(P59,0))>10), _xlfn.TEXTJOIN(", ", TRUE, _xlfn._xlws.FILTER($S:$S, ($C:$C=C59) * ($P:$P>=DATE(YEAR(P59),MONTH(P59),1)) * ($P:$P<=EOMONTH(P59,0)))), "")} -> Parto por cesarea, sin otra especificacion
A60: 53 | B60: TEMPOACTIVA | C60: =_xlfn.XLOOKUP(D60,[1]!Data[CEDULA],[1]!Data[Nombre Completo],"No Existe",0,1) -> HELIS MARI RAMIREZ PATIÑO | D60: 1140868628 | E60: =IFERROR(_xlfn.NUMBERVALUE(Data[[#This Row],[CEDULA ]],",","."),_xlfn.NUMBERVALUE(Data[[#This Row],[CEDULA ]],".",",")) -> 1140868628 | F60: =_xlfn.XLOOKUP(E60,[1]!Data[CEDULA],[1]!Data[CARGO],"No Existe",0,1) -> SUPERNUMERARIO(A) | G60: =_xlfn.XLOOKUP(E60,[1]!Data[CEDULA],[1]!Data[EMPRESA DONDE PRESTA SERVICIO],"No Existe",0,1) -> COMFAMILIAR ATLANTICO | H60: =_xlfn.XLOOKUP(E60,[1]!Data[CEDULA],[1]!Data[UBICACIÓN],"No Existe",0,1) -> SEDE NORTE | I60: MUJER | J60: =UPPER(TEXT(Data[[#This Row],[F. INICIO]],"mmmm")) -> MARZO | K60: 18 | L60: EPS | M60: ENFERMENDAD GENERAL | N60: =_xlfn.XLOOKUP(D60,[1]!Data[CEDULA],[1]!Data[EPS/SURA],"No Existe",0,1) -> MUTUALSER | O60: =YEAR(Data[[#This Row],[F. INICIO]]) -> 2024 | P60: 45365 | Q60: 45382 | R60: Z359 | S60: =IF(Data[[#This Row],[TIPO DE INCAPACIDAD]]="LICENCIA DE PATERNIDAD","Licencia de paternidad",IF(Data[[#This Row],[TIPO DE INCAPACIDAD]]="LICENCIA DE LUTO","Licencia de Luto",_xlfn.IFNA(VLOOKUP(R60,'CIE-10 PARA RIPS'!$A$6:B13195,2,0),"No especificado"))) -> Supervision de embarazo de alto riesgo, sin otra especificacion | T60: =IF(P60<>"", IF(P60>0, IF(P60<=DATE(YEAR(P60),MONTH(P60),DAY(P60)), IF(P60>=DATE(YEAR(P60),MONTH(P60),1), IF(K60>10, C60, IF(SUMIFS($K:$K, $C:$C, C60, $P:$P, ">="&DATE(YEAR(P60),MONTH(P60),1), $P:$P, "<="&EOMONTH(P60,0))>10, C60, "")), ""))), "") -> HELIS MARI RAMIREZ PATIÑO | U60: =IF(AND(P60<>"", P60>=DATE(YEAR(P60),MONTH(P60),1), SUMIFS($K:$K, $C:$C, C60, $P:$P, ">="&DATE(YEAR(P60),MONTH(P60),1), $P:$P, "<="&EOMONTH(P60,0))>10), K60, "") -> 18 | V60: =IF(AND(P60<>"", P60>=DATE(YEAR(P60),MONTH(P60),1), SUMIFS($K:$K, $C:$C, C60, $P:$P, ">="&DATE(YEAR(P60),MONTH(P60),1), $P:$P, "<="&EOMONTH(P60,0))>10), YEAR(P60), "") -> 2024 | W60: =IF(AND(P60<>"", P60>=DATE(YEAR(P60),MONTH(P60),1), SUMIFS($K:$K, $C:$C, C60, $P:$P, ">="&DATE(YEAR(P60),MONTH(P60),1), $P:$P, "<="&EOMONTH(P60,0))>10), TEXT(P60, "MMMM"), "") -> marzo | X60: {=IF(AND(P60<>"", P60>=DATE(YEAR(P60),MONTH(P60),1), SUMIFS($K:$K, $C:$C, C60, $P:$P, ">="&DATE(YEAR(P60),MONTH(P60),1), $P:$P, "<="&EOMONTH(P60,0))>10), _xlfn.TEXTJOIN(", ", TRUE, _xlfn._xlws.FILTER($R:$R, ($C:$C=C60) * ($P:$P>=DATE(YEAR(P60),MONTH(P60),1)) * ($P:$P<=EOMONTH(P60,0)))), "")} -> Z359 | Y60: {=IF(AND(P60<>"", P60>=DATE(YEAR(P60),MONTH(P60),1), SUMIFS($K:$K, $C:$C, C60, $P:$P, ">="&DATE(YEAR(P60),MONTH(P60),1), $P:$P, "<="&EOMONTH(P60,0))>10), _xlfn.TEXTJOIN(", ", TRUE, _xlfn._xlws.FILTER($S:$S, ($C:$C=C60) * ($P:$P>=DATE(YEAR(P60),MONTH(P60),1)) * ($P:$P<=EOMONTH(P60,0)))), "")} -> Supervision de embarazo de alto riesgo, sin otra especificacion
A61: 54 | B61: TEMPOACTIVA | C61: =_xlfn.XLOOKUP(D61,[1]!Data[CEDULA],[1]!Data[Nombre Completo],"No Existe",0,1) -> MARTIN JOSE BALLESTAS JIMENEZ | D61: 1002131545 | E61: =IFERROR(_xlfn.NUMBERVALUE(Data[[#This Row],[CEDULA ]],",","."),_xlfn.NUMBERVALUE(Data[[#This Row],[CEDULA ]],".",",")) -> 1002131545 | F61: =_xlfn.XLOOKUP(E61,[1]!Data[CEDULA],[1]!Data[CARGO],"No Existe",0,1) -> SUPERNUMERARIO(A) | G61: =_xlfn.XLOOKUP(E61,[1]!Data[CEDULA],[1]!Data[EMPRESA DONDE PRESTA SERVICIO],"No Existe",0,1) -> COMFAMILIAR ATLANTICO | H61: =_xlfn.XLOOKUP(E61,[1]!Data[CEDULA],[1]!Data[UBICACIÓN],"No Existe",0,1) -> SEDE CARIBE | I61: HOMBRE | J61: =UPPER(TEXT(Data[[#This Row],[F. INICIO]],"mmmm")) -> MARZO | K61: 2 | L61: EPS | M61: ENFERMENDAD GENERAL | N61: =_xlfn.XLOOKUP(D61,[1]!Data[CEDULA],[1]!Data[EPS/SURA],"No Existe",0,1) -> EPS/SURA | O61: =YEAR(Data[[#This Row],[F. INICIO]]) -> 2024 | P61: 45370 | Q61: 45371 | R61: b349 | S61: =IF(Data[[#This Row],[TIPO DE INCAPACIDAD]]="LICENCIA DE PATERNIDAD","Licencia de paternidad",IF(Data[[#This Row],[TIPO DE INCAPACIDAD]]="LICENCIA DE LUTO","Licencia de Luto",_xlfn.IFNA(VLOOKUP(R61,'CIE-10 PARA RIPS'!$A$6:B13197,2,0),"No especificado"))) -> Infeccion viral, no especificada | T61: =IF(P61<>"", IF(P61>0, IF(P61<=DATE(YEAR(P61),MONTH(P61),DAY(P61)), IF(P61>=DATE(YEAR(P61),MONTH(P61),1), IF(K61>10, C61, IF(SUMIFS($K:$K, $C:$C, C61, $P:$P, ">="&DATE(YEAR(P61),MONTH(P61),1), $P:$P, "<="&EOMONTH(P61,0))>10, C61, "")), ""))), "") | U61: =IF(AND(P61<>"", P61>=DATE(YEAR(P61),MONTH(P61),1), SUMIFS($K:$K, $C:$C, C61, $P:$P, ">="&DATE(YEAR(P61),MONTH(P61),1), $P:$P, "<="&EOMONTH(P61,0))>10), K61, "") | V61: =IF(AND(P61<>"", P61>=DATE(YEAR(P61),MONTH(P61),1), SUMIFS($K:$K, $C:$C, C61, $P:$P, ">="&DATE(YEAR(P61),MONTH(P61),1), $P:$P, "<="&EOMONTH(P61,0))>10), YEAR(P61), "") | W61: =IF(AND(P61<>"", P61>=DATE(YEAR(P61),MONTH(P61),1), SUMIFS($K:$K, $C:$C, C61, $P:$P, ">="&DATE(YEAR(P61),MONTH(P61),1), $P:$P, "<="&EOMONTH(P61,0))>10), TEXT(P61, "MMMM"), "") | X61: {=IF(AND(P61<>"", P61>=DATE(YEAR(P61),MONTH(P61),1), SUMIFS($K:$K, $C:$C, C61, $P:$P, ">="&DATE(YEAR(P61),MONTH(P61),1), $P:$P, "<="&EOMONTH(P61,0))>10), _xlfn.TEXTJOIN(", ", TRUE, _xlfn._xlws.FILTER($R:$R, ($C:$C=C61) * ($P:$P>=DATE(YEAR(P61),MONTH(P61),1)) * ($P:$P<=EOMONTH(P61,0)))), "")} | Y61: {=IF(AND(P61<>"", P61>=DATE(YEAR(P61),MONTH(P61),1), SUMIFS($K:$K, $C:$C, C61, $P:$P, ">="&DATE(YEAR(P61),MONTH(P61),1), $P:$P, "<="&EOMONTH(P61,0))>10), _xlfn.TEXTJOIN(", ", TRUE, _xlfn._xlws.FILTER($S:$S, ($C:$C=C61) * ($P:$P>=DATE(YEAR(P61),MONTH(P61),1)) * ($P:$P<=EOMONTH(P61,0)))), "")}
A62: 55 | B62: TEMPOACTIVA | C62: =_xlfn.XLOOKUP(D62,[1]!Data[CEDULA],[1]!Data[Nombre Completo],"No Existe",0,1) -> KELLY YULIETH ROJAS MERCADO | D62: 1065599209 | E62: =IFERROR(_xlfn.NUMBERVALUE(Data[[#This Row],[CEDULA ]],",","."),_xlfn.NUMBERVALUE(Data[[#This Row],[CEDULA ]],".",",")) -> 1065599209 | F62: =_xlfn.XLOOKUP(E62,[1]!Data[CEDULA],[1]!Data[CARGO],"No Existe",0,1) -> SUPERNUMERARIO(A) | G62: =_xlfn.XLOOKUP(E62,[1]!Data[CEDULA],[1]!Data[EMPRESA DONDE PRESTA SERVICIO],"No Existe",0,1) -> COMFAMILIAR ATLANTICO | H62: =_xlfn.XLOOKUP(E62,[1]!Data[CEDULA],[1]!Data[UBICACIÓN],"No Existe",0,1) -> CENTRO RECREACIONAL TURIPANA | I62: MUJER | J62: =UPPER(TEXT(Data[[#This Row],[F. INICIO]],"mmmm")) -> MARZO | K62: 2 | L62: EPS | M62: ENFERMENDAD GENERAL | N62: =_xlfn.XLOOKUP(D62,[1]!Data[CEDULA],[1]!Data[EPS/SURA],"No Existe",0,1) -> MUTUALSER | O62: =YEAR(Data[[#This Row],[F. INICIO]]) -> 2024 | P62: 45369 | Q62: 45370 | R62: R51X | S62: =IF(Data[[#This Row],[TIPO DE INCAPACIDAD]]="LICENCIA DE PATERNIDAD","Licencia de paternidad",IF(Data[[#This Row],[TIPO DE INCAPACIDAD]]="LICENCIA DE LUTO","Licencia de Luto",_xlfn.IFNA(VLOOKUP(R62,'CIE-10 PARA RIPS'!$A$6:B13198,2,0),"No especificado"))) -> Cefalea | T62: =IF(P62<>"", IF(P62>0, IF(P62<=DATE(YEAR(P62),MONTH(P62),DAY(P62)), IF(P62>=DATE(YEAR(P62),MONTH(P62),1), IF(K62>10, C62, IF(SUMIFS($K:$K, $C:$C, C62, $P:$P, ">="&DATE(YEAR(P62),MONTH(P62),1), $P:$P, "<="&EOMONTH(P62,0))>10, C62, "")), ""))), "") | U62: =IF(AND(P62<>"", P62>=DATE(YEAR(P62),MONTH(P62),1), SUMIFS($K:$K, $C:$C, C62, $P:$P, ">="&DATE(YEAR(P62),MONTH(P62),1), $P:$P, "<="&EOMONTH(P62,0))>10), K62, "") | V62: =IF(AND(P62<>"", P62>=DATE(YEAR(P62),MONTH(P62),1), SUMIFS($K:$K, $C:$C, C62, $P:$P, ">="&DATE(YEAR(P62),MONTH(P62),1), $P:$P, "<="&EOMONTH(P62,0))>10), YEAR(P62), "") | W62: =IF(AND(P62<>"", P62>=DATE(YEAR(P62),MONTH(P62),1), SUMIFS($K:$K, $C:$C, C62, $P:$P, ">="&DATE(YEAR(P62),MONTH(P62),1), $P:$P, "<="&EOMONTH(P62,0))>10), TEXT(P62, "MMMM"), "") | X62: {=IF(AND(P62<>"", P62>=DATE(YEAR(P62),MONTH(P62),1), SUMIFS($K:$K, $C:$C, C62, $P:$P, ">="&DATE(YEAR(P62),MONTH(P62),1), $P:$P, "<="&EOMONTH(P62,0))>10), _xlfn.TEXTJOIN(", ", TRUE, _xlfn._xlws.FILTER($R:$R, ($C:$C=C62) * ($P:$P>=DATE(YEAR(P62),MONTH(P62),1)) * ($P:$P<=EOMONTH(P62,0)))), "")} | Y62: {=IF(AND(P62<>"", P62>=DATE(YEAR(P62),MONTH(P62),1), SUMIFS($K:$K, $C:$C, C62, $P:$P, ">="&DATE(YEAR(P62),MONTH(P62),1), $P:$P, "<="&EOMONTH(P62,0))>10), _xlfn.TEXTJOIN(", ", TRUE, _xlfn._xlws.FILTER($S:$S, ($C:$C=C62) * ($P:$P>=DATE(YEAR(P62),MONTH(P62),1)) * ($P:$P<=EOMONTH(P62,0)))), "")}
A63: 56 | B63: TEMPOACTIVA | C63: =_xlfn.XLOOKUP(D63,[1]!Data[CEDULA],[1]!Data[Nombre Completo],"No Existe",0,1) -> LISBET MARIA CANTILLO MURIEL | D63: 44205186 | E63: =IFERROR(_xlfn.NUMBERVALUE(Data[[#This Row],[CEDULA ]],",","."),_xlfn.NUMBERVALUE(Data[[#This Row],[CEDULA ]],".",",")) -> 44205186 | F63: =_xlfn.XLOOKUP(E63,[1]!Data[CEDULA],[1]!Data[CARGO],"No Existe",0,1) -> SUPERNUMERARIO(A) | G63: =_xlfn.XLOOKUP(E63,[1]!Data[CEDULA],[1]!Data[EMPRESA DONDE PRESTA SERVICIO],"No Existe",0,1) -> COMFAMILIAR ATLANTICO | H63: =_xlfn.XLOOKUP(E63,[1]!Data[CEDULA],[1]!Data[UBICACIÓN],"No Existe",0,1) -> SEDE NORTE | I63: MUJER | J63: =UPPER(TEXT(Data[[#This Row],[F. INICIO]],"mmmm")) -> MARZO | K63: 1 | L63: EPS | M63: ENFERMENDAD GENERAL | N63: =_xlfn.XLOOKUP(D63,[1]!Data[CEDULA],[1]!Data[EPS/SURA],"No Existe",0,1) -> EPS/SURA | O63: =YEAR(Data[[#This Row],[F. INICIO]]) -> 2024 | P63: 45373 | Q63: 45373 | R63: J00X | S63: =IF(Data[[#This Row],[TIPO DE INCAPACIDAD]]="LICENCIA DE PATERNIDAD","Licencia de paternidad",IF(Data[[#This Row],[TIPO DE INCAPACIDAD]]="LICENCIA DE LUTO","Licencia de Luto",_xlfn.IFNA(VLOOKUP(R63,'CIE-10 PARA RIPS'!$A$6:B13200,2,0),"No especificado"))) -> Rinofaringitis aguda [resfriado comun] | T63: =IF(P63<>"", IF(P63>0, IF(P63<=DATE(YEAR(P63),MONTH(P63),DAY(P63)), IF(P63>=DATE(YEAR(P63),MONTH(P63),1), IF(K63>10, C63, IF(SUMIFS($K:$K, $C:$C, C63, $P:$P, ">="&DATE(YEAR(P63),MONTH(P63),1), $P:$P, "<="&EOMONTH(P63,0))>10, C63, "")), ""))), "") | U63: =IF(AND(P63<>"", P63>=DATE(YEAR(P63),MONTH(P63),1), SUMIFS($K:$K, $C:$C, C63, $P:$P, ">="&DATE(YEAR(P63),MONTH(P63),1), $P:$P, "<="&EOMONTH(P63,0))>10), K63, "") | V63: =IF(AND(P63<>"", P63>=DATE(YEAR(P63),MONTH(P63),1), SUMIFS($K:$K, $C:$C, C63, $P:$P, ">="&DATE(YEAR(P63),MONTH(P63),1), $P:$P, "<="&EOMONTH(P63,0))>10), YEAR(P63), "") | W63: =IF(AND(P63<>"", P63>=DATE(YEAR(P63),MONTH(P63),1), SUMIFS($K:$K, $C:$C, C63, $P:$P, ">="&DATE(YEAR(P63),MONTH(P63),1), $P:$P, "<="&EOMONTH(P63,0))>10), TEXT(P63, "MMMM"), "") | X63: {=IF(AND(P63<>"", P63>=DATE(YEAR(P63),MONTH(P63),1), SUMIFS($K:$K, $C:$C, C63, $P:$P, ">="&DATE(YEAR(P63),MONTH(P63),1), $P:$P, "<="&EOMONTH(P63,0))>10), _xlfn.TEXTJOIN(", ", TRUE, _xlfn._xlws.FILTER($R:$R, ($C:$C=C63) * ($P:$P>=DATE(YEAR(P63),MONTH(P63),1)) * ($P:$P<=EOMONTH(P63,0)))), "")} | Y63: {=IF(AND(P63<>"", P63>=DATE(YEAR(P63),MONTH(P63),1), SUMIFS($K:$K, $C:$C, C63, $P:$P, ">="&DATE(YEAR(P63),MONTH(P63),1), $P:$P, "<="&EOMONTH(P63,0))>10), _xlfn.TEXTJOIN(", ", TRUE, _xlfn._xlws.FILTER($S:$S, ($C:$C=C63) * ($P:$P>=DATE(YEAR(P63),MONTH(P63),1)) * ($P:$P<=EOMONTH(P63,0)))), "")}
A64: 57 | B64: TEMPOACTIVA | C64: =_xlfn.XLOOKUP(D64,[1]!Data[CEDULA],[1]!Data[Nombre Completo],"No Existe",0,1) -> LISETH ANDREA RODRIGUEZ BARRAZA | D64: 1143163270 | E64: =IFERROR(_xlfn.NUMBERVALUE(Data[[#This Row],[CEDULA ]],",","."),_xlfn.NUMBERVALUE(Data[[#This Row],[CEDULA ]],".",",")) -> 1143163270 | F64: =_xlfn.XLOOKUP(E64,[1]!Data[CEDULA],[1]!Data[CARGO],"No Existe",0,1) -> AYUDANTE COCINA | G64: =_xlfn.XLOOKUP(E64,[1]!Data[CEDULA],[1]!Data[EMPRESA DONDE PRESTA SERVICIO],"No Existe",0,1) -> COMFAMILIAR ATLANTICO | H64: =_xlfn.XLOOKUP(E64,[1]!Data[CEDULA],[1]!Data[UBICACIÓN],"No Existe",0,1) -> CRU MERCADEO | I64: MUJER | J64: =UPPER(TEXT(Data[[#This Row],[F. INICIO]],"mmmm")) -> MARZO | K64: 2 | L64: EPS | M64: ENFERMENDAD GENERAL | N64: =_xlfn.XLOOKUP(D64,[1]!Data[CEDULA],[1]!Data[EPS/SURA],"No Existe",0,1) -> CAJACOPI | O64: =YEAR(Data[[#This Row],[F. INICIO]]) -> 2024 | P64: 45372 | Q64: 45373 | R64: A084 | S64: =IF(Data[[#This Row],[TIPO DE INCAPACIDAD]]="LICENCIA DE PATERNIDAD","Licencia de paternidad",IF(Data[[#This Row],[TIPO DE INCAPACIDAD]]="LICENCIA DE LUTO","Licencia de Luto",_xlfn.IFNA(VLOOKUP(R64,'CIE-10 PARA RIPS'!$A$6:B13201,2,0),"No especificado"))) -> Infeccion intestinal viral, sin otra especificacion | T64: =IF(P64<>"", IF(P64>0, IF(P64<=DATE(YEAR(P64),MONTH(P64),DAY(P64)), IF(P64>=DATE(YEAR(P64),MONTH(P64),1), IF(K64>10, C64, IF(SUMIFS($K:$K, $C:$C, C64, $P:$P, ">="&DATE(YEAR(P64),MONTH(P64),1), $P:$P, "<="&EOMONTH(P64,0))>10, C64, "")), ""))), "") | U64: =IF(AND(P64<>"", P64>=DATE(YEAR(P64),MONTH(P64),1), SUMIFS($K:$K, $C:$C, C64, $P:$P, ">="&DATE(YEAR(P64),MONTH(P64),1), $P:$P, "<="&EOMONTH(P64,0))>10), K64, "") | V64: =IF(AND(P64<>"", P64>=DATE(YEAR(P64),MONTH(P64),1), SUMIFS($K:$K, $C:$C, C64, $P:$P, ">="&DATE(YEAR(P64),MONTH(P64),1), $P:$P, "<="&EOMONTH(P64,0))>10), YEAR(P64), "") | W64: =IF(AND(P64<>"", P64>=DATE(YEAR(P64),MONTH(P64),1), SUMIFS($K:$K, $C:$C, C64, $P:$P, ">="&DATE(YEAR(P64),MONTH(P64),1), $P:$P, "<="&EOMONTH(P64,0))>10), TEXT(P64, "MMMM"), "") | X64: {=IF(AND(P64<>"", P64>=DATE(YEAR(P64),MONTH(P64),1), SUMIFS($K:$K, $C:$C, C64, $P:$P, ">="&DATE(YEAR(P64),MONTH(P64),1), $P:$P, "<="&EOMONTH(P64,0))>10), _xlfn.TEXTJOIN(", ", TRUE, _xlfn._xlws.FILTER($R:$R, ($C:$C=C64) * ($P:$P>=DATE(YEAR(P64),MONTH(P64),1)) * ($P:$P<=EOMONTH(P64,0)))), "")} | Y64: {=IF(AND(P64<>"", P64>=DATE(YEAR(P64),MONTH(P64),1), SUMIFS($K:$K, $C:$C, C64, $P:$P, ">="&DATE(YEAR(P64),MONTH(P64),1), $P:$P, "<="&EOMONTH(P64,0))>10), _xlfn.TEXTJOIN(", ", TRUE, _xlfn._xlws.FILTER($S:$S, ($C:$C=C64) * ($P:$P>=DATE(YEAR(P64),MONTH(P64),1)) * ($P:$P<=EOMONTH(P64,0)))), "")}
A65: 58 | B65: TEMPOACTIVA | C65: =_xlfn.XLOOKUP(D65,[1]!Data[CEDULA],[1]!Data[Nombre Completo],"No Existe",0,1) -> IVAN ANDRES VALENCIA PEREZ | D65: 1042243313 | E65: =IFERROR(_xlfn.NUMBERVALUE(Data[[#This Row],[CEDULA ]],",","."),_xlfn.NUMBERVALUE(Data[[#This Row],[CEDULA ]],".",",")) -> 1042243313 | F65: =_xlfn.XLOOKUP(E65,[1]!Data[CEDULA],[1]!Data[CARGO],"No Existe",0,1) -> SUPERNUMERARIO(A) | G65: =_xlfn.XLOOKUP(E65,[1]!Data[CEDULA],[1]!Data[EMPRESA DONDE PRESTA SERVICIO],"No Existe",0,1) -> COMFAMILIAR ATLANTICO | H65: =_xlfn.XLOOKUP(E65,[1]!Data[CEDULA],[1]!Data[UBICACIÓN],"No Existe",0,1) -> SEDE NORTE | I65: HOMBRE | J65: =UPPER(TEXT(Data[[#This Row],[F. INICIO]],"mmmm")) -> MARZO | K65: 2 | L65: EPS | M65: ENFERMENDAD GENERAL | N65: =_xlfn.XLOOKUP(D65,[1]!Data[CEDULA],[1]!Data[EPS/SURA],"No Existe",0,1) -> MUTUALSER | O65: =YEAR(Data[[#This Row],[F. INICIO]]) -> 2024 | P65: 45369 | Q65: 45370 | R65: J060 | S65: =IF(Data[[#This Row],[TIPO DE INCAPACIDAD]]="LICENCIA DE PATERNIDAD","Licencia de paternidad",IF(Data[[#This Row],[TIPO DE INCAPACIDAD]]="LICENCIA DE LUTO","Licencia de Luto",_xlfn.IFNA(VLOOKUP(R65,'CIE-10 PARA RIPS'!$A$6:B13202,2,0),"No especificado"))) -> Laringofaringitis aguda | T65: =IF(P65<>"", IF(P65>0, IF(P65<=DATE(YEAR(P65),MONTH(P65),DAY(P65)), IF(P65>=DATE(YEAR(P65),MONTH(P65),1), IF(K65>10, C65, IF(SUMIFS($K:$K, $C:$C, C65, $P:$P, ">="&DATE(YEAR(P65),MONTH(P65),1), $P:$P, "<="&EOMONTH(P65,0))>10, C65, "")), ""))), "") | U65: =IF(AND(P65<>"", P65>=DATE(YEAR(P65),MONTH(P65),1), SUMIFS($K:$K, $C:$C, C65, $P:$P, ">="&DATE(YEAR(P65),MONTH(P65),1), $P:$P, "<="&EOMONTH(P65,0))>10), K65, "") | V65: =IF(AND(P65<>"", P65>=DATE(YEAR(P65),MONTH(P65),1), SUMIFS($K:$K, $C:$C, C65, $P:$P, ">="&DATE(YEAR(P65),MONTH(P65),1), $P:$P, "<="&EOMONTH(P65,0))>10), YEAR(P65), "") | W65: =IF(AND(P65<>"", P65>=DATE(YEAR(P65),MONTH(P65),1), SUMIFS($K:$K, $C:$C, C65, $P:$P, ">="&DATE(YEAR(P65),MONTH(P65),1), $P:$P, "<="&EOMONTH(P65,0))>10), TEXT(P65, "MMMM"), "") | X65: {=IF(AND(P65<>"", P65>=DATE(YEAR(P65),MONTH(P65),1), SUMIFS($K:$K, $C:$C, C65, $P:$P, ">="&DATE(YEAR(P65),MONTH(P65),1), $P:$P, "<="&EOMONTH(P65,0))>10), _xlfn.TEXTJOIN(", ", TRUE, _xlfn._xlws.FILTER($R:$R, ($C:$C=C65) * ($P:$P>=DATE(YEAR(P65),MONTH(P65),1)) * ($P:$P<=EOMONTH(P65,0)))), "")} | Y65: {=IF(AND(P65<>"", P65>=DATE(YEAR(P65),MONTH(P65),1), SUMIFS($K:$K, $C:$C, C65, $P:$P, ">="&DATE(YEAR(P65),MONTH(P65),1), $P:$P, "<="&EOMONTH(P65,0))>10), _xlfn.TEXTJOIN(", ", TRUE, _xlfn._xlws.FILTER($S:$S, ($C:$C=C65) * ($P:$P>=DATE(YEAR(P65),MONTH(P65),1)) * ($P:$P<=EOMONTH(P65,0)))), "")}
A66: 59 | B66: TEMPOACTIVA | C66: =_xlfn.XLOOKUP(D66,[1]!Data[CEDULA],[1]!Data[Nombre Completo],"No Existe",0,1) -> ALICIA ESTHER VASQUEZ YEPES | D66: 1140853573 | E66: =IFERROR(_xlfn.NUMBERVALUE(Data[[#This Row],[CEDULA ]],",","."),_xlfn.NUMBERVALUE(Data[[#This Row],[CEDULA ]],".",",")) -> 1140853573 | F66: =_xlfn.XLOOKUP(E66,[1]!Data[CEDULA],[1]!Data[CARGO],"No Existe",0,1) -> ASESOR COMERCIAL | G66: =_xlfn.XLOOKUP(E66,[1]!Data[CEDULA],[1]!Data[EMPRESA DONDE PRESTA SERVICIO],"No Existe",0,1) -> COMFAMILIAR ATLANTICO | H66: =_xlfn.XLOOKUP(E66,[1]!Data[CEDULA],[1]!Data[UBICACIÓN],"No Existe",0,1) -> C. ATENCION VIA 40 | I66: MUJER | J66: =UPPER(TEXT(Data[[#This Row],[F. INICIO]],"mmmm")) -> AGOSTO | K66: 2 | L66: EPS | M66: ENFERMENDAD GENERAL | N66: =_xlfn.XLOOKUP(D66,[1]!Data[CEDULA],[1]!Data[EPS/SURA],"No Existe",0,1) -> EPS/SURA | O66: =YEAR(Data[[#This Row],[F. INICIO]]) -> 2017 | P66: 42977 | Q66: 42978 | R66: M624 | S66: =IF(Data[[#This Row],[TIPO DE INCAPACIDAD]]="LICENCIA DE PATERNIDAD","Licencia de paternidad",IF(Data[[#This Row],[TIPO DE INCAPACIDAD]]="LICENCIA DE LUTO","Licencia de Luto",_xlfn.IFNA(VLOOKUP(R66,'CIE-10 PARA RIPS'!$A$6:B13231,2,0),"No especificado"))) -> Contractura muscular | T66: =IF(P66<>"", IF(P66>0, IF(P66<=DATE(YEAR(P66),MONTH(P66),DAY(P66)), IF(P66>=DATE(YEAR(P66),MONTH(P66),1), IF(K66>10, C66, IF(SUMIFS($K:$K, $C:$C, C66, $P:$P, ">="&DATE(YEAR(P66),MONTH(P66),1), $P:$P, "<="&EOMONTH(P66,0))>10, C66, "")), ""))), "") | U66: =IF(AND(P66<>"", P66>=DATE(YEAR(P66),MONTH(P66),1), SUMIFS($K:$K, $C:$C, C66, $P:$P, ">="&DATE(YEAR(P66),MONTH(P66),1), $P:$P, "<="&EOMONTH(P66,0))>10), K66, "") | V66: =IF(AND(P66<>"", P66>=DATE(YEAR(P66),MONTH(P66),1), SUMIFS($K:$K, $C:$C, C66, $P:$P, ">="&DATE(YEAR(P66),MONTH(P66),1), $P:$P, "<="&EOMONTH(P66,0))>10), YEAR(P66), "") | W66: =IF(AND(P66<>"", P66>=DATE(YEAR(P66),MONTH(P66),1), SUMIFS($K:$K, $C:$C, C66, $P:$P, ">="&DATE(YEAR(P66),MONTH(P66),1), $P:$P, "<="&EOMONTH(P66,0))>10), TEXT(P66, "MMMM"), "") | X66: {=IF(AND(P66<>"", P66>=DATE(YEAR(P66),MONTH(P66),1), SUMIFS($K:$K, $C:$C, C66, $P:$P, ">="&DATE(YEAR(P66),MONTH(P66),1), $P:$P, "<="&EOMONTH(P66,0))>10), _xlfn.TEXTJOIN(", ", TRUE, _xlfn._xlws.FILTER($R:$R, ($C:$C=C66) * ($P:$P>=DATE(YEAR(P66),MONTH(P66),1)) * ($P:$P<=EOMONTH(P66,0)))), "")} | Y66: {=IF(AND(P66<>"", P66>=DATE(YEAR(P66),MONTH(P66),1), SUMIFS($K:$K, $C:$C, C66, $P:$P, ">="&DATE(YEAR(P66),MONTH(P66),1), $P:$P, "<="&EOMONTH(P66,0))>10), _xlfn.TEXTJOIN(", ", TRUE, _xlfn._xlws.FILTER($S:$S, ($C:$C=C66) * ($P:$P>=DATE(YEAR(P66),MONTH(P66),1)) * ($P:$P<=EOMONTH(P66,0)))), "")}
A67: 60 | B67: TEMPOACTIVA | C67: =_xlfn.XLOOKUP(D67,[1]!Data[CEDULA],[1]!Data[Nombre Completo],"No Existe",0,1) -> CRISTIAN IVAN ALVAREZ ORTEGA | D67: 1143262291 | E67: =IFERROR(_xlfn.NUMBERVALUE(Data[[#This Row],[CEDULA ]],",","."),_xlfn.NUMBERVALUE(Data[[#This Row],[CEDULA ]],".",",")) -> 1143262291 | F67: =_xlfn.XLOOKUP(E67,[1]!Data[CEDULA],[1]!Data[CARGO],"No Existe",0,1) -> SUPERNUMERARIO(A) | G67: =_xlfn.XLOOKUP(E67,[1]!Data[CEDULA],[1]!Data[EMPRESA DONDE PRESTA SERVICIO],"No Existe",0,1) -> COMFAMILIAR ATLANTICO | H67: =_xlfn.XLOOKUP(E67,[1]!Data[CEDULA],[1]!Data[UBICACIÓN],"No Existe",0,1) -> CENTRO RECREACIONAL CLL 48 | I67: HOMBRE | J67: =UPPER(TEXT(Data[[#This Row],[F. INICIO]],"mmmm")) -> MARZO | K67: 5 | L67: EMPRESA | M67: LICENCIA DE LUTO | N67: =_xlfn.XLOOKUP(D67,[1]!Data[CEDULA],[1]!Data[EPS/SURA],"No Existe",0,1) -> SALUD TOTAL | O67: =YEAR(Data[[#This Row],[F. INICIO]]) -> 2024 | P67: 45368 | Q67: 45372 | R67: =IF(Data[[#This Row],[DESCRIPCION]]="Licencia de Luto","Licencia de Luto",IF(Data[[#This Row],[DESCRIPCION]]="Licencia de paternidad","Licencia de paternidad")) -> Licencia de Luto | S67: =IF(Data[[#This Row],[TIPO DE INCAPACIDAD]]="LICENCIA DE PATERNIDAD","Licencia de paternidad",IF(Data[[#This Row],[TIPO DE INCAPACIDAD]]="LICENCIA DE LUTO","Licencia de Luto",_xlfn.IFNA(VLOOKUP(R67,'CIE-10 PARA RIPS'!$A$6:B13421,2,0),"No especificado"))) -> Licencia de Luto | T67: =IF(P67<>"", IF(P67>0, IF(P67<=DATE(YEAR(P67),MONTH(P67),DAY(P67)), IF(P67>=DATE(YEAR(P67),MONTH(P67),1), IF(K67>10, C67, IF(SUMIFS($K:$K, $C:$C, C67, $P:$P, ">="&DATE(YEAR(P67),MONTH(P67),1), $P:$P, "<="&EOMONTH(P67,0))>10, C67, "")), ""))), "") | U67: =IF(AND(P67<>"", P67>=DATE(YEAR(P67),MONTH(P67),1), SUMIFS($K:$K, $C:$C, C67, $P:$P, ">="&DATE(YEAR(P67),MONTH(P67),1), $P:$P, "<="&EOMONTH(P67,0))>10), K67, "") | V67: =IF(AND(P67<>"", P67>=DATE(YEAR(P67),MONTH(P67),1), SUMIFS($K:$K, $C:$C, C67, $P:$P, ">="&DATE(YEAR(P67),MONTH(P67),1), $P:$P, "<="&EOMONTH(P67,0))>10), YEAR(P67), "") | W67: =IF(AND(P67<>"", P67>=DATE(YEAR(P67),MONTH(P67),1), SUMIFS($K:$K, $C:$C, C67, $P:$P, ">="&DATE(YEAR(P67),MONTH(P67),1), $P:$P, "<="&EOMONTH(P67,0))>10), TEXT(P67, "MMMM"), "") | X67: {=IF(AND(P67<>"", P67>=DATE(YEAR(P67),MONTH(P67),1), SUMIFS($K:$K, $C:$C, C67, $P:$P, ">="&DATE(YEAR(P67),MONTH(P67),1), $P:$P, "<="&EOMONTH(P67,0))>10), _xlfn.TEXTJOIN(", ", TRUE, _xlfn._xlws.FILTER($R:$R, ($C:$C=C67) * ($P:$P>=DATE(YEAR(P67),MONTH(P67),1)) * ($P:$P<=EOMONTH(P67,0)))), "")} | Y67: {=IF(AND(P67<>"", P67>=DATE(YEAR(P67),MONTH(P67),1), SUMIFS($K:$K, $C:$C, C67, $P:$P, ">="&DATE(YEAR(P67),MONTH(P67),1), $P:$P, "<="&EOMONTH(P67,0))>10), _xlfn.TEXTJOIN(", ", TRUE, _xlfn._xlws.FILTER($S:$S, ($C:$C=C67) * ($P:$P>=DATE(YEAR(P67),MONTH(P67),1)) * ($P:$P<=EOMONTH(P67,0)))), "")}
A68: 61 | B68: TEMPOACTIVA | C68: =_xlfn.XLOOKUP(D68,[1]!Data[CEDULA],[1]!Data[Nombre Completo],"No Existe",0,1) -> JESICA PAOLA CAMPO CHAMORRO | D68: 1005649208 | E68: =IFERROR(_xlfn.NUMBERVALUE(Data[[#This Row],[CEDULA ]],",","."),_xlfn.NUMBERVALUE(Data[[#This Row],[CEDULA ]],".",",")) -> 1005649208 | F68: =_xlfn.XLOOKUP(E68,[1]!Data[CEDULA],[1]!Data[CARGO],"No Existe",0,1) -> SUPERNUMERARIO(A) | G68: =_xlfn.XLOOKUP(E68,[1]!Data[CEDULA],[1]!Data[EMPRESA DONDE PRESTA SERVICIO],"No Existe",0,1) -> COMFAMILIAR ATLANTICO | H68: =_xlfn.XLOOKUP(E68,[1]!Data[CEDULA],[1]!Data[UBICACIÓN],"No Existe",0,1) -> SEDE CARIBE | I68: MUJER | J68: =UPPER(TEXT(Data[[#This Row],[F. INICIO]],"mmmm")) -> MAYO | K68: 2 | L68: EPS | M68: ENFERMENDAD GENERAL | N68: =_xlfn.XLOOKUP(D68,[1]!Data[CEDULA],[1]!Data[EPS/SURA],"No Existe",0,1) -> SALUD TOTAL | O68: =YEAR(Data[[#This Row],[F. INICIO]]) -> 2024 | P68: 45442 | Q68: 45443 | R68: A083 | S68: =IF(Data[[#This Row],[TIPO DE INCAPACIDAD]]="LICENCIA DE PATERNIDAD","Licencia de paternidad",IF(Data[[#This Row],[TIPO DE INCAPACIDAD]]="LICENCIA DE LUTO","Licencia de Luto",_xlfn.IFNA(VLOOKUP(R68,'CIE-10 PARA RIPS'!$A$6:B13203,2,0),"No especificado"))) -> Otras enteritis virales | T68: =IF(P68<>"", IF(P68>0, IF(P68<=DATE(YEAR(P68),MONTH(P68),DAY(P68)), IF(P68>=DATE(YEAR(P68),MONTH(P68),1), IF(K68>10, C68, IF(SUMIFS($K:$K, $C:$C, C68, $P:$P, ">="&DATE(YEAR(P68),MONTH(P68),1), $P:$P, "<="&EOMONTH(P68,0))>10, C68, "")), ""))), "") | U68: =IF(AND(P68<>"", P68>=DATE(YEAR(P68),MONTH(P68),1), SUMIFS($K:$K, $C:$C, C68, $P:$P, ">="&DATE(YEAR(P68),MONTH(P68),1), $P:$P, "<="&EOMONTH(P68,0))>10), K68, "") | V68: =IF(AND(P68<>"", P68>=DATE(YEAR(P68),MONTH(P68),1), SUMIFS($K:$K, $C:$C, C68, $P:$P, ">="&DATE(YEAR(P68),MONTH(P68),1), $P:$P, "<="&EOMONTH(P68,0))>10), YEAR(P68), "") | W68: =IF(AND(P68<>"", P68>=DATE(YEAR(P68),MONTH(P68),1), SUMIFS($K:$K, $C:$C, C68, $P:$P, ">="&DATE(YEAR(P68),MONTH(P68),1), $P:$P, "<="&EOMONTH(P68,0))>10), TEXT(P68, "MMMM"), "") | X68: {=IF(AND(P68<>"", P68>=DATE(YEAR(P68),MONTH(P68),1), SUMIFS($K:$K, $C:$C, C68, $P:$P, ">="&DATE(YEAR(P68),MONTH(P68),1), $P:$P, "<="&EOMONTH(P68,0))>10), _xlfn.TEXTJOIN(", ", TRUE, _xlfn._xlws.FILTER($R:$R, ($C:$C=C68) * ($P:$P>=DATE(YEAR(P68),MONTH(P68),1)) * ($P:$P<=EOMONTH(P68,0)))), "")} | Y68: {=IF(AND(P68<>"", P68>=DATE(YEAR(P68),MONTH(P68),1), SUMIFS($K:$K, $C:$C, C68, $P:$P, ">="&DATE(YEAR(P68),MONTH(P68),1), $P:$P, "<="&EOMONTH(P68,0))>10), _xlfn.TEXTJOIN(", ", TRUE, _xlfn._xlws.FILTER($S:$S, ($C:$C=C68) * ($P:$P>=DATE(YEAR(P68),MONTH(P68),1)) * ($P:$P<=EOMONTH(P68,0)))), "")}
A69: 62 | B69: TEMPOACTIVA | C69: =_xlfn.XLOOKUP(D69,[1]!Data[CEDULA],[1]!Data[Nombre Completo],"No Existe",0,1) -> GREIDY DE JESUS ACOSTA CONRADO | D69: 1044428902 | E69: =IFERROR(_xlfn.NUMBERVALUE(Data[[#This Row],[CEDULA ]],",","."),_xlfn.NUMBERVALUE(Data[[#This Row],[CEDULA ]],".",",")) -> 1044428902 | F69: =_xlfn.XLOOKUP(E69,[1]!Data[CEDULA],[1]!Data[CARGO],"No Existe",0,1) -> SUPERNUMERARIO(A) | G69: =_xlfn.XLOOKUP(E69,[1]!Data[CEDULA],[1]!Data[EMPRESA DONDE PRESTA SERVICIO],"No Existe",0,1) -> COMFAMILIAR ATLANTICO | H69: =_xlfn.XLOOKUP(E69,[1]!Data[CEDULA],[1]!Data[UBICACIÓN],"No Existe",0,1) -> SALGARITO | I69: MUJER | J69: =UPPER(TEXT(Data[[#This Row],[F. INICIO]],"mmmm")) -> MAYO | K69: 4 | L69: EPS | M69: ENFERMENDAD GENERAL | N69: =_xlfn.XLOOKUP(D69,[1]!Data[CEDULA],[1]!Data[EPS/SURA],"No Existe",0,1) -> EPS/SURA | O69: =YEAR(Data[[#This Row],[F. INICIO]]) -> 2024 | P69: 45427 | Q69: 45430 | R69: H200 | S69: =IF(Data[[#This Row],[TIPO DE INCAPACIDAD]]="LICENCIA DE PATERNIDAD","Licencia de paternidad",IF(Data[[#This Row],[TIPO DE INCAPACIDAD]]="LICENCIA DE LUTO","Licencia de Luto",_xlfn.IFNA(VLOOKUP(R69,'CIE-10 PARA RIPS'!$A$6:B13210,2,0),"No especificado"))) -> Iridociclitis aguda y subaguda | T69: =IF(P69<>"", IF(P69>0, IF(P69<=DATE(YEAR(P69),MONTH(P69),DAY(P69)), IF(P69>=DATE(YEAR(P69),MONTH(P69),1), IF(K69>10, C69, IF(SUMIFS($K:$K, $C:$C, C69, $P:$P, ">="&DATE(YEAR(P69),MONTH(P69),1), $P:$P, "<="&EOMONTH(P69,0))>10, C69, "")), ""))), "") | U69: =IF(AND(P69<>"", P69>=DATE(YEAR(P69),MONTH(P69),1), SUMIFS($K:$K, $C:$C, C69, $P:$P, ">="&DATE(YEAR(P69),MONTH(P69),1), $P:$P, "<="&EOMONTH(P69,0))>10), K69, "") | V69: =IF(AND(P69<>"", P69>=DATE(YEAR(P69),MONTH(P69),1), SUMIFS($K:$K, $C:$C, C69, $P:$P, ">="&DATE(YEAR(P69),MONTH(P69),1), $P:$P, "<="&EOMONTH(P69,0))>10), YEAR(P69), "") | W69: =IF(AND(P69<>"", P69>=DATE(YEAR(P69),MONTH(P69),1), SUMIFS($K:$K, $C:$C, C69, $P:$P, ">="&DATE(YEAR(P69),MONTH(P69),1), $P:$P, "<="&EOMONTH(P69,0))>10), TEXT(P69, "MMMM"), "") | X69: {=IF(AND(P69<>"", P69>=DATE(YEAR(P69),MONTH(P69),1), SUMIFS($K:$K, $C:$C, C69, $P:$P, ">="&DATE(YEAR(P69),MONTH(P69),1), $P:$P, "<="&EOMONTH(P69,0))>10), _xlfn.TEXTJOIN(", ", TRUE, _xlfn._xlws.FILTER($R:$R, ($C:$C=C69) * ($P:$P>=DATE(YEAR(P69),MONTH(P69),1)) * ($P:$P<=EOMONTH(P69,0)))), "")} | Y69: {=IF(AND(P69<>"", P69>=DATE(YEAR(P69),MONTH(P69),1), SUMIFS($K:$K, $C:$C, C69, $P:$P, ">="&DATE(YEAR(P69),MONTH(P69),1), $P:$P, "<="&EOMONTH(P69,0))>10), _xlfn.TEXTJOIN(", ", TRUE, _xlfn._xlws.FILTER($S:$S, ($C:$C=C69) * ($P:$P>=DATE(YEAR(P69),MONTH(P69),1)) * ($P:$P<=EOMONTH(P69,0)))), "")}
A70: 63 | B70: TEMPOACTIVA | C70: =_xlfn.XLOOKUP(D70,[1]!Data[CEDULA],[1]!Data[Nombre Completo],"No Existe",0,1) -> JUAN HUMBERTO MOLINA JIMENEZ | D70: 1044395070 | E70: =IFERROR(_xlfn.NUMBERVALUE(Data[[#This Row],[CEDULA ]],",","."),_xlfn.NUMBERVALUE(Data[[#This Row],[CEDULA ]],".",",")) -> 1044395070 | F70: =_xlfn.XLOOKUP(E70,[1]!Data[CEDULA],[1]!Data[CARGO],"No Existe",0,1) -> SUPERNUMERARIO(A) | G70: =_xlfn.XLOOKUP(E70,[1]!Data[CEDULA],[1]!Data[EMPRESA DONDE PRESTA SERVICIO],"No Existe",0,1) -> COMFAMILIAR ATLANTICO | H70: =_xlfn.XLOOKUP(E70,[1]!Data[CEDULA],[1]!Data[UBICACIÓN],"No Existe",0,1) -> CENTRO RECREACIONAL TURIPANA | I70: HOMBRE | J70: =UPPER(TEXT(Data[[#This Row],[F. INICIO]],"mmmm")) -> MAYO | K70: 4 | L70: EPS | M70: ENFERMENDAD GENERAL | N70: =_xlfn.XLOOKUP(D70,[1]!Data[CEDULA],[1]!Data[EPS/SURA],"No Existe",0,1) -> SALUD TOTAL | O70: =YEAR(Data[[#This Row],[F. INICIO]]) -> 2024 | P70: 45424 | Q70: 45427 | R70: R509 | S70: =IF(Data[[#This Row],[TIPO DE INCAPACIDAD]]="LICENCIA DE PATERNIDAD","Licencia de paternidad",IF(Data[[#This Row],[TIPO DE INCAPACIDAD]]="LICENCIA DE LUTO","Licencia de Luto",_xlfn.IFNA(VLOOKUP(R70,'CIE-10 PARA RIPS'!$A$6:B13211,2,0),"No especificado"))) -> Fiebre, no especificada | T70: =IF(P70<>"", IF(P70>0, IF(P70<=DATE(YEAR(P70),MONTH(P70),DAY(P70)), IF(P70>=DATE(YEAR(P70),MONTH(P70),1), IF(K70>10, C70, IF(SUMIFS($K:$K, $C:$C, C70, $P:$P, ">="&DATE(YEAR(P70),MONTH(P70),1), $P:$P, "<="&EOMONTH(P70,0))>10, C70, "")), ""))), "") | U70: =IF(AND(P70<>"", P70>=DATE(YEAR(P70),MONTH(P70),1), SUMIFS($K:$K, $C:$C, C70, $P:$P, ">="&DATE(YEAR(P70),MONTH(P70),1), $P:$P, "<="&EOMONTH(P70,0))>10), K70, "") | V70: =IF(AND(P70<>"", P70>=DATE(YEAR(P70),MONTH(P70),1), SUMIFS($K:$K, $C:$C, C70, $P:$P, ">="&DATE(YEAR(P70),MONTH(P70),1), $P:$P, "<="&EOMONTH(P70,0))>10), YEAR(P70), "") | W70: =IF(AND(P70<>"", P70>=DATE(YEAR(P70),MONTH(P70),1), SUMIFS($K:$K, $C:$C, C70, $P:$P, ">="&DATE(YEAR(P70),MONTH(P70),1), $P:$P, "<="&EOMONTH(P70,0))>10), TEXT(P70, "MMMM"), "") | X70: {=IF(AND(P70<>"", P70>=DATE(YEAR(P70),MONTH(P70),1), SUMIFS($K:$K, $C:$C, C70, $P:$P, ">="&DATE(YEAR(P70),MONTH(P70),1), $P:$P, "<="&EOMONTH(P70,0))>10), _xlfn.TEXTJOIN(", ", TRUE, _xlfn._xlws.FILTER($R:$R, ($C:$C=C70) * ($P:$P>=DATE(YEAR(P70),MONTH(P70),1)) * ($P:$P<=EOMONTH(P70,0)))), "")} | Y70: {=IF(AND(P70<>"", P70>=DATE(YEAR(P70),MONTH(P70),1), SUMIFS($K:$K, $C:$C, C70, $P:$P, ">="&DATE(YEAR(P70),MONTH(P70),1), $P:$P, "<="&EOMONTH(P70,0))>10), _xlfn.TEXTJOIN(", ", TRUE, _xlfn._xlws.FILTER($S:$S, ($C:$C=C70) * ($P:$P>=DATE(YEAR(P70),MONTH(P70),1)) * ($P:$P<=EOMONTH(P70,0)))), "")}
